Workbook

Sheet ISM Manu
Z1: https://etfdb.com/etf/XLV/#etf-holdings&sort_name=weight&sort_order=desc&page=1 | AD1: https://money.usnews.com/investing/stocks/metal-fabrication
B2: WIKIPEDIA | C2: 3 | Z2: https://www.nasdaq.com/markets/barchart-sectors.aspx | AD2: https://etfdb.com/etfs/ | AF2: https://etfdb.com/etfs/
B3: Yahoo Finance Screener | C3: 6 | Z3: https://www.barchart.com/stocks/sectors/rankings | AF3: https://www.instituteforsupplymanagement.org/news/content.cfm?ItemNumber=28859
B4: Link(s) | C4: Past __ Mnths | D4: ( + ) Count | E4: Link | F4: Link | G4: Link | H4: Link | I4: Link | J4: Link | K4: Link | L4: Link | M4: Link | N4: Link | O4: Link | P4: Link | Q4: Link | R4: Link | S4: Link | T4: Link | Z4: https://www.macrotrends.net/stocks/sector/2/consumer-discretionary | BO4: =MAX(BO7:BO24) -> 8 | BP4: =MAX(BP7:BP24) -> 5 | BQ4: =MAX(BQ7:BQ24) -> 5 | BR4: =MAX(BR7:BR24) -> 5 | BS4: =MAX(BS7:BS24) -> 5 | BT4: =MAX(BT7:BT24) -> 3 | BU4: =MAX(BU7:BU24) -> 7 | BV4: =MAX(BV7:BV24) -> 8 | ... CD4: =MAX(CD7:CD24) -> 5
B5: Sectors | C5: 3 | E5: 43556 | F5: 43586 | G5: 43617 | H5: 43647 | I5: 43678 | J5: 43709 | K5: 43739 | L5: 43770 | M5: 43800 | N5: 43831 | O5: 43862 | P5: 43891 | Q5: 43922 | R5: 43952 | S5: 43983 | T5: 44013 | U5: 44044 | V5: 44075 | W5: 44105 | X5: 44136 | Y5: 44166 | Z5: 44197 | AA5: 44228 | AB5: 44256 | AC5: 44287 | AD5: 44317 | AE5: 44348 | AF5: 44378 | AG5: 44409 | AH5: 44440 | AI5: 44470 | AJ5: 44501 | AK5: 44531 | AL5: 44562 | AM5: 44593 | AN5: 44621 | AO5: 44652 | AP5: 44682 | AQ5: 44713 | AR5: 44743 | AS5: 44774 | AT5: 44805 | AU5: 44835 | AV5: 44866 | AW5: 44896 | AX5: 44927 | AY5: 44958 | AZ5: 44986 | BA5: 45017 | BB5: 45047 | BC5: 45078 | BD5: 45108 | BE5: 45139 | BF5: 45170 | BG5: 45200 | BH5: 45231 | BI5: 45261 | BJ5: 45292 | BK5: 45323 | BL5: 45352 | BM5: 45383 | BN5: 45413 | BO5: 45444 | BP5: 45474 | BQ5: 45505 | BR5: 45536 | BS5: 45566 | BT5: 45597 | BU5: 45627 | BV5: 45658 | BW5: 45689 | BX5: 45717 | BY5: 45748 | BZ5: 45778 | CA5: 45809 | CB5: 45839 | CC5: 45870 | CD5: 45901 | CE5: 45931
A6: AVERAGE | E6: =AVERAGE(E7:E24) -> 4.5555556 | F6: =AVERAGE(F7:F24) -> 2.6111111 | G6: =AVERAGE(G7:G24) -> 3.5 | H6: =AVERAGE(H7:H24) -> 0 | I6: =AVERAGE(I7:I24) -> 0.94444444 | J6: =AVERAGE(J7:J24) -> -6.3333333 | K6: =AVERAGE(K7:K24) -> -3.5 | L6: =AVERAGE(L7:L24) -> -4.2222222 | ... CE6: =AVERAGE(CE7:CE24) -> -3.1666667
A7: PMI Itself | B7: Apparel, Leather & Allied Products | D7: =IF(COUNTIF(S7:X7,">0")=0,(COUNTIF(S7:X7,"<0")*-1),COUNTIF(S7:X7,">0")) -> 5 | E7: -5 | F7: -6 | G7: -5 | H7: -9 | I7: -7 | J7: -15 | K7: -11 | L7: 5 | M7: 0 | N7: -7 | O7: 0 | P7: 8 | Q7: 0 | R7: 4 | S7: 9 | T7: 6 | U7: 6 | V7: -4 | W7: 15 | X7: 16 | Y7: 16 | Z7: 9 | AA7: 5 | AB7: 13 | AC7: 6 | AD7: 0 | AE7: 0 | AF7: 15 | AG7: 0 | AH7: 11 | AI7: 16 | AJ7: 13 | AK7: 15 | AL7: 14 | AM7: 16 | AN7: 15 | AO7: 17 | AP7: 15 | AQ7: 15 | AR7: 11 | AS7: -6 | AT7: 5 | AU7: 8 | AV7: 6 | AW7: -6 | AX7: -11 | AY7: 4 | AZ7: -5 | BA7: 4 | BB7: -12 | BC7: 0 | BD7: -16 | BE7: -13 | BF7: 0 | BG7: 0 | BH7: -10 | BI7: -15 | BJ7: 4 | BK7: 8 | BL7: 0 | BM7: 0 | BN7: 0 | BO7: 0 | BP7: 0 | BQ7: 0 | BR7: -10 | BS7: 5 | BT7: 0 | BU7: 0 | BV7: 0 | BW7: 0 | BX7: 0 | BY7: 11 | BZ7: 0 | CA7: 9 | CB7: 7 | CC7: 6 | CD7: -10 | CE7: -11
B8: Chemical Products | D8: =IF(COUNTIF(S8:X8,">0")=0,(COUNTIF(S8:X8,"<0")*-1),COUNTIF(S8:X8,">0")) -> 6 | E8: 9 | F8: 4 | G8: 6 | H8: 1 | I8: 1 | J8: 1 | K8: -6 | L8: -2 | M8: -2 | N8: 2 | O8: 1 | P8: 5 | Q8: -1 | R8: -3 | S8: 5 | T8: 7 | U8: 11 | V8: 7 | W8: 6 | X8: 8 | Y8: 7 | Z8: 13 | AA8: 12 | AB8: 5 | AC8: 11 | AD8: 6 | AE8: 12 | AF8: 8 | AG8: 8 | AH8: 12 | AI8: 8 | AJ8: 4 | AK8: 8 | AL8: 3 | AM8: 2 | AN8: 5 | AO8: 5 | AP8: 4 | AQ8: 1 | AR8: -1 | AS8: -3 | AT8: -2 | AU8: -4 | AV8: -6 | AW8: -11 | AX8: -5 | AY8: -6 | AZ8: -4 | BA8: -6 | BB8: -7 | BC8: -8 | BD8: -10 | BE8: -6 | BF8: -2 | BG8: -2 | BH8: -4 | BI8: -1 | BJ8: 1 | BK8: 3 | BL8: 2 | BM8: 2 | BN8: 1 | BO8: 3 | BP8: -2 | BQ8: -2 | BR8: -3 | BS8: -8 | BT8: -9 | BU8: -3 | BV8: 5 | BW8: 4 | BX8: -3 | BY8: 2 | BZ8: -2 | CA8: -3 | CB8: -8 | CC8: -2 | CD8: -6 | CE8: -4
B9: Computer & Electronic Products | D9: =IF(COUNTIF(S9:X9,">0")=0,(COUNTIF(S9:X9,"<0")*-1),COUNTIF(S9:X9,">0")) -> 6 | E9: 3 | F9: 5 | G9: 5 | H9: 4 | I9: 0 | J9: -1 | K9: 1 | L9: 1 | M9: -3 | N9: 5 | O9: 6 | P9: 4 | Q9: -3 | R9: -2 | S9: 7 | T9: 5 | U9: 10 | V9: 2 | W9: 4 | X9: 6 | Y9: 11 | Z9: 1 | AA9: 6 | AB9: 14 | AC9: 8 | AD9: 11 | AE9: 14 | AF9: 13 | AG9: 14 | AH9: 13 | AI9: 9 | AJ9: 10 | AK9: 5 | AL9: 4 | AM9: 8 | AN9: 4 | AO9: 13 | AP9: 11 | AQ9: 12 | AR9: 7 | AS9: 7 | AT9: 2 | AU9: -2 | AV9: -4 | AW9: -5 | AX9: -1 | AY9: -4 | AZ9: -3 | BA9: -3 | BB9: -5 | BC9: -5 | BD9: -11 | BE9: -5 | BF9: -5 | BG9: -7 | BH9: -11 | BI9: -6 | BJ9: -8 | BK9: -4 | BL9: -2 | BM9: 0 | BN9: -4 | BO9: -1 | BP9: -1 | BQ9: 1 | BR9: -1 | BS9: 2 | BT9: 2 | BU9: 0 | BV9: -3 | BW9: -2 | BX9: 5 | BY9: 6 | BZ9: 0 | CA9: 4 | CB9: -4 | CC9: -3 | CD9: -1 | CE9: -1
B10: Electrical Equipment, Appliances & Components | D10: =IF(COUNTIF(S10:X10,">0")=0,(COUNTIF(S10:X10,"<0")*-1),COUNTIF(S10:X10,">0")) -> 6 | E10: 12 | F10: 6 | G10: 2 | H10: -2 | I10: -1 | J10: -12 | K10: -4 | L10: -1 | M10: -6 | N10: -6 | O10: 4 | P10: 0 | Q10: -7 | R10: -4 | S10: 1 | T10: 1 | U10: 3 | V10: 10 | W10: 2 | X10: 12 | Y10: 3 | Z10: 16 | AA10: 15 | AB10: 16 | AC10: 18 | AD10: 10 | AE10: 15 | AF10: 3 | AG10: 11 | AH10: 14 | AI10: 13 | AJ10: 11 | AK10: 7 | AL10: 9 | AM10: 9 | AN10: 12 | AO10: 9 | AP10: 1 | AQ10: 10 | AR10: 1 | AS10: -1 | AT10: 1 | AU10: 1 | AV10: -1 | AW10: -8 | AX10: -9 | AY10: 1 | AZ10: -2 | BA10: -8 | BB10: -4 | BC10: -6 | BD10: -7 | BE10: -7 | BF10: -3 | BG10: -11 | BH10: -12 | BI10: -3 | BJ10: -4 | BK10: -1 | BL10: -4 | BM10: 5 | BN10: 0 | BO10: -2 | BP10: -8 | BQ10: -8 | BR10: -6 | BS10: -7 | BT10: 1 | BU10: 6 | BV10: 1 | BW10: 5 | BX10: 2 | BY10: 8 | BZ10: 3 | CA10: 1 | CB10: -2 | CC10: -4 | CD10: -5 | CE10: -5
B11: Fabricated Metal Products | D11: =IF(COUNTIF(S11:X11,">0")=0,(COUNTIF(S11:X11,"<0")*-1),COUNTIF(S11:X11,">0")) -> 4 | E11: 1 | F11: -1 | G11: -1 | H11: -8 | I11: -6 | J11: -9 | K11: -3 | L11: -9 | M11: -7 | N11: 1 | O11: 3 | P11: -2 | Q11: -11 | R11: -7 | S11: -2 | T11: -1 | U11: 8 | V11: 8 | W11: 14 | X11: 11 | Y11: 13 | Z11: 12 | AA11: 10 | AB11: 11 | AC11: 14 | AD11: 9 | AE11: 11 | AF11: 10 | AG11: 10 | AH11: 5 | AI11: 7 | AJ11: 2 | AK11: 6 | AL11: 5 | AM11: 5 | AN11: 7 | AO11: 3 | AP11: 5 | AQ11: 5 | AR11: -3 | AS11: -2 | AT11: -1 | AU11: -5 | AV11: -8 | AW11: -12 | AX11: -6 | AY11: -3 | AZ11: 4 | BA11: 2 | BB11: 1 | BC11: -3 | BD11: -4 | BE11: -9 | BF11: -7 | BG11: -9 | BH11: -3 | BI11: -7 | BJ11: -7 | BK11: 4 | BL11: 3 | BM11: -2 | BN11: 2 | BO11: -7 | BP11: -6 | BQ11: -7 | BR11: -2 | BS11: -2 | BT11: -6 | BU11: -6 | BV11: -5 | BW11: 2 | BX11: 7 | BY11: -1 | BZ11: 2 | CA11: -1 | CB11: -5 | CC11: -1 | CD11: 2 | CE11: 2
B12: Food, Beverage & Tobacco Products | D12: =IF(COUNTIF(S12:X12,">0")=0,(COUNTIF(S12:X12,"<0")*-1),COUNTIF(S12:X12,">0")) -> 6 | E12: 4 | F12: 3 | G12: 8 | H12: 6 | I12: 7 | J12: 2 | K12: 3 | L12: 4 | M12: 2 | N12: 6 | O12: 7 | P12: 9 | Q12: 1 | R12: 3 | S12: 8 | T12: 9 | U12: 13 | V12: 12 | W12: 12 | X12: 1 | Y12: 2 | Z12: 6 | AA12: 4 | AB12: 10 | AC12: 9 | AD12: 8 | AE12: 5 | AF12: 7 | AG12: 6 | AH12: 6 | AI12: 10 | AJ12: 6 | AK12: 4 | AL12: 8 | AM12: 4 | AN12: 13 | AO12: 12 | AP12: 10 | AQ12: 2 | AR12: -2 | AS12: 1 | AT12: 3 | AU12: -1 | AV12: -3 | AW12: -3 | AX12: -3 | AY12: -7 | AZ12: -6 | BA12: -2 | BB12: -6 | BC12: -2 | BD12: -8 | BE12: 3 | BF12: 4 | BG12: 2 | BH12: 3 | BI12: 0 | BJ12: -5 | BK12: -3 | BL12: 4 | BM12: -3 | BN12: -1 | BO12: -3 | BP12: -5 | BQ12: 2 | BR12: 4 | BS12: 4 | BT12: 3 | BU12: 0 | BV12: -1 | BW12: 6 | BX12: -2 | BY12: -3 | BZ12: -4 | CA12: 2 | CB12: -1 | CC12: 4 | CD12: 0 | CE12: 5
B13: Furniture & Related Products | D13: =IF(COUNTIF(S13:X13,">0")=0,(COUNTIF(S13:X13,"<0")*-1),COUNTIF(S13:X13,">0")) -> 5 | E13: 5 | F13: 10 | G13: 12 | H13: 7 | I13: 8 | J13: -2 | K13: 5 | L13: -11 | M13: -11 | N13: 8 | O13: 13 | P13: -3 | Q13: -14 | R13: 5 | S13: 11 | T13: 12 | U13: -1 | V13: 11 | W13: 9 | X13: 2 | Y13: 15 | Z13: 4 | AA13: 2 | AB13: 12 | AC13: 16 | AD13: 16 | AE13: 17 | AF13: 17 | AG13: 15 | AH13: 17 | AI13: 15 | AJ13: 12 | AK13: 14 | AL13: 13 | AM13: 7 | AN13: 14 | AO13: 6 | AP13: -1 | AQ13: -1 | AR13: -6 | AS13: -5 | AT13: -7 | AU13: -10 | AV13: -7 | AW13: -7 | AX13: -12 | AY13: -10 | AZ13: -12 | BA13: -11 | BB13: 3 | BC13: 0 | BD13: 1 | BE13: -12 | BF13: -10 | BG13: -6 | BH13: -6 | BI13: -4 | BJ13: -9 | BK13: -7 | BL13: -6 | BM13: -5 | BN13: -3 | BO13: 5 | BP13: 2 | BQ13: 3 | BR13: 2 | BS13: 0 | BT13: -5 | BU13: 4 | BV13: -4 | BW13: -5 | BX13: -4 | BY13: -5 | BZ13: 4 | CA13: 5 | CB13: 2 | CC13: -6 | CD13: -7 | CE13: -10
B14: Machinery | D14: =IF(COUNTIF(S14:X14,">0")=0,(COUNTIF(S14:X14,"<0")*-1),COUNTIF(S14:X14,">0")) -> 4 | E14: 6 | F14: 1 | G14: 1 | H14: -1 | I14: 3 | J14: -3 | K14: -7 | L14: -3 | M14: -1 | N14: -1 | O14: 2 | P14: -1 | Q14: -9 | R14: -6 | S14: -1 | T14: -2 | U14: 7 | V14: 4 | W14: 10 | X14: 7 | Y14: 12 | Z14: 15 | AA14: 11 | AB14: 15 | AC14: 15 | AD14: 7 | AE14: 16 | AF14: 11 | AG14: 13 | AH14: 15 | AI14: 12 | AJ14: 9 | AK14: 11 | AL14: 10 | AM14: 12 | AN14: 10 | AO14: 16 | AP14: 13 | AQ14: 11 | AR14: 5 | AS14: 3 | AT14: 8 | AU14: 6 | AV14: -2 | AW14: -4 | AX14: -4 | AY14: -2 | AZ14: 1 | BA14: -5 | BB14: -2 | BC14: -1 | BD14: -1 | BE14: -1 | BF14: -4 | BG14: -10 | BH14: -8 | BI14: -13 | BJ14: -12 | BK14: -6 | BL14: -3 | BM14: -6 | BN14: -5 | BO14: -8 | BP14: -9 | BQ14: -4 | BR14: -4 | BS14: -6 | BT14: -4 | BU14: -4 | BV14: 4 | BW14: -1 | BX14: -1 | BY14: 3 | BZ14: 1 | CA14: 3 | CB14: -7 | CC14: -5 | CD14: -2 | CE14: -3
B15: Miscellaneous Manufacturing | D15: =IF(COUNTIF(S15:X15,">0")=0,(COUNTIF(S15:X15,"<0")*-1),COUNTIF(S15:X15,">0")) -> 6 | E15: 11 | F15: 7 | G15: 3 | H15: -3 | I15: 2 | J15: 3 | K15: -2 | L15: 2 | M15: 1 | N15: 4 | O15: 5 | P15: 2 | Q15: -4 | R15: -5 | S15: 4 | T15: 2 | U15: 4 | V15: 6 | W15: 1 | X15: 4 | Y15: 1 | Z15: 3 | AA15: 3 | AB15: 3 | AC15: 12 | AD15: 5 | AE15: 9 | AF15: 14 | AG15: 7 | AH15: 7 | AI15: 6 | AJ15: 5 | AK15: 9 | AL15: 12 | AM15: 11 | AN15: 11 | AO15: 2 | AP15: 3 | AQ15: 4 | AR15: -4 | AS15: 2 | AT15: 6 | AU15: 3 | AV15: 3 | AW15: -1 | AX15: 2 | AY15: -1 | AZ15: 5 | BA15: -1 | BB15: -1 | BC15: -7 | BD15: -5 | BE15: 1 | BF15: 0 | BG15: -4 | BH15: -5 | BI15: -5 | BJ15: -2 | BK15: 2 | BL15: -1 | BM15: -7 | BN15: 0 | BO15: 2 | BP15: 3 | BQ15: -1 | BR15: 1 | BS15: 1 | BT15: -2 | BU15: 2 | BV15: -7 | BW15: 9 | BX15: 1 | BY15: 4 | BZ15: 0 | CA15: 6 | CB15: 3 | CC15: 2 | CD15: 1 | CE15: -2
B16: Nonmetallic Mineral Products | D16: =IF(COUNTIF(S16:X16,">0")=0,(COUNTIF(S16:X16,"<0")*-1),COUNTIF(S16:X16,">0")) -> 5 | E16: 8 | F16: 2 | G16: 9 | H16: -6 | I16: 4 | J16: -4 | K16: 0 | L16: -4 | M16: -10 | N16: 3 | O16: -1 | P16: 0 | Q16: -10 | R16: 6 | S16: 3 | T16: 0 | U16: 5 | V16: 9 | W16: 13 | X16: 15 | Y16: -1 | Z16: 5 | AA16: 1 | AB16: 4 | AC16: 7 | AD16: 15 | AE16: 8 | AF16: 12 | AG16: -1 | AH16: 2 | AI16: -1 | AJ16: 0 | AK16: 10 | AL16: 11 | AM16: 3 | AN16: 3 | AO16: 14 | AP16: 12 | AQ16: 8 | AR16: 10 | AS16: 10 | AT16: 9 | AU16: 7 | AV16: 5 | AW16: 0 | AX16: -7 | AY16: -9 | AZ16: -11 | BA16: -9 | BB16: 4 | BC16: 3 | BD16: -2 | BE16: -2 | BF16: 5 | BG16: 0 | BH16: 2 | BI16: -12 | BJ16: -10 | BK16: 7 | BL16: 8 | BM16: 9 | BN16: 0 | BO16: 1 | BP16: 1 | BQ16: -10 | BR16: -7 | BS16: -4 | BT16: -3 | BU16: -1 | BV16: -8 | BW16: -3 | BX16: 4 | BY16: 5 | BZ16: 6 | CA16: 7 | CB16: 5 | CC16: 5 | CD16: -3 | CE16: 1
B17: Paper Products | D17: =IF(COUNTIF(S17:X17,">0")=0,(COUNTIF(S17:X17,"<0")*-1),COUNTIF(S17:X17,">0")) -> 5 | E17: 8 | F17: -2 | G17: 4 | H17: -4 | I17: -2 | J17: -10 | K17: -1 | L17: 3 | M17: -5 | N17: 0 | O17: 10 | P17: 6 | Q17: 2 | R17: 2 | S17: 2 | T17: 0 | U17: 2 | V17: 14 | W17: 8 | X17: 5 | Y17: 8 | Z17: 8 | AA17: 13 | AB17: 7 | AC17: 4 | AD17: 2 | AE17: 4 | AF17: 9 | AG17: 2 | AH17: 9 | AI17: 3 | AJ17: 7 | AK17: -1 | AL17: -1 | AM17: 14 | AN17: 6 | AO17: 8 | AP17: 8 | AQ17: -3 | AR17: -5 | AS17: -4 | AT17: -3 | AU17: -8 | AV17: -10 | AW17: -10 | AX17: -13 | AY17: -13 | AZ17: -8 | BA17: 0 | BB17: -10 | BC17: -4 | BD17: -14 | BE17: -4 | BF17: -8 | BG17: -5 | BH17: -14 | BI17: -9 | BJ17: -3 | BK17: -2 | BL17: 7 | BM17: -1 | BN17: 5 | BO17: 4 | BP17: -3 | BQ17: -3 | BR17: -5 | BS17: -1 | BT17: -8 | BU17: 3 | BV17: -2 | BW17: 0 | BX17: -6 | BY17: -4 | BZ17: -7 | CA17: -4 | CB17: -9 | CC17: -10 | CD17: -8 | CE17: -9
B18: Petroleum & Coal Products | D18: =IF(COUNTIF(S18:X18,">0")=0,(COUNTIF(S18:X18,"<0")*-1),COUNTIF(S18:X18,">0")) -> 1 | E18: -2 | F18: -4 | G18: 7 | H18: 2 | I18: 5 | J18: -7 | K18: -5 | L18: -5 | M18: 0 | N18: -5 | O18: -3 | P18: -6 | Q18: -6 | R18: -8 | S18: 0 | T18: 3 | U18: -2 | V18: -2 | W18: 0 | X18: -1 | Y18: 6 | Z18: -1 | AA18: -1 | AB18: 1 | AC18: 3 | AD18: 1 | AE18: 1 | AF18: 1 | AG18: 1 | AH18: 16 | AI18: 5 | AJ18: 3 | AK18: 1 | AL18: 2 | AM18: 1 | AN18: -1 | AO18: -1 | AP18: 7 | AQ18: 3 | AR18: 9 | AS18: 9 | AT18: 0 | AU18: 5 | AV18: 2 | AW18: 1 | AX18: -2 | AY18: 2 | AZ18: 3 | BA18: 3 | BB18: -8 | BC18: 0 | BD18: 2 | BE18: 2 | BF18: 1 | BG18: 0 | BH18: 0 | BI18: -10 | BJ18: -6 | BK18: 0 | BL18: 6 | BM18: 4 | BN18: 6 | BO18: 7 | BP18: 4 | BQ18: 4 | BR18: 5 | BS18: 3 | BT18: 0 | BU18: 0 | BV18: 6 | BW18: 10 | BX18: 8 | BY18: 10 | BZ18: 5 | CA18: 8 | CB18: 0 | CC18: 3 | CD18: 5 | CE18: -6
B19: Plastics & Rubber Products | D19: =IF(COUNTIF(S19:X19,">0")=0,(COUNTIF(S19:X19,"<0")*-1),COUNTIF(S19:X19,">0")) -> 6 | E19: 7 | F19: 9 | G19: 0 | H19: 5 | I19: -3 | J19: =+-8 -> -8 | K19: -8 | L19: -6 | M19: 0 | N19: 0 | O19: 12 | P19: 1 | Q19: -8 | R19: -1 | S19: 6 | T19: 8 | U19: 14 | V19: 5 | W19: 11 | X19: 10 | Y19: 9 | Z19: 11 | AA19: 7 | AB19: 8 | AC19: 10 | AD19: 14 | AE19: 13 | AF19: 5 | AG19: 9 | AH19: 1 | AI19: 4 | AJ19: 8 | AK19: 12 | AL19: 1 | AM19: 6 | AN19: 1 | AO19: 15 | AP19: 6 | AQ19: 7 | AR19: 2 | AS19: 5 | AT19: 7 | AU19: 2 | AV19: -5 | AW19: -9 | AX19: -10 | AY19: -8 | AZ19: -9 | BA19: -7 | BB19: -3 | BC19: -11 | BD19: -15 | BE19: -11 | BF19: -9 | BG19: 1 | BH19: -1 | BI19: -14 | BJ19: -11 | BK19: 5 | BL19: -5 | BM19: 1 | BN19: -6 | BO19: -4 | BP19: -10 | BQ19: -9 | BR19: -12 | BS19: -3 | BT19: -10 | BU19: 1 | BV19: 2 | BW19: 3 | BX19: -5 | BY19: 9 | BZ19: 7 | CA19: 0 | CB19: 6 | CC19: -8 | CD19: -9 | CE19: 3
B20: Primary Metals | D20: =IF(COUNTIF(S20:X20,">0")=0,(COUNTIF(S20:X20,"<0")*-1),COUNTIF(S20:X20,">0")) -> 4 | E20: -4 | F20: -5 | G20: -4 | H20: -7 | I20: -4 | J20: -6 | K20: -12 | L20: -7 | M20: -4 | N20: -2 | O20: 8 | P20: 3 | Q20: -2 | R20: -10 | S20: -3 | T20: 4 | U20: 9 | V20: -1 | W20: 5 | X20: 9 | Y20: 5 | Z20: 14 | AA20: 14 | AB20: 9 | AC20: 13 | AD20: 12 | AE20: 6 | AF20: 6 | AG20: 12 | AH20: 3 | AI20: 2 | AJ20: -1 | AK20: 2 | AL20: 6 | AM20: 10 | AN20: 2 | AO20: 7 | AP20: 2 | AQ20: 9 | AR20: 3 | AS20: 4 | AT20: 0 | AU20: -3 | AV20: 4 | AW20: 2 | AX20: -8 | AY20: -5 | AZ20: 2 | BA20: -4 | BB20: -13 | BC20: 2 | BD20: -9 | BE20: -10 | BF20: 2 | BG20: -3 | BH20: -7 | BI20: 1 | BJ20: -1 | BK20: 6 | BL20: 5 | BM20: 7 | BN20: 3 | BO20: 6 | BP20: -11 | BQ20: 5 | BR20: -9 | BS20: -5 | BT20: -1 | BU20: 7 | BV20: 7 | BW20: 8 | BX20: 6 | BY20: 1 | BZ20: -1 | CA20: 0 | CB20: 1 | CC20: 1 | CD20: 4 | CE20: 6
B21: Printing & Related Support Activities | D21: =IF(COUNTIF(S21:X21,">0")=0,(COUNTIF(S21:X21,"<0")*-1),COUNTIF(S21:X21,">0")) -> 2 | E21: 10 | F21: 11 | G21: 11 | H21: 8 | I21: 0 | J21: -14 | K21: 4 | L21: -12 | M21: -9 | N21: -8 | O21: 11 | P21: 10 | Q21: -15 | R21: -11 | S21: 10 | T21: 10 | U21: -3 | V21: -3 | W21: -1 | X21: -2 | Y21: -2 | Z21: -2 | AA21: -2 | AB21: 2 | AC21: 2 | AD21: -1 | AE21: 3 | AF21: 16 | AG21: 3 | AH21: 8 | AI21: 11 | AJ21: -2 | AK21: -2 | AL21: 0 | AM21: 0 | AN21: 0 | AO21: 10 | AP21: 14 | AQ21: 13 | AR21: 8 | AS21: 6 | AT21: -4 | AU21: -6 | AV21: -12 | AW21: 0 | AX21: -14 | AY21: -14 | AZ21: 6 | BA21: 5 | BB21: -9 | BC21: 4 | BD21: -6 | BE21: 5 | BF21: -11 | BG21: -13 | BH21: -13 | BI21: -16 | BJ21: 0 | BK21: 0 | BL21: 0 | BM21: 8 | BN21: 7 | BO21: 8 | BP21: 5 | BQ21: -11 | BR21: -13 | BS21: -10 | BT21: -11 | BU21: -5 | BV21: 0 | BW21: 0 | BX21: 0 | BY21: 0 | BZ21: -5 | CA21: 0 | CB21: -10 | CC21: 0 | CD21: 0 | CE21: -8
B22: Textile Mills | D22: =IF(COUNTIF(S22:X22,">0")=0,(COUNTIF(S22:X22,"<0")*-1),COUNTIF(S22:X22,">0")) -> 5 | E22: 13 | F22: 10 | G22: 10 | H22: 3 | I22: 9 | J22: -11 | K22: -10 | L22: -10 | M22: 3 | N22: -4 | O22: 9 | P22: -5 | Q22: -12 | R22: 0 | S22: 13 | T22: 11 | U22: 12 | V22: 3 | W22: -2 | X22: 14 | Y22: 4 | Z22: 2 | AA22: 16 | AB22: 17 | AC22: 17 | AD22: 13 | AE22: 7 | AF22: -1 | AG22: -2 | AH22: 10 | AI22: 14 | AJ22: 0 | AK22: 13 | AL22: 0 | AM22: 15 | AN22: 9 | AO22: 4 | AP22: 0 | AQ22: 14 | AR22: 4 | AS22: 0 | AT22: -6 | AU22: -7 | AV22: -9 | AW22: 0 | AX22: 0 | AY22: -11 | AZ22: -10 | BA22: 0 | BB22: -11 | BC22: -9 | BD22: -13 | BE22: -8 | BF22: 3 | BG22: -12 | BH22: -9 | BI22: -11 | BJ22: 3 | BK22: 0 | BL22: 9 | BM22: 6 | BN22: 4 | BO22: -9 | BP22: 0 | BQ22: -12 | BR22: 3 | BS22: -11 | BT22: 0 | BU22: -7 | BV22: 8 | BW22: -4 | BX22: 9 | BY22: 7 | BZ22: 0 | CA22: -6 | CB22: 4 | CC22: 7 | CD22: 3 | CE22: -12
B23: Transportation Equipment | D23: =IF(COUNTIF(S23:X23,">0")=0,(COUNTIF(S23:X23,"<0")*-1),COUNTIF(S23:X23,">0")) -> 4 | E23: -1 | F23: 0 | G23: -2 | H23: -5 | I23: -5 | J23: -5 | K23: -9 | L23: -8 | M23: -8 | N23: -3 | O23: -2 | P23: -4 | Q23: -13 | R23: -9 | S23: -4 | T23: -3 | U23: 1 | V23: 1 | W23: 3 | X23: 3 | Y23: 10 | Z23: 10 | AA23: 9 | AB23: 6 | AC23: 5 | AD23: 4 | AE23: 10 | AF23: 4 | AG23: 5 | AH23: 4 | AI23: 1 | AJ23: 1 | AK23: 3 | AL23: 7 | AM23: 13 | AN23: 8 | AO23: 11 | AP23: 9 | AQ23: 6 | AR23: 6 | AS23: 8 | AT23: 4 | AU23: 4 | AV23: 1 | AW23: -2 | AX23: 1 | AY23: 3 | AZ23: -1 | BA23: 1 | BB23: 2 | BC23: 1 | BD23: -3 | BE23: 4 | BF23: -1 | BG23: -1 | BH23: 1 | BI23: -2 | BJ23: 2 | BK23: 1 | BL23: 1 | BM23: 3 | BN23: -2 | BO23: -5 | BP23: -7 | BQ23: -6 | BR23: -8 | BS23: -9 | BT23: -7 | BU23: -2 | BV23: 3 | BW23: 1 | BX23: 3 | BY23: -2 | BZ23: -3 | CA23: -2 | CB23: -3 | CC23: -7 | CD23: -4 | CE23: 4
B24: Wood Products | D24: =IF(COUNTIF(S24:X24,">0")=0,(COUNTIF(S24:X24,"<0")*-1),COUNTIF(S24:X24,">0")) -> 6 | E24: -3 | F24: -3 | G24: -3 | H24: 9 | I24: 6 | J24: -13 | K24: 2 | L24: -13 | M24: -12 | N24: 7 | O24: 14 | P24: 7 | Q24: -5 | R24: 1 | S24: 12 | T24: 13 | U24: 15 | V24: 13 | W24: 7 | X24: 13 | Y24: 14 | Z24: 7 | AA24: 8 | AB24: 0 | AC24: 1 | AD24: 3 | AE24: 2 | AF24: 2 | AG24: 4 | AH24: -1 | AI24: -2 | AJ24: 0 | AK24: -3 | AL24: 0 | AM24: -1 | AN24: -2 | AO24: 1 | AP24: 0 | AQ24: -2 | AR24: -7 | AS24: -7 | AT24: -5 | AU24: -9 | AV24: -11 | AW24: -13 | AX24: -15 | AY24: -12 | AZ24: -7 | BA24: -10 | BB24: -14 | BC24: -10 | BD24: -12 | BE24: -3 | BF24: -6 | BG24: -8 | BH24: -2 | BI24: -8 | BJ24: -13 | BK24: -5 | BL24: 0 | BM24: -4 | BN24: -7 | BO24: -6 | BP24: -4 | BQ24: -5 | BR24: -11 | BS24: 0 | BT24: 0 | BU24: 5 | BV24: -6 | BW24: 7 | BX24: -7 | BY24: -6 | BZ24: -6 | CA24: -5 | CB24: -6 | CC24: -9 | CD24: -11 | CE24: -7
B25: PMI Rank | H25: =AVERAGE(H26:H43) -> -1.5 | I25: =AVERAGE(I26:I43) -> -3.3333333 | J25: =AVERAGE(J26:J43) -> -3.3333333 | K25: =AVERAGE(K26:K43) -> 9.5 | L25: =AVERAGE(L26:L43) -> 9.5 | M25: =AVERAGE(M26:M43) -> 9.5 | N25: =AVERAGE(N26:N43) -> 9.5 | O25: =AVERAGE(O26:O43) -> 9.5 | P25: =AVERAGE(P26:P43) -> 9.5
A26: PMI Rank | B26: Apparel, Leather & Allied Products | D26: =SUM(S26:X26) -> 71 | G26: -6 | H26: -10 | I26: -11 | J26: -11 | K26: =_xlfn.RANK.AVG(K7,K$7:K$24,1) -> 2 | L26: =_xlfn.RANK.AVG(L7,L$7:L$24,1) -> 18 | M26: =_xlfn.RANK.AVG(M7,M$7:M$24,1) -> 14 | N26: =_xlfn.RANK.AVG(N7,N$7:N$24,1) -> 2 | O26: =_xlfn.RANK.AVG(O7,O$7:O$24,1) -> 4 | P26: =_xlfn.RANK.AVG(P7,P$7:P$24,1) -> 16 | Q26: =_xlfn.RANK.AVG(Q7,Q$7:Q$24,1) -> 16 | R26: =_xlfn.RANK.AVG(R7,R$7:R$24,1) -> 16 | ... T26: =_xlfn.RANK.AVG(T7,T$7:T$24,1) -> 11 | U26: =_xlfn.RANK.AVG(U7,$U$7:$U$24,1) -> 9 | V26: =_xlfn.RANK.AVG(V7,$V$7:$V$24,1) -> 1 | W26: =_xlfn.RANK.AVG(W7,W$7:W$24,1) -> 18 | X26: =_xlfn.RANK.AVG(X7,X$7:X$24,1) -> 18 | Y26: =_xlfn.RANK.AVG(Y7,Y$7:Y$24,1) -> 18 | Z26: =_xlfn.RANK.AVG(Z7,Z$7:Z$24,1) -> 11 | AA26: =_xlfn.RANK.AVG(AA7,AA$7:AA$24,1) -> 7 | AB26: =_xlfn.RANK.AVG(AB7,AB$7:AB$24,1) -> 14 | AC26: =_xlfn.RANK.AVG(AC7,AC$7:AC$24,1) -> 6 | AD26: =_xlfn.RANK.AVG(AD7,AD$7:AD$24,1) -> 2 | ... CE26: =_xlfn.RANK.AVG(CE7,CE$7:CE$24,1) -> 2
B27: Chemical Products | D27: =SUM(S27:X27) -> 66 | G27: 6 | H27: 2 | I27: 1 | J27: 1 | K27: =_xlfn.RANK.AVG(K8,K$7:K$24,1) -> 7 | L27: =_xlfn.RANK.AVG(L8,L$7:L$24,1) -> 12 | M27: =_xlfn.RANK.AVG(M8,M$7:M$24,1) -> 11 | N27: =_xlfn.RANK.AVG(N8,N$7:N$24,1) -> 12 | O27: =_xlfn.RANK.AVG(O8,O$7:O$24,1) -> 5 | P27: =_xlfn.RANK.AVG(P8,P$7:P$24,1) -> 13 | Q27: =_xlfn.RANK.AVG(Q8,Q$7:Q$24,1) -> 15 | R27: =_xlfn.RANK.AVG(R8,R$7:R$24,1) -> 9 | ... T27: =_xlfn.RANK.AVG(T8,T$7:T$24,1) -> 12 | U27: =_xlfn.RANK.AVG(U8,$U$7:$U$24,1) -> 14 | V27: =_xlfn.RANK.AVG(V8,$V$7:$V$24,1) -> 11 | W27: =_xlfn.RANK.AVG(W8,W$7:W$24,1) -> 9 | X27: =_xlfn.RANK.AVG(X8,X$7:X$24,1) -> 10 | Y27: =_xlfn.RANK.AVG(Y8,Y$7:Y$24,1) -> 9 | Z27: =_xlfn.RANK.AVG(Z8,Z$7:Z$24,1) -> 15 | AA27: =_xlfn.RANK.AVG(AA8,AA$7:AA$24,1) -> 14 | AB27: =_xlfn.RANK.AVG(AB8,AB$7:AB$24,1) -> 6 | AC27: =_xlfn.RANK.AVG(AC8,AC$7:AC$24,1) -> 11 | AD27: =_xlfn.RANK.AVG(AD8,AD$7:AD$24,1) -> 8 | ... CE27: =_xlfn.RANK.AVG(CE8,CE$7:CE$24,1) -> 9
B28: Computer & Electronic Products | D28: =SUM(S28:X28) -> 56 | G28: 1 | H28: 1 | I28: -1 | J28: -3 | K28: =_xlfn.RANK.AVG(K9,K$7:K$24,1) -> 14 | L28: =_xlfn.RANK.AVG(L9,L$7:L$24,1) -> 14 | M28: =_xlfn.RANK.AVG(M9,M$7:M$24,1) -> 10 | N28: =_xlfn.RANK.AVG(N9,N$7:N$24,1) -> 15 | O28: =_xlfn.RANK.AVG(O9,O$7:O$24,1) -> 10 | P28: =_xlfn.RANK.AVG(P9,P$7:P$24,1) -> 12 | Q28: =_xlfn.RANK.AVG(Q9,Q$7:Q$24,1) -> 13 | R28: =_xlfn.RANK.AVG(R9,R$7:R$24,1) -> 10 | ... T28: =_xlfn.RANK.AVG(T9,T$7:T$24,1) -> 10 | U28: =_xlfn.RANK.AVG(U9,$U$7:$U$24,1) -> 13 | V28: =_xlfn.RANK.AVG(V9,$V$7:$V$24,1) -> 6 | W28: =_xlfn.RANK.AVG(W9,W$7:W$24,1) -> 7 | X28: =_xlfn.RANK.AVG(X9,X$7:X$24,1) -> 8 | Y28: =_xlfn.RANK.AVG(Y9,Y$7:Y$24,1) -> 13 | Z28: =_xlfn.RANK.AVG(Z9,Z$7:Z$24,1) -> 3 | AA28: =_xlfn.RANK.AVG(AA9,AA$7:AA$24,1) -> 8 | AB28: =_xlfn.RANK.AVG(AB9,AB$7:AB$24,1) -> 15 | AC28: =_xlfn.RANK.AVG(AC9,AC$7:AC$24,1) -> 8 | AD28: =_xlfn.RANK.AVG(AD9,AD$7:AD$24,1) -> 13 | ... CE28: =_xlfn.RANK.AVG(CE9,CE$7:CE$24,1) -> 12
B29: Electrical Equipment, Appliances & Components | D29: =SUM(S29:X29) -> 51 | G29: 0 | H29: -6 | I29: 0 | J29: -8 | K29: =_xlfn.RANK.AVG(K10,K$7:K$24,1) -> 9 | L29: =_xlfn.RANK.AVG(L10,L$7:L$24,1) -> 13 | M29: =_xlfn.RANK.AVG(M10,M$7:M$24,1) -> 7 | N29: =_xlfn.RANK.AVG(N10,N$7:N$24,1) -> 3 | O29: =_xlfn.RANK.AVG(O10,O$7:O$24,1) -> 8 | P29: =_xlfn.RANK.AVG(P10,P$7:P$24,1) -> 7.5 | Q29: =_xlfn.RANK.AVG(Q10,Q$7:Q$24,1) -> 9 | R29: =_xlfn.RANK.AVG(R10,R$7:R$24,1) -> 8 | ... T29: =_xlfn.RANK.AVG(T10,T$7:T$24,1) -> 6 | U29: =_xlfn.RANK.AVG(U10,$U$7:$U$24,1) -> 6 | V29: =_xlfn.RANK.AVG(V10,$V$7:$V$24,1) -> 14 | W29: =_xlfn.RANK.AVG(W10,W$7:W$24,1) -> 5 | X29: =_xlfn.RANK.AVG(X10,X$7:X$24,1) -> 14 | Y29: =_xlfn.RANK.AVG(Y10,Y$7:Y$24,1) -> 5 | Z29: =_xlfn.RANK.AVG(Z10,Z$7:Z$24,1) -> 18 | AA29: =_xlfn.RANK.AVG(AA10,AA$7:AA$24,1) -> 17 | AB29: =_xlfn.RANK.AVG(AB10,AB$7:AB$24,1) -> 17 | AC29: =_xlfn.RANK.AVG(AC10,AC$7:AC$24,1) -> 18 | AD29: =_xlfn.RANK.AVG(AD10,AD$7:AD$24,1) -> 12 | ... CE29: =_xlfn.RANK.AVG(CE10,CE$7:CE$24,1) -> 8
B30: Fabricated Metal Products | D30: =SUM(S30:X30) -> 59 | G30: -1 | H30: -7 | I30: -6 | J30: -2 | K30: =_xlfn.RANK.AVG(K11,K$7:K$24,1) -> 10 | L30: =_xlfn.RANK.AVG(L11,L$7:L$24,1) -> 5 | M30: =_xlfn.RANK.AVG(M11,M$7:M$24,1) -> 6 | N30: =_xlfn.RANK.AVG(N11,N$7:N$24,1) -> 11 | O30: =_xlfn.RANK.AVG(O11,O$7:O$24,1) -> 7 | P30: =_xlfn.RANK.AVG(P11,P$7:P$24,1) -> 5 | Q30: =_xlfn.RANK.AVG(Q11,Q$7:Q$24,1) -> 5 | R30: =_xlfn.RANK.AVG(R11,R$7:R$24,1) -> 5 | ... T30: =_xlfn.RANK.AVG(T11,T$7:T$24,1) -> 3 | U30: =_xlfn.RANK.AVG(U11,$U$7:$U$24,1) -> 11 | V30: =_xlfn.RANK.AVG(V11,$V$7:$V$24,1) -> 12 | W30: =_xlfn.RANK.AVG(W11,W$7:W$24,1) -> 17 | X30: =_xlfn.RANK.AVG(X11,X$7:X$24,1) -> 13 | Y30: =_xlfn.RANK.AVG(Y11,Y$7:Y$24,1) -> 15 | Z30: =_xlfn.RANK.AVG(Z11,Z$7:Z$24,1) -> 14 | AA30: =_xlfn.RANK.AVG(AA11,AA$7:AA$24,1) -> 12 | AB30: =_xlfn.RANK.AVG(AB11,AB$7:AB$24,1) -> 12 | AC30: =_xlfn.RANK.AVG(AC11,AC$7:AC$24,1) -> 14 | AD30: =_xlfn.RANK.AVG(AD11,AD$7:AD$24,1) -> 11 | ... CE30: =_xlfn.RANK.AVG(CE11,CE$7:CE$24,1) -> 14
B31: Food, Beverage & Tobacco Products | D31: =SUM(S31:X31) -> 77 | G31: 5 | H31: 4 | I31: 0 | J31: 2 | K31: =_xlfn.RANK.AVG(K12,K$7:K$24,1) -> 16 | L31: =_xlfn.RANK.AVG(L12,L$7:L$24,1) -> 17 | M31: =_xlfn.RANK.AVG(M12,M$7:M$24,1) -> 17 | N31: =_xlfn.RANK.AVG(N12,N$7:N$24,1) -> 16 | O31: =_xlfn.RANK.AVG(O12,O$7:O$24,1) -> 11 | P31: =_xlfn.RANK.AVG(P12,P$7:P$24,1) -> 17 | Q31: =_xlfn.RANK.AVG(Q12,Q$7:Q$24,1) -> 17 | R31: =_xlfn.RANK.AVG(R12,R$7:R$24,1) -> 15 | ... T31: =_xlfn.RANK.AVG(T12,T$7:T$24,1) -> 14 | U31: =_xlfn.RANK.AVG(U12,$U$7:$U$24,1) -> 16 | V31: =_xlfn.RANK.AVG(V12,$V$7:$V$24,1) -> 16 | W31: =_xlfn.RANK.AVG(W12,W$7:W$24,1) -> 15 | X31: =_xlfn.RANK.AVG(X12,X$7:X$24,1) -> 3 | Y31: =_xlfn.RANK.AVG(Y12,Y$7:Y$24,1) -> 4 | Z31: =_xlfn.RANK.AVG(Z12,Z$7:Z$24,1) -> 8 | AA31: =_xlfn.RANK.AVG(AA12,AA$7:AA$24,1) -> 6 | AB31: =_xlfn.RANK.AVG(AB12,AB$7:AB$24,1) -> 11 | AC31: =_xlfn.RANK.AVG(AC12,AC$7:AC$24,1) -> 9 | AD31: =_xlfn.RANK.AVG(AD12,AD$7:AD$24,1) -> 10 | ... CE31: =_xlfn.RANK.AVG(CE12,CE$7:CE$24,1) -> 17
B32: Furniture & Related Products | D32: =SUM(S32:X32) -> 67 | G32: 10 | H32: 7 | I32: 0 | J32: 0 | K32: =_xlfn.RANK.AVG(K13,K$7:K$24,1) -> 18 | L32: =_xlfn.RANK.AVG(L13,L$7:L$24,1) -> 3 | M32: =_xlfn.RANK.AVG(M13,M$7:M$24,1) -> 2 | N32: =_xlfn.RANK.AVG(N13,N$7:N$24,1) -> 18 | O32: =_xlfn.RANK.AVG(O13,O$7:O$24,1) -> 17 | P32: =_xlfn.RANK.AVG(P13,P$7:P$24,1) -> 4 | Q32: =_xlfn.RANK.AVG(Q13,Q$7:Q$24,1) -> 2 | R32: =_xlfn.RANK.AVG(R13,R$7:R$24,1) -> 17 | ... T32: =_xlfn.RANK.AVG(T13,T$7:T$24,1) -> 17 | U32: =_xlfn.RANK.AVG(U13,$U$7:$U$24,1) -> 3 | V32: =_xlfn.RANK.AVG(V13,$V$7:$V$24,1) -> 15 | W32: =_xlfn.RANK.AVG(W13,W$7:W$24,1) -> 12 | X32: =_xlfn.RANK.AVG(X13,X$7:X$24,1) -> 4 | Y32: =_xlfn.RANK.AVG(Y13,Y$7:Y$24,1) -> 17 | Z32: =_xlfn.RANK.AVG(Z13,Z$7:Z$24,1) -> 6 | AA32: =_xlfn.RANK.AVG(AA13,AA$7:AA$24,1) -> 4 | AB32: =_xlfn.RANK.AVG(AB13,AB$7:AB$24,1) -> 13 | AC32: =_xlfn.RANK.AVG(AC13,AC$7:AC$24,1) -> 16 | AD32: =_xlfn.RANK.AVG(AD13,AD$7:AD$24,1) -> 18 | ... CE32: =_xlfn.RANK.AVG(CE13,CE$7:CE$24,1) -> 3
B33: Machinery | D33: =SUM(S33:X33) -> 46 | G33: -2 | H33: 0 | I33: 2 | J33: 0 | K33: =_xlfn.RANK.AVG(K14,K$7:K$24,1) -> 6 | L33: =_xlfn.RANK.AVG(L14,L$7:L$24,1) -> 11 | M33: =_xlfn.RANK.AVG(M14,M$7:M$24,1) -> 12 | N33: =_xlfn.RANK.AVG(N14,N$7:N$24,1) -> 8 | O33: =_xlfn.RANK.AVG(O14,O$7:O$24,1) -> 6 | P33: =_xlfn.RANK.AVG(P14,P$7:P$24,1) -> 6 | Q33: =_xlfn.RANK.AVG(Q14,Q$7:Q$24,1) -> 7 | R33: =_xlfn.RANK.AVG(R14,R$7:R$24,1) -> 6 | ... T33: =_xlfn.RANK.AVG(T14,T$7:T$24,1) -> 2 | U33: =_xlfn.RANK.AVG(U14,$U$7:$U$24,1) -> 10 | V33: =_xlfn.RANK.AVG(V14,$V$7:$V$24,1) -> 8 | W33: =_xlfn.RANK.AVG(W14,W$7:W$24,1) -> 13 | X33: =_xlfn.RANK.AVG(X14,X$7:X$24,1) -> 9 | Y33: =_xlfn.RANK.AVG(Y14,Y$7:Y$24,1) -> 14 | Z33: =_xlfn.RANK.AVG(Z14,Z$7:Z$24,1) -> 17 | AA33: =_xlfn.RANK.AVG(AA14,AA$7:AA$24,1) -> 13 | AB33: =_xlfn.RANK.AVG(AB14,AB$7:AB$24,1) -> 16 | AC33: =_xlfn.RANK.AVG(AC14,AC$7:AC$24,1) -> 15 | AD33: =_xlfn.RANK.AVG(AD14,AD$7:AD$24,1) -> 9 | ... CE33: =_xlfn.RANK.AVG(CE14,CE$7:CE$24,1) -> 10
B34: Miscellaneous Manufacturing | D34: =SUM(S34:X34) -> 43 | G34: 3 | H34: -3 | I34: -2 | J34: 3 | K34: =_xlfn.RANK.AVG(K15,K$7:K$24,1) -> 11 | L34: =_xlfn.RANK.AVG(L15,L$7:L$24,1) -> 15 | M34: =_xlfn.RANK.AVG(M15,M$7:M$24,1) -> 16 | N34: =_xlfn.RANK.AVG(N15,N$7:N$24,1) -> 14 | O34: =_xlfn.RANK.AVG(O15,O$7:O$24,1) -> 9 | P34: =_xlfn.RANK.AVG(P15,P$7:P$24,1) -> 10 | Q34: =_xlfn.RANK.AVG(Q15,Q$7:Q$24,1) -> 12 | R34: =_xlfn.RANK.AVG(R15,R$7:R$24,1) -> 7 | ... T34: =_xlfn.RANK.AVG(T15,T$7:T$24,1) -> 7 | U34: =_xlfn.RANK.AVG(U15,$U$7:$U$24,1) -> 7 | V34: =_xlfn.RANK.AVG(V15,$V$7:$V$24,1) -> 10 | W34: =_xlfn.RANK.AVG(W15,W$7:W$24,1) -> 4 | X34: =_xlfn.RANK.AVG(X15,X$7:X$24,1) -> 6 | Y34: =_xlfn.RANK.AVG(Y15,Y$7:Y$24,1) -> 3 | Z34: =_xlfn.RANK.AVG(Z15,Z$7:Z$24,1) -> 5 | AA34: =_xlfn.RANK.AVG(AA15,AA$7:AA$24,1) -> 5 | AB34: =_xlfn.RANK.AVG(AB15,AB$7:AB$24,1) -> 4 | AC34: =_xlfn.RANK.AVG(AC15,AC$7:AC$24,1) -> 12 | AD34: =_xlfn.RANK.AVG(AD15,AD$7:AD$24,1) -> 7 | ... CE34: =_xlfn.RANK.AVG(CE15,CE$7:CE$24,1) -> 11
B35: Nonmetallic Mineral Products | D35: =SUM(S35:X35) -> 66.5 | G35: 9 | H35: -4 | I35: 3 | J35: -7 | K35: =_xlfn.RANK.AVG(K16,K$7:K$24,1) -> 13 | L35: =_xlfn.RANK.AVG(L16,L$7:L$24,1) -> 10 | M35: =_xlfn.RANK.AVG(M16,M$7:M$24,1) -> 3 | N35: =_xlfn.RANK.AVG(N16,N$7:N$24,1) -> 13 | O35: =_xlfn.RANK.AVG(O16,O$7:O$24,1) -> 3 | P35: =_xlfn.RANK.AVG(P16,P$7:P$24,1) -> 7.5 | Q35: =_xlfn.RANK.AVG(Q16,Q$7:Q$24,1) -> 6 | R35: =_xlfn.RANK.AVG(R16,R$7:R$24,1) -> 18 | ... T35: =_xlfn.RANK.AVG(T16,T$7:T$24,1) -> 4.5 | U35: =_xlfn.RANK.AVG(U16,$U$7:$U$24,1) -> 8 | V35: =_xlfn.RANK.AVG(V16,$V$7:$V$24,1) -> 13 | W35: =_xlfn.RANK.AVG(W16,W$7:W$24,1) -> 16 | X35: =_xlfn.RANK.AVG(X16,X$7:X$24,1) -> 17 | Y35: =_xlfn.RANK.AVG(Y16,Y$7:Y$24,1) -> 2 | Z35: =_xlfn.RANK.AVG(Z16,Z$7:Z$24,1) -> 7 | AA35: =_xlfn.RANK.AVG(AA16,AA$7:AA$24,1) -> 3 | AB35: =_xlfn.RANK.AVG(AB16,AB$7:AB$24,1) -> 5 | AC35: =_xlfn.RANK.AVG(AC16,AC$7:AC$24,1) -> 7 | AD35: =_xlfn.RANK.AVG(AD16,AD$7:AD$24,1) -> 17 | ... CE35: =_xlfn.RANK.AVG(CE16,CE$7:CE$24,1) -> 13
B36: Paper Products | D36: =SUM(S36:X36) -> 52.5 | G36: 2 | H36: -2 | I36: -10 | J36: -4 | K36: =_xlfn.RANK.AVG(K17,K$7:K$24,1) -> 12 | L36: =_xlfn.RANK.AVG(L17,L$7:L$24,1) -> 16 | M36: =_xlfn.RANK.AVG(M17,M$7:M$24,1) -> 8 | N36: =_xlfn.RANK.AVG(N17,N$7:N$24,1) -> 9.5 | O36: =_xlfn.RANK.AVG(O17,O$7:O$24,1) -> 14 | P36: =_xlfn.RANK.AVG(P17,P$7:P$24,1) -> 14 | Q36: =_xlfn.RANK.AVG(Q17,Q$7:Q$24,1) -> 18 | R36: =_xlfn.RANK.AVG(R17,R$7:R$24,1) -> 14 | ... T36: =_xlfn.RANK.AVG(T17,T$7:T$24,1) -> 4.5 | U36: =_xlfn.RANK.AVG(U17,$U$7:$U$24,1) -> 5 | V36: =_xlfn.RANK.AVG(V17,$V$7:$V$24,1) -> 18 | W36: =_xlfn.RANK.AVG(W17,W$7:W$24,1) -> 11 | X36: =_xlfn.RANK.AVG(X17,X$7:X$24,1) -> 7 | Y36: =_xlfn.RANK.AVG(Y17,Y$7:Y$24,1) -> 10 | Z36: =_xlfn.RANK.AVG(Z17,Z$7:Z$24,1) -> 10 | AA36: =_xlfn.RANK.AVG(AA17,AA$7:AA$24,1) -> 15 | AB36: =_xlfn.RANK.AVG(AB17,AB$7:AB$24,1) -> 8 | AC36: =_xlfn.RANK.AVG(AC17,AC$7:AC$24,1) -> 4 | AD36: =_xlfn.RANK.AVG(AD17,AD$7:AD$24,1) -> 4 | ... CE36: =_xlfn.RANK.AVG(CE17,CE$7:CE$24,1) -> 4
B37: Petroleum & Coal Products | D37: =SUM(S37:X37) -> 23 | G37: 0 | H37: -8 | I37: -5 | J37: -6 | K37: =_xlfn.RANK.AVG(K18,K$7:K$24,1) -> 8 | L37: =_xlfn.RANK.AVG(L18,L$7:L$24,1) -> 9 | M37: =_xlfn.RANK.AVG(M18,M$7:M$24,1) -> 14 | N37: =_xlfn.RANK.AVG(N18,N$7:N$24,1) -> 4 | O37: =_xlfn.RANK.AVG(O18,O$7:O$24,1) -> 1 | P37: =_xlfn.RANK.AVG(P18,P$7:P$24,1) -> 1 | Q37: =_xlfn.RANK.AVG(Q18,Q$7:Q$24,1) -> 10 | R37: =_xlfn.RANK.AVG(R18,R$7:R$24,1) -> 4 | ... T37: =_xlfn.RANK.AVG(T18,T$7:T$24,1) -> 8 | U37: =_xlfn.RANK.AVG(U18,$U$7:$U$24,1) -> 2 | V37: =_xlfn.RANK.AVG(V18,$V$7:$V$24,1) -> 3 | W37: =_xlfn.RANK.AVG(W18,W$7:W$24,1) -> 3 | X37: =_xlfn.RANK.AVG(X18,X$7:X$24,1) -> 2 | Y37: =_xlfn.RANK.AVG(Y18,Y$7:Y$24,1) -> 8 | Z37: =_xlfn.RANK.AVG(Z18,Z$7:Z$24,1) -> 2 | AA37: =_xlfn.RANK.AVG(AA18,AA$7:AA$24,1) -> 2 | AB37: =_xlfn.RANK.AVG(AB18,AB$7:AB$24,1) -> 2 | AC37: =_xlfn.RANK.AVG(AC18,AC$7:AC$24,1) -> 3 | AD37: =_xlfn.RANK.AVG(AD18,AD$7:AD$24,1) -> 3 | ... CE37: =_xlfn.RANK.AVG(CE18,CE$7:CE$24,1) -> 7
B38: Plastics & Rubber Products | D38: =SUM(S38:X38) -> 76 | G38: 4 | H38: -1 | I38: -4 | J38: -1 | K38: =_xlfn.RANK.AVG(K19,K$7:K$24,1) -> 5 | L38: =_xlfn.RANK.AVG(L19,L$7:L$24,1) -> 8 | M38: =_xlfn.RANK.AVG(M19,M$7:M$24,1) -> 14 | N38: =_xlfn.RANK.AVG(N19,N$7:N$24,1) -> 9.5 | O38: =_xlfn.RANK.AVG(O19,O$7:O$24,1) -> 16 | P38: =_xlfn.RANK.AVG(P19,P$7:P$24,1) -> 9 | Q38: =_xlfn.RANK.AVG(Q19,Q$7:Q$24,1) -> 8 | R38: =_xlfn.RANK.AVG(R19,R$7:R$24,1) -> 11 | ... T38: =_xlfn.RANK.AVG(T19,T$7:T$24,1) -> 13 | U38: =_xlfn.RANK.AVG(U19,$U$7:$U$24,1) -> 17 | V38: =_xlfn.RANK.AVG(V19,$V$7:$V$24,1) -> 9 | W38: =_xlfn.RANK.AVG(W19,W$7:W$24,1) -> 14 | X38: =_xlfn.RANK.AVG(X19,X$7:X$24,1) -> 12 | Y38: =_xlfn.RANK.AVG(Y19,Y$7:Y$24,1) -> 11 | Z38: =_xlfn.RANK.AVG(Z19,Z$7:Z$24,1) -> 13 | AA38: =_xlfn.RANK.AVG(AA19,AA$7:AA$24,1) -> 9 | AB38: =_xlfn.RANK.AVG(AB19,AB$7:AB$24,1) -> 9 | AC38: =_xlfn.RANK.AVG(AC19,AC$7:AC$24,1) -> 10 | AD38: =_xlfn.RANK.AVG(AD19,AD$7:AD$24,1) -> 16 | ... CE38: =_xlfn.RANK.AVG(CE19,CE$7:CE$24,1) -> 15
... B43: Wood Products | D43: =SUM(S43:X43) -> 95 | G43: -4 | H43: 6 | I43: -9 | J43: -9 | K43: =_xlfn.RANK.AVG(K24,K$7:K$24,1) -> 15 | L43: =_xlfn.RANK.AVG(L24,L$7:L$24,1) -> 1 | M43: =_xlfn.RANK.AVG(M24,M$7:M$24,1) -> 1 | N43: =_xlfn.RANK.AVG(N24,N$7:N$24,1) -> 17 | O43: =_xlfn.RANK.AVG(O24,O$7:O$24,1) -> 18 | P43: =_xlfn.RANK.AVG(P24,P$7:P$24,1) -> 15 | Q43: =_xlfn.RANK.AVG(Q24,Q$7:Q$24,1) -> 11 | R43: =_xlfn.RANK.AVG(R24,R$7:R$24,1) -> 13 | ... T43: =_xlfn.RANK.AVG(T24,T$7:T$24,1) -> 18 | U43: =_xlfn.RANK.AVG(U24,$U$7:$U$24,1) -> 18 | V43: =_xlfn.RANK.AVG(V24,$V$7:$V$24,1) -> 17 | W43: =_xlfn.RANK.AVG(W24,W$7:W$24,1) -> 10 | X43: =_xlfn.RANK.AVG(X24,X$7:X$24,1) -> 15 | Y43: =_xlfn.RANK.AVG(Y24,Y$7:Y$24,1) -> 16 | Z43: =_xlfn.RANK.AVG(Z24,Z$7:Z$24,1) -> 9 | AA43: =_xlfn.RANK.AVG(AA24,AA$7:AA$24,1) -> 10 | AB43: =_xlfn.RANK.AVG(AB24,AB$7:AB$24,1) -> 1 | AC43: =_xlfn.RANK.AVG(AC24,AC$7:AC$24,1) -> 1 | AD43: =_xlfn.RANK.AVG(AD24,AD$7:AD$24,1) -> 5 | ... CE43: =_xlfn.RANK.AVG(CE24,CE$7:CE$24,1) -> 6
B44: New Orders | H44: =AVERAGE(H45:H62) -> -1.5 | I44: =AVERAGE(I45:I62) -> -3.3333333 | J44: =AVERAGE(J45:J62) -> -3.3333333 | K44: =AVERAGE(K45:K62) -> -2.2222222 | L44: =AVERAGE(L45:L62) -> -3.5 | M44: =AVERAGE(M45:M62) -> -4 | N44: =AVERAGE(N45:N62) -> 2.2222222 | O44: =AVERAGE(O45:O62) -> 7.3888889 | P44: =AVERAGE(P45:P62) -> 0
A45: NEW ORDERS | B45: Apparel, Leather & Allied Products | D45: =IF(COUNTIF(P45:U45,">0")=0,(COUNTIF(P45:U45,"<0")*-1),COUNTIF(P45:U45,">0")) -> 1 | G45: -6 | H45: -10 | I45: -11 | J45: -11 | K45: -9 | L45: 5 | M45: 0 | N45: -3 | O45: 12 | P45: 7 | Q45: 0 | R45: 0 | S45: 0 | T45: 0 | U45: 0 | V45: -3 | W45: 16 | X45: 15 | Y45: 13 | Z45: 0 | AA45: 0 | AB45: 15 | AC45: 0 | AD45: 0 | AE45: 0 | AF45: 0 | AG45: 0 | AH45: 0 | AI45: 14 | AJ45: 10 | AK45: 0 | AL45: 11 | AM45: 13 | AN45: 13 | AO45: 0 | AP45: 11 | AQ45: 7 | AR45: 0 | AS45: 0 | AT45: -7 | AU45: 3 | AV45: 1 | AW45: 0 | AX45: -15 | AY45: 0 | AZ45: 0 | BA45: 0 | BB45: 0 | BC45: 0 | BD45: -12 | BE45: 0 | BF45: 0 | BG45: 0 | BH45: 0 | BI45: -12 | BJ45: 5 | BK45: 11 | BL45: 0 | BM45: 0 | BN45: 0 | BO45: 0 | BP45: 0 | BQ45: 0 | BR45: 0 | BS45: 3 | BT45: 0 | BU45: 0 | BV45: 0 | BW45: 0 | BX45: 0 | BY45: 8 | BZ45: 8 | CA45: 7 | CB45: 4 | CC45: 8 | CD45: 0 | CE45: -11
B46: Chemical Products | D46: =IF(COUNTIF(P46:U46,">0")=0,(COUNTIF(P46:U46,"<0")*-1),COUNTIF(P46:U46,">0")) -> 4 | G46: 6 | H46: 2 | I46: 1 | J46: 1 | K46: -1 | L46: -2 | M46: -2 | N46: 3 | O46: 1 | P46: 2 | Q46: -1 | R46: -3 | S46: 6 | T46: 9 | U46: 11 | V46: 2 | W46: 5 | X46: 7 | Y46: 3 | Z46: 5 | AA46: 7 | AB46: 3 | AC46: 9 | AD46: 8 | AE46: 8 | AF46: 8 | AG46: 5 | AH46: 7 | AI46: 9 | AJ46: 1 | AK46: 5 | AL46: 1 | AM46: 5 | AN46: 6 | AO46: 2 | AP46: 3 | AQ46: -2 | AR46: -2 | AS46: -5 | AT46: -4 | AU46: -2 | AV46: -5 | AW46: -7 | AX46: -3 | AY46: 0 | AZ46: -1 | BA46: -4 | BB46: -4 | BC46: -2 | BD46: 1 | BE46: -1 | BF46: -1 | BG46: 0 | BH46: -4 | BI46: 1 | BJ46: 3 | BK46: 6 | BL46: 2 | BM46: 2 | BN46: 1 | BO46: 2 | BP46: 1 | BQ46: -2 | BR46: -1 | BS46: -5 | BT46: -3 | BU46: 0 | BV46: 5 | BW46: 1 | BX46: -1 | BY46: 1 | BZ46: -2 | CA46: -4 | CB46: -2 | CC46: 0 | CD46: -1 | CE46: -4
B47: Computer & Electronic Products | D47: =IF(COUNTIF(P47:U47,">0")=0,(COUNTIF(P47:U47,"<0")*-1),COUNTIF(P47:U47,">0")) -> 4 | G47: 1 | H47: 1 | I47: -1 | J47: -3 | K47: 2 | L47: -1 | M47: -3 | N47: 6 | O47: 7 | P47: 1 | Q47: -4 | R47: -6 | S47: 1 | T47: 2 | U47: 12 | V47: 0 | W47: 9 | X47: 5 | Y47: 8 | Z47: 1 | AA47: 3 | AB47: 7 | AC47: 2 | AD47: 11 | AE47: 7 | AF47: 14 | AG47: 13 | AH47: 9 | AI47: 4 | AJ47: 6 | AK47: 1 | AL47: 6 | AM47: 9 | AN47: 3 | AO47: 10 | AP47: 10 | AQ47: 2 | AR47: 1 | AS47: 5 | AT47: 2 | AU47: 0 | AV47: -1 | AW47: -2 | AX47: -2 | AY47: -1 | AZ47: -6 | BA47: -3 | BB47: -8 | BC47: -5 | BD47: -2 | BE47: -5 | BF47: -2 | BG47: -6 | BH47: -8 | BI47: -2 | BJ47: -1 | BK47: 1 | BL47: 5 | BM47: 3 | BN47: 0 | BO47: 3 | BP47: 3 | BQ47: 1 | BR47: 2 | BS47: 1 | BT47: 2 | BU47: 1 | BV47: 0 | BW47: -2 | BX47: 0 | BY47: 3 | BZ47: -3 | CA47: 1 | CB47: -1 | CC47: 4 | CD47: -4 | CE47: -3
B48: Electrical Equipment, Appliances & Components | D48: =IF(COUNTIF(P48:U48,">0")=0,(COUNTIF(P48:U48,"<0")*-1),COUNTIF(P48:U48,">0")) -> 4 | G48: 0 | H48: -6 | I48: 0 | J48: -8 | K48: 0 | L48: 4 | M48: -6 | N48: -2 | O48: 11 | P48: 5 | Q48: -7 | R48: -1 | S48: 4 | T48: 8 | U48: 1 | V48: 11 | W48: 11 | X48: 11 | Y48: 2 | Z48: 12 | AA48: 9 | AB48: 14 | AC48: 16 | AD48: 14 | AE48: 10 | AF48: 9 | AG48: 1 | AH48: 2 | AI48: 3 | AJ48: 4 | AK48: 11 | AL48: 5 | AM48: 7 | AN48: 9 | AO48: -1 | AP48: 0 | AQ48: -3 | AR48: 0 | AS48: -6 | AT48: -3 | AU48: 0 | AV48: -9 | AW48: -4 | AX48: -12 | AY48: -2 | AZ48: -3 | BA48: -5 | BB48: -10 | BC48: -6 | BD48: -6 | BE48: -9 | BF48: -6 | BG48: -8 | BH48: -13 | BI48: -1 | BJ48: -4 | BK48: 3 | BL48: 0 | BM48: -2 | BN48: -4 | BO48: -2 | BP48: -3 | BQ48: -5 | BR48: -3 | BS48: -2 | BT48: 4 | BU48: 6 | BV48: 1 | BW48: 7 | BX48: -3 | BY48: 0 | BZ48: 4 | CA48: -3 | CB48: 0 | CC48: 2 | CD48: 1 | CE48: -1
B49: Fabricated Metal Products | D49: =IF(COUNTIF(P49:U49,">0")=0,(COUNTIF(P49:U49,"<0")*-1),COUNTIF(P49:U49,">0")) -> 2 | G49: -1 | H49: -7 | I49: -6 | J49: -2 | K49: 1 | L49: -7 | M49: -7 | N49: 2 | O49: 4 | P49: -2 | Q49: -9 | R49: -9 | S49: -2 | T49: 6 | U49: 5 | V49: 5 | W49: 12 | X49: 10 | Y49: 7 | Z49: 6 | AA49: 5 | AB49: 8 | AC49: 14 | AD49: 6 | AE49: 6 | AF49: 5 | AG49: 2 | AH49: 1 | AI49: 2 | AJ49: -1 | AK49: 4 | AL49: 8 | AM49: 2 | AN49: 5 | AO49: 5 | AP49: 1 | AQ49: 0 | AR49: -5 | AS49: -4 | AT49: -5 | AU49: -7 | AV49: -8 | AW49: -9 | AX49: -8 | AY49: -3 | AZ49: 1 | BA49: 6 | BB49: -2 | BC49: -1 | BD49: -5 | BE49: -6 | BF49: 2 | BG49: -2 | BH49: -5 | BI49: -4 | BJ49: 1 | BK49: 7 | BL49: 4 | BM49: 1 | BN49: -3 | BO49: -6 | BP49: -6 | BQ49: -8 | BR49: 0 | BS49: -1 | BT49: -7 | BU49: -3 | BV49: 2 | BW49: 3 | BX49: 3 | BY49: 2 | BZ49: 2 | CA49: -1 | CB49: -4 | CC49: -3 | CD49: 4 | CE49: 2
B50: Food, Beverage & Tobacco Products | D50: =IF(COUNTIF(P50:U50,">0")=0,(COUNTIF(P50:U50,"<0")*-1),COUNTIF(P50:U50,">0")) -> 6 | G50: 5 | H50: 4 | I50: 0 | J50: 2 | K50: 3 | L50: 2 | M50: 2 | N50: 5 | O50: 2 | P50: 6 | Q50: 2 | R50: 2 | S50: 7 | T50: 7 | U50: 7 | V50: 6 | W50: 7 | X50: 3 | Y50: 1 | Z50: 4 | AA50: 2 | AB50: 6 | AC50: 6 | AD50: 5 | AE50: 1 | AF50: 7 | AG50: 9 | AH50: 12 | AI50: 8 | AJ50: 3 | AK50: 10 | AL50: 7 | AM50: 1 | AN50: 12 | AO50: 8 | AP50: 8 | AQ50: -1 | AR50: 0 | AS50: -3 | AT50: -1 | AU50: -4 | AV50: -2 | AW50: -8 | AX50: -5 | AY50: 0 | AZ50: -5 | BA50: 0 | BB50: -3 | BC50: 0 | BD50: -8 | BE50: 0 | BF50: 4 | BG50: 0 | BH50: 2 | BI50: 0 | BJ50: -2 | BK50: -2 | BL50: 3 | BM50: -4 | BN50: -2 | BO50: -1 | BP50: -5 | BQ50: -1 | BR50: 1 | BS50: 2 | BT50: 3 | BU50: 4 | BV50: -1 | BW50: 2 | BX50: 2 | BY50: -1 | BZ50: -5 | CA50: 2 | CB50: 0 | CC50: 5 | CD50: -2 | CE50: 0
B51: Furniture & Related Products | D51: =IF(COUNTIF(P51:U51,">0")=0,(COUNTIF(P51:U51,"<0")*-1),COUNTIF(P51:U51,">0")) -> 3 | G51: 10 | H51: 7 | I51: 0 | J51: 0 | K51: 4 | L51: -9 | M51: -11 | N51: 9 | O51: 8 | P51: -4 | Q51: -10 | R51: 0 | S51: 5 | T51: 12 | U51: 4 | V51: 9 | W51: 10 | X51: 0 | Y51: 11 | Z51: 2 | AA51: 0 | AB51: 10 | AC51: 8 | AD51: 15 | AE51: 15 | AF51: 15 | AG51: 14 | AH51: 11 | AI51: 13 | AJ51: 8 | AK51: 12 | AL51: 10 | AM51: 0 | AN51: 4 | AO51: 7 | AP51: 0 | AQ51: -6 | AR51: -6 | AS51: -7 | AT51: -11 | AU51: -11 | AV51: 0 | AW51: -6 | AX51: -11 | AY51: -8 | AZ51: -9 | BA51: -6 | BB51: 3 | BC51: 3 | BD51: 4 | BE51: -8 | BF51: -7 | BG51: -3 | BH51: -10 | BI51: -9 | BJ51: -8 | BK51: -4 | BL51: -2 | BM51: 0 | BN51: 0 | BO51: 4 | BP51: 2 | BQ51: -6 | BR51: 0 | BS51: -6 | BT51: -8 | BU51: 0 | BV51: -2 | BW51: -4 | BX51: -6 | BY51: -4 | BZ51: 3 | CA51: 5 | CB51: 0 | CC51: 0 | CD51: 5 | CE51: -7
B52: Machinery | D52: =IF(COUNTIF(P52:U52,">0")=0,(COUNTIF(P52:U52,"<0")*-1),COUNTIF(P52:U52,">0")) -> 3 | G52: -2 | H52: 0 | I52: 2 | J52: 0 | K52: -3 | L52: -5 | M52: -1 | N52: 1 | O52: 3 | P52: -1 | Q52: -8 | R52: -4 | S52: 2 | T52: 1 | U52: 9 | V52: 3 | W52: 6 | X52: 6 | Y52: 9 | Z52: 11 | AA52: 6 | AB52: 9 | AC52: 10 | AD52: 9 | AE52: 9 | AF52: 12 | AG52: 11 | AH52: 8 | AI52: 7 | AJ52: 7 | AK52: 6 | AL52: 2 | AM52: 3 | AN52: 1 | AO52: 4 | AP52: 6 | AQ52: 0 | AR52: -1 | AS52: -2 | AT52: 1 | AU52: 0 | AV52: -7 | AW52: -1 | AX52: -7 | AY52: -6 | AZ52: -2 | BA52: -2 | BB52: -7 | BC52: -4 | BD52: -7 | BE52: -4 | BF52: -4 | BG52: -5 | BH52: -7 | BI52: -5 | BJ52: -7 | BK52: -1 | BL52: 0 | BM52: -3 | BN52: -1 | BO52: -4 | BP52: -4 | BQ52: -3 | BR52: -4 | BS52: -4 | BT52: 1 | BU52: -1 | BV52: 6 | BW52: 4 | BX52: -4 | BY52: 5 | BZ52: 1 | CA52: -2 | CB52: -3 | CC52: -1 | CD52: -3 | CE52: -1
B53: Miscellaneous Manufacturing | D53: =IF(COUNTIF(P53:U53,">0")=0,(COUNTIF(P53:U53,"<0")*-1),COUNTIF(P53:U53,">0")) -> 3 | G53: 3 | H53: -3 | I53: -2 | J53: 3 | K53: -2 | L53: 1 | M53: 1 | N53: 7 | O53: 6 | P53: -3 | Q53: -5 | R53: -8 | S53: 3 | T53: 4 | U53: 3 | V53: -1 | W53: 1 | X53: 4 | Y53: -1 | Z53: 3 | AA53: -1 | AB53: 1 | AC53: 7 | AD53: 1 | AE53: 12 | AF53: 11 | AG53: 4 | AH53: 6 | AI53: 5 | AJ53: 5 | AK53: 9 | AL53: 0 | AM53: 8 | AN53: 11 | AO53: 3 | AP53: 5 | AQ53: 1 | AR53: -4 | AS53: -1 | AT53: 3 | AU53: -1 | AV53: -3 | AW53: -3 | AX53: -4 | AY53: 1 | AZ53: 4 | BA53: 2 | BB53: 1 | BC53: -3 | BD53: -1 | BE53: -3 | BF53: 5 | BG53: -1 | BH53: -2 | BI53: 2 | BJ53: -3 | BK53: 2 | BL53: 1 | BM53: -1 | BN53: 2 | BO53: 1 | BP53: -1 | BQ53: -4 | BR53: -2 | BS53: 0 | BT53: -4 | BU53: 3 | BV53: -4 | BW53: 6 | BX53: 0 | BY53: 0 | BZ53: -1 | CA53: 3 | CB53: 1 | CC53: 1 | CD53: 3 | CE53: -2
B54: Nonmetallic Mineral Products | D54: =IF(COUNTIF(P54:U54,">0")=0,(COUNTIF(P54:U54,"<0")*-1),COUNTIF(P54:U54,">0")) -> 2 | G54: 9 | H54: -4 | I54: 3 | J54: -7 | K54: -5 | L54: -4 | M54: -10 | N54: 0 | O54: 5 | P54: -5 | Q54: -13 | R54: 3 | S54: 0 | T54: 0 | U54: 10 | V54: 4 | W54: 2 | X54: 8 | Y54: -3 | Z54: 0 | AA54: 0 | AB54: 11 | AC54: 11 | AD54: 16 | AE54: 11 | AF54: 3 | AG54: -1 | AH54: 4 | AI54: -2 | AJ54: -3 | AK54: 0 | AL54: 0 | AM54: -1 | AN54: 0 | AO54: 0 | AP54: 0 | AQ54: 6 | AR54: 4 | AS54: 4 | AT54: 5 | AU54: -5 | AV54: -10 | AW54: -10 | AX54: -13 | AY54: -11 | AZ54: -10 | BA54: 5 | BB54: 0 | BC54: 4 | BD54: 2 | BE54: 4 | BF54: 1 | BG54: -4 | BH54: -6 | BI54: -10 | BJ54: -9 | BK54: 0 | BL54: 12 | BM54: 7 | BN54: -6 | BO54: 0 | BP54: 6 | BQ54: -11 | BR54: -6 | BS54: -8 | BT54: -9 | BU54: -6 | BV54: -5 | BW54: -6 | BX54: 4 | BY54: -2 | BZ54: 5 | CA54: 4 | CB54: -5 | CC54: 3 | CD54: -8 | CE54: -6
B55: Paper Products | D55: =IF(COUNTIF(P55:U55,">0")=0,(COUNTIF(P55:U55,"<0")*-1),COUNTIF(P55:U55,">0")) -> 4 | G55: 2 | H55: -2 | I55: -10 | J55: -4 | K55: 0 | L55: 3 | M55: -5 | N55: 0 | O55: 15 | P55: 3 | Q55: 1 | R55: 1 | S55: 0 | T55: -1 | U55: 8 | V55: 8 | W55: 8 | X55: 9 | Y55: 0 | Z55: 7 | AA55: 13 | AB55: 12 | AC55: 12 | AD55: 13 | AE55: 5 | AF55: 10 | AG55: 10 | AH55: 5 | AI55: 0 | AJ55: 2 | AK55: -1 | AL55: 0 | AM55: 12 | AN55: 7 | AO55: 6 | AP55: 0 | AQ55: -5 | AR55: 0 | AS55: 0 | AT55: -6 | AU55: -9 | AV55: -12 | AW55: 0 | AX55: -14 | AY55: -12 | AZ55: -11 | BA55: 7 | BB55: -5 | BC55: 1 | BD55: -10 | BE55: 2 | BF55: 0 | BG55: 0 | BH55: -9 | BI55: -6 | BJ55: 0 | BK55: 10 | BL55: 11 | BM55: 5 | BN55: 0 | BO55: 0 | BP55: 5 | BQ55: 4 | BR55: -9 | BS55: -9 | BT55: -5 | BU55: 5 | BV55: 0 | BW55: -5 | BX55: -8 | BY55: -5 | BZ55: -7 | CA55: -7 | CB55: -8 | CC55: -6 | CD55: -6 | CE55: -9
B56: Petroleum & Coal Products | D56: =IF(COUNTIF(P56:U56,">0")=0,(COUNTIF(P56:U56,"<0")*-1),COUNTIF(P56:U56,">0")) -> 2 | G56: 0 | H56: -8 | I56: -5 | J56: -6 | K56: -4 | L56: -6 | M56: 0 | N56: 0 | O56: -2 | P56: -9 | Q56: -11 | R56: -7 | S56: 0 | T56: 5 | U56: 6 | V56: 0 | W56: 4 | X56: -1 | Y56: 10 | Z56: 0 | AA56: 0 | AB56: 0 | AC56: 1 | AD56: 3 | AE56: 3 | AF56: 4 | AG56: 6 | AH56: 10 | AI56: 6 | AJ56: 0 | AK56: 8 | AL56: -1 | AM56: 6 | AN56: -1 | AO56: 0 | AP56: 7 | AQ56: 5 | AR56: 0 | AS56: 0 | AT56: 0 | AU56: 2 | AV56: 0 | AW56: 0 | AX56: -6 | AY56: 3 | AZ56: 2 | BA56: 4 | BB56: -6 | BC56: 0 | BD56: 0 | BE56: -7 | BF56: -5 | BG56: 0 | BH56: 0 | BI56: -7 | BJ56: -5 | BK56: 0 | BL56: 7 | BM56: 0 | BN56: 3 | BO56: 5 | BP56: 4 | BQ56: 0 | BR56: 0 | BS56: 0 | BT56: 0 | BU56: 0 | BV56: 7 | BW56: 9 | BX56: 5 | BY56: 7 | BZ56: 6 | CA56: 6 | CB56: -6 | CC56: 0 | CD56: 0 | CE56: -8
B57: Plastics & Rubber Products | D57: =IF(COUNTIF(P57:U57,">0")=0,(COUNTIF(P57:U57,"<0")*-1),COUNTIF(P57:U57,">0")) -> 4 | G57: 4 | H57: -1 | I57: -4 | J57: -1 | K57: -6 | L57: -3 | M57: 0 | N57: 4 | O57: 10 | P57: 4 | Q57: -6 | R57: -5 | S57: 10 | T57: 10 | U57: 14 | V57: 10 | W57: 14 | X57: 14 | Y57: 5 | Z57: 10 | AA57: 1 | AB57: 2 | AC57: 3 | AD57: 10 | AE57: 4 | AF57: 2 | AG57: 7 | AH57: 0 | AI57: 1 | AJ57: 9 | AK57: 2 | AL57: 3 | AM57: 4 | AN57: 2 | AO57: 1 | AP57: 4 | AQ57: 3 | AR57: -3 | AS57: 1 | AT57: 0 | AU57: 1 | AV57: -6 | AW57: -5 | AX57: -10 | AY57: -5 | AZ57: -7 | BA57: 3 | BB57: 2 | BC57: -8 | BD57: -9 | BE57: -2 | BF57: 0 | BG57: 3 | BH57: 1 | BI57: -8 | BJ57: -6 | BK57: 9 | BL57: 6 | BM57: 6 | BN57: 0 | BO57: 0 | BP57: -2 | BQ57: -9 | BR57: -11 | BS57: 0 | BT57: -6 | BU57: -2 | BV57: 3 | BW57: -3 | BX57: -5 | BY57: 6 | BZ57: 7 | CA57: 0 | CB57: 3 | CC57: -4 | CD57: -7 | CE57: 3
... B59: Printing & Related Support Activities | D59: =IF(COUNTIF(P59:U59,">0")=0,(COUNTIF(P59:U59,"<0")*-1),COUNTIF(P59:U59,">0")) -> 2 | G59: 7 | H59: 5 | I59: 0 | J59: 0 | K59: 0 | L59: -10 | M59: -9 | N59: -5 | O59: 14 | P59: 8 | Q59: -14 | R59: -12 | S59: 8 | T59: 0 | U59: -1 | V59: 7 | W59: 0 | X59: -2 | Y59: 0 | Z59: -2 | AA59: 4 | AB59: 0 | AC59: -1 | AD59: -1 | AE59: 14 | AF59: 13 | AG59: 12 | AH59: -2 | AI59: 12 | AJ59: -5 | AK59: 0 | AL59: 0 | AM59: 0 | AN59: 0 | AO59: 11 | AP59: 0 | AQ59: 0 | AR59: 3 | AS59: 0 | AT59: -8 | AU59: -10 | AV59: -13 | AW59: 0 | AX59: 0 | AY59: -9 | AZ59: 5 | BA59: 8 | BB59: 0 | BC59: 5 | BD59: 0 | BE59: 0 | BF59: -8 | BG59: -9 | BH59: 0 | BI59: -13 | BJ59: 0 | BK59: 0 | BL59: 9 | BM59: 8 | BN59: 4 | BO59: 0 | BP59: 0 | BQ59: -10 | BR59: -10 | BS59: -10 | BT59: 0 | BU59: -7 | BV59: 0 | BW59: 0 | BX59: 0 | BY59: 0 | BZ59: 0 | CA59: 0 | CB59: 0 | CC59: 0 | CD59: 0 | CE59: 0
B60: Textile Mills | D60: =IF(COUNTIF(P60:U60,">0")=0,(COUNTIF(P60:U60,"<0")*-1),COUNTIF(P60:U60,">0")) -> 2 | G60: 8 | H60: 3 | I60: -7 | J60: -10 | K60: -8 | L60: -11 | M60: 3 | N60: -4 | O60: 9 | P60: -6 | Q60: -15 | R60: 4 | S60: 11 | T60: -2 | U60: 0 | V60: -2 | W60: -1 | X60: 13 | Y60: b v | Z60: -1 | AA60: 10 | AB60: 13 | AC60: 15 | AD60: 7 | AE60: 0 | AF60: -1 | AG60: 0 | AH60: 0 | AI60: 11 | AJ60: 0 | AK60: 13 | AL60: -2 | AM60: 10 | AN60: 10 | AO60: -3 | AP60: 0 | AQ60: 8 | AR60: 0 | AS60: 6 | AT60: -9 | AU60: -8 | AV60: 0 | AW60: 3 | AX60: -16 | AY60: -10 | AZ60: -8 | BA60: 0 | BB60: -11 | BC60: -7 | BD60: 3 | BE60: 3 | BF60: 0 | BG60: -7 | BH60: -12 | BI60: 4 | BJ60: 0 | BK60: -3 | BL60: 0 | BM60: -5 | BN60: -7 | BO60: -5 | BP60: 0 | BQ60: 0 | BR60: 0 | BS60: -11 | BT60: 5 | BU60: -8 | BV60: 9 | BW60: 0 | BX60: 6 | BY60: 0 | BZ60: 0 | CA60: -6 | CB60: 0 | CC60: 7 | CD60: 6 | CE60: -10
B61: Transportation Equipment | D61: =IF(COUNTIF(P61:U61,">0")=0,(COUNTIF(P61:U61,"<0")*-1),COUNTIF(P61:U61,">0")) -> 2 | G61: -3 | H61: -5 | I61: -8 | J61: -5 | K61: -7 | L61: -8 | M61: -8 | N61: -1 | O61: -1 | P61: -8 | Q61: -12 | R61: -11 | S61: -1 | T61: 3 | U61: 2 | V61: 1 | W61: 3 | X61: 1 | Y61: 6 | Z61: 9 | AA61: 8 | AB61: 4 | AC61: 5 | AD61: 2 | AE61: 13 | AF61: 6 | AG61: 3 | AH61: 3 | AI61: 1 | AJ61: -2 | AK61: 3 | AL61: 4 | AM61: 11 | AN61: 8 | AO61: 9 | AP61: 2 | AQ61: -4 | AR61: 0 | AS61: 3 | AT61: 4 | AU61: -3 | AV61: -4 | AW61: 1 | AX61: -1 | AY61: 2 | AZ61: -4 | BA61: 1 | BB61: -1 | BC61: 2 | BD61: -3 | BE61: 1 | BF61: -3 | BG61: 1 | BH61: -1 | BI61: -3 | BJ61: 2 | BK61: 4 | BL61: -1 | BM61: 0 | BN61: -5 | BO61: -3 | BP61: -7 | BQ61: -7 | BR61: -5 | BS61: -7 | BT61: -2 | BU61: -4 | BV61: 4 | BW61: -1 | BX61: -2 | BY61: -3 | BZ61: 0 | CA61: -5 | CB61: 0 | CC61: -2 | CD61: -5 | CE61: 1
B62: Wood Products | D62: =IF(COUNTIF(P62:U62,">0")=0,(COUNTIF(P62:U62,"<0")*-1),COUNTIF(P62:U62,">0")) -> 4 | G62: -4 | H62: 6 | I62: -9 | J62: -9 | K62: 5 | L62: -12 | M62: -12 | N62: 10 | O62: 16 | P62: 9 | Q62: -3 | R62: -2 | S62: 9 | T62: 13 | U62: 13 | V62: 12 | W62: 15 | X62: 12 | Y62: 12 | Z62: 8 | AA62: 12 | AB62: -1 | AC62: 4 | AD62: 4 | AE62: -1 | AF62: 0 | AG62: 0 | AH62: -1 | AI62: 0 | AJ62: 0 | AK62: -2 | AL62: 0 | AM62: 0 | AN62: 0 | AO62: 0 | AP62: -1 | AQ62: -7 | AR62: -7 | AS62: -8 | AT62: -10 | AU62: -12 | AV62: -14 | AW62: -11 | AX62: -17 | AY62: -7 | AZ62: 0 | BA62: 0 | BB62: -12 | BC62: -9 | BD62: -11 | BE62: 0 | BF62: 0 | BG62: -10 | BH62: -11 | BI62: -11 | BJ62: -10 | BK62: 8 | BL62: 8 | BM62: 0 | BN62: -8 | BO62: 0 | BP62: 0 | BQ62: 2 | BR62: -7 | BS62: 0 | BT62: -10 | BU62: -5 | BV62: -2 | BW62: 8 | BX62: -7 | BY62: -6 | BZ62: -6 | CA62: 0 | CB62: -7 | CC62: -5 | CD62: -9 | CE62: 0
A64: PRODUCTION | B64: Apparel, Leather & Allied Products | G64: -5 | H64: -10 | I64: -9 | J64: -11 | K64: -9 | L64: 7 | M64: -14 | N64: -7
B65: Chemical Products | G65: 6 | H65: 2 | I65: 1 | J65: 3 | K65: -2 | L65: 1 | M65: -5 | N65: 1
B66: Computer & Electronic Products | G66: 4 | H66: 1 | I66: 0 | J66: 2 | K66: 0 | L66: -2 | M66: -1 | N66: 3
B67: Electrical Equipment, Appliances & Components | G67: 5 | H67: -8 | I67: -4 | J67: -2 | K67: 2 | L67: 3 | M67: -3 | N67: -5
B68: Fabricated Metal Products | G68: -2 | H68: -4 | I68: -2 | J68: -1 | K68: 1 | L68: -4 | M68: -7 | N68: 2
B69: Food, Beverage & Tobacco Products | G69: 7 | H69: 5 | I69: 3 | J69: 0 | K69: 3 | L69: 5 | M69: 2 | N69: 5
B70: Furniture & Related Products | G70: 12 | H70: 6 | I70: 0 | J70: 0 | K70: 5 | L70: -6 | M70: -4 | N70: 7
B71: Machinery | G71: 1 | H71: -2 | I71: -1 | J71: -4 | K71: -5 | L71: -1 | M71: 1 | N71: -1
B72: Miscellaneous Manufacturing | G72: 2 | H72: -3 | I72: 0 | J72: 1 | K72: -1 | L72: 2 | M72: 3 | N72: -3
B73: Nonmetallic Mineral Products | G73: 8 | H73: -7 | I73: 2 | J73: -7 | K73: -7 | L73: -11 | M73: -12 | N73: 0
B74: Paper Products | G74: 3 | H74: -9 | I74: -8 | J74: -5 | K74: 4 | L74: 6 | M74: -8 | N74: 0
B75: Petroleum & Coal Products | G75: 9 | H75: -5 | I75: -7 | J75: -8 | K75: -8 | L75: 4 | M75: -6 | N75: 4
B76: Plastics & Rubber Products | G76: -1 | H76: -1 | I76: -3 | J76: -3 | K76: -4 | L76: -5 | M76: 0 | N76: -2
... B81: Wood Products | G81: 13 | H81: 8 | I81: 0 | J81: -10 | K81: -6 | L81: -7 | M81: -13 | N81: 6
A83: EMPLOYMENT | B83: Apparel, Leather & Allied Products | H83: -6 | I83: -7 | J83: -10 | K83: -9 | L83: 0 | M83: -11 | N83: 0
B84: Chemical Products | G84: 2 | H84: 1 | I84: 0 | J84: 1 | K84: -5 | L84: 1 | M84: -2 | N84: -1
B85: Computer & Electronic Products | G85: 6 | H85: 0 | I85: -2 | J85: -2 | K85: -3 | L85: 4 | M85: 1 | N85: 1
B86: Electrical Equipment, Appliances & Components | G86: 7 | H86: 4 | I86: -4 | J86: -5 | K86: -2 | L86: -4 | M86: -4 | N86: -6
B87: Fabricated Metal Products | G87: -1 | H87: -3 | I87: -3 | J87: -6 | K87: -1 | L87: -2 | M87: -7 | N87: -4
B88: Food, Beverage & Tobacco Products | G88: 3 | H88: 7 | I88: 0 | J88: 2 | K88: 1 | L88: 2 | M88: 0 | N88: 0
B89: Furniture & Related Products | G89: 12 | H89: 9 | I89: 6 | J89: 0 | K89: 3 | L89: 0 | M89: 0 | N89: 3
B90: Machinery | G90: 4 | H90: 2 | I90: -1 | J90: -1 | K90: -6 | L90: -1 | M90: -1 | N90: -5
B91: Miscellaneous Manufacturing | G91: 5 | H91: -1 | I91: 4 | J91: 4 | K91: 0 | L91: 0 | M91: 0 | N91: -2
B92: Nonmetallic Mineral Products | G92: 0 | H92: -5 | I92: 2 | J92: 0 | K92: 2 | L92: -3 | M92: -3 | N92: 0
B93: Paper Products | G93: 10 | H93: 3 | I93: 1 | J93: -8 | K93: -4 | L93: 5 | M93: 0 | N93: 2
B94: Petroleum & Coal Products | G94: 9 | H94: 5 | I94: 3 | J94: 0 | K94: 0 | L94: -7 | M94: -8 | N94: -10
B95: Plastics & Rubber Products | G95: -2 | H95: 6 | I95: 0 | J95: -3 | K95: 0 | L95: 3 | M95: 2 | N95: -3
... B100: Wood Products | G100: -4 | H100: 0 | I100: -9 | J100: -7 | K100: 0 | L100: -9 | M100: -10 | N100: 4
A102: SUPPLIER DELIVERABLES | B102: Apparel, Leather & Allied Products | G102: 0 | H102: -5 | I102: 0 | J102: 0 | K102: -6 | L102: 6 | M102: 0
B103: Chemical Products | G103: -5 | H103: 1 | I103: 0 | J103: -1 | K103: 2 | L103: 0 | M103: -1
B104: Computer & Electronic Products | G104: -6 | H104: -3 | I104: -6 | J104: -4 | K104: -1 | L104: 5 | M104: -4
B105: Electrical Equipment, Appliances & Components | G105: 2 | H105: 4 | I105: 1 | J105: 5 | K105: 0 | L105: -4 | M105: 3
B106: Fabricated Metal Products | G106: 4 | H106: 3 | I106: 2 | J106: 2 | K106: 7 | L106: 2 | M106: -6
B107: Food, Beverage & Tobacco Products | G107: -1 | H107: -2 | I107: -3 | J107: -8 | K107: -4 | L107: 4 | M107: 0
B108: Furniture & Related Products | G108: -8 | H108: 0 | I108: 0 | J108: 3 | K108: 0 | L108: -3 | M108: 0
B109: Machinery | G109: -3 | H109: 0 | I109: -5 | J109: -2 | K109: 1 | L109: -1 | M109: -3
B110: Miscellaneous Manufacturing | G110: -2 | H110: -1 | I110: -2 | J110: -7 | K110: -2 | L110: 3 | M110: -2
B111: Nonmetallic Mineral Products | G111: -9 | H111: 0 | I111: 0 | J111: 4 | K111: 6 | L111: 0 | M111: 0
B112: Paper Products | G112: 3 | H112: 5 | I112: -4 | J112: -5 | K112: 5 | L112: 0 | M112: 0
B113: Petroleum & Coal Products | G113: 0 | H113: -6 | I113: 0 | J113: 0 | K113: 0 | L113: 0 | M113: 0
B114: Plastics & Rubber Products | G114: -4 | H114: -4 | I114: 3 | J114: -3 | K114: 3 | L114: -2 | M114: 2
... B119: Wood Products | G119: 5 | H119: -7 | I119: -8 | J119: 0 | K119: 0 | L119: 0 | M119: -5
A121: INVENTORIES | B121: Apparel, Leather & Allied Products | G121: -5 | H121: -8 | I121: 0 | J121: -10 | K121: -8 | L121: -12 | M121: -11 | N121: -7
...

Sheet industry notes
B2: Basic Materials | C2: Conglomerates | D2: Consumer Goods | E2: Financial | F2: Healthcare | G2: Industrial Goods | H2: Services | K2: Technology | L2: Utilities
B4: Agricultural Chemicals | C4: Conglomerates | D4: Appliances | E4: Accident & Health Insurance | F4: Biotechnology | G4: Aerospace/Defense - Major Diversified | H4: Advertising Agencies | I4: Publishing - Books | K4: Application Software | L4: Diversified Utilities
B5: Aluminum | D5: Auto Manufacturers - Major | E5: Asset Management | F5: Diagnostic Substances | G5: Aerospace/Defense Products & Services | H5: Air Delivery & Freight Services | I5: Publishing - Newspapers | K5: Business Software & Services | L5: Electric Utilities
B6: Chemicals - Major Diversified | D6: Auto Parts | E6: Closed-End Fund - Debt | F6: Drug Delivery | G6: Cement | H6: Air Services, Other | I6: Publishing - Periodicals | K6: Communication Equipment | L6: Foreign Utilities
B7: Copper | D7: Beverages - Brewers | E7: Closed-End Fund - Equity | F7: Drug Manufacturers - Major | G7: Diversified Machinery | H7: Apparel Stores | I7: Railroads | K7: Computer Based Systems | L7: Gas Utilities
B8: Gold | D8: Beverages - Soft Drinks | E8: Closed-End Fund - Foreign | F8: Drug Manufacturers - Other | G8: Farm & Construction Machinery | H8: Auto Dealerships | I8: Regional Airlines | K8: Computer Peripherals | L8: Water Utilities
B9: Independent Oil & Gas | D9: Beverages - Wineries & Distillers | E9: Credit Services | F9: Drug Related Products | G9: General Building Materials | H9: Auto Parts Stores | I9: Rental & Leasing Services | K9: Data Storage Devices
B10: Industrial Metals & Minerals | D10: Business Equipment | E10: Diversified Investments | F10: Drugs - Generic | G10: General Contractors | H10: Auto Parts Wholesale | I10: Research Services | K10: Diversified Communication Services
B11: Major Integrated Oil & Gas | D11: Cigarettes | E11: Foreign Money Center Banks | F11: Health Care Plans | G11: Heavy Construction | H11: Basic Materials Wholesale | I11: Resorts & Casinos | K11: Diversified Computer Systems
B12: Nonmetallic Mineral Mining | D12: Cleaning Products | E12: Foreign Regional Banks | F12: Home Health Care | G12: Industrial Electrical Equipment | H12: Broadcasting - Radio | I12: Restaurants | K12: Diversified Electronics
B13: Oil & Gas Drilling & Exploration | D13: Confectioners | E13: Insurance Brokers | F13: Hospitals | G13: Industrial Equipment & Components | H13: Broadcasting - TV | I13: Security & Protection Services | K13: Healthcare Information Services
B14: Oil & Gas Equipment & Services | D14: Dairy Products | E14: Investment Brokerage - National | F14: Long-Term Care Facilities | G14: Lumber, Wood Production | H14: Building Materials Wholesale | I14: Shipping | K14: Information & Delivery Services
B15: Oil & Gas Pipelines | D15: Electronic Equipment | E15: Investment Brokerage - Regional | F15: Medical Appliances & Equipment | G15: Machine Tools & Accessories | H15: Business Services | I15: Specialty Eateries | K15: Information Technology Services
B16: Oil & Gas Refining & Marketing | D16: Farm Products | E16: Life Insurance | F16: Medical Instruments & Supplies | G16: Manufactured Housing | H16: Catalog & Mail Order Houses | I16: Specialty Retail, Other | K16: Internet Information Providers
B17: Silver | D17: Food - Major Diversified | E17: Money Center Banks | F17: Medical Laboratories & Research | G17: Metal Fabrication | H17: CATV Systems | I17: Sporting Activities | K17: Internet Service Providers
B18: Specialty Chemicals | D18: Home Furnishings & Fixtures | E18: Mortgage Investment | F18: Medical Practitioners | G18: Pollution & Treatment Controls | H18: Computers Wholesale | I18: Sporting Goods Stores | K18: Internet Software & Services
B19: Steel & Iron | D19: Housewares & Accessories | E19: Property & Casualty Insurance | F19: Specialized Health Services | G19: Residential Construction | H19: Consumer Services | I19: Staffing & Outsourcing Services | K19: Long Distance Carriers
B20: Synthetics | D20: Meat Products | E20: Property Management | G20: Small Tools & Accessories | H20: Department Stores | I20: Technical Services | K20: Multimedia & Graphics Software
D21: Office Supplies | E21: Real Estate Development | G21: Textile Industrial | H21: Discount, Variety Stores | I21: Toy & Hobby Stores | K21: Networking & Communication Devices
D22: Packaging & Containers | E22: Regional - Mid-Atlantic Banks | G22: Waste Management | H22: Drug Stores | I22: Trucking | K22: Personal Computers
D23: Paper & Paper Products | E23: Regional - Midwest Banks | H23: Drugs Wholesale | I23: Wholesale, Other | K23: Printed Circuit Boards
D24: Personal Products | E24: Regional - Northeast Banks | H24: Education & Training Services | K24: Processing Systems & Products
D25: Photographic Equipment & Supplies | E25: Regional - Pacific Banks | H25: Electronics Stores | K25: Scientific & Technical Instruments
D26: Processed & Packaged Goods | E26: Regional - Southeast Banks | H26: Electronics Wholesale | K26: Security Software & Services
D27: Recreational Goods, Other | E27: Regional - Southwest Banks | H27: Entertainment - Diversified | K27: Semiconductor - Broad Line
D28: Recreational Vehicles | E28: REIT - Diversified | H28: Food Wholesale | K28: Semiconductor - Integrated Circuits
D29: Rubber & Plastics | E29: REIT - Healthcare Facilities | H29: Gaming Activities | K29: Semiconductor - Specialized
D30: Sporting Goods | E30: REIT - Hotel/Motel | H30: General Entertainment | K30: Semiconductor Equipment & Materials
D31: Textile - Apparel Clothing | E31: REIT - Industrial | H31: Grocery Stores | K31: Semiconductor- Memory Chips
D32: Textile - Apparel Footwear & Accessories | E32: REIT - Office | H32: Home Furnishing Stores | K32: Technical & System Software
D33: Tobacco Products, Other | E33: REIT - Residential | H33: Home Improvement Stores | K33: Telecom Services - Domestic
D34: Toys & Games | E34: REIT - Retail | H34: Industrial Equipment Wholesale | K34: Telecom Services - Foreign
D35: Trucks & Other Vehicles | E35: Savings & Loans | H35: Jewelry Stores | K35: Wireless Communications
E36: Surety & Title Insurance | H36: Lodging
H37: Major Airlines
H38: Management Services
H39: Marketing Services
H40: Medical Equipment Wholesale
H41: Movie Production, Theaters
B42: Use this spreadsheet to drill down through the sector level and analyse stocks within sectors | H42: Music & Video Stores
B43: across the United States and Europe by clicking on the embedded links. | H43: Personal Services

Sheet manu_pmi
A1: dates | B1: Apparel, Leather & Allied Products_pmi | C1: Chemical Products_pmi | D1: Computer & Electronic Products_pmi | E1: Electrical Equipment, Appliances & Components_pmi | F1: Fabricated Metal Products_pmi | G1: Food, Beverage & Tobacco Products_pmi | H1: Furniture & Related Products_pmi | I1: Machinery_pmi | J1: Miscellaneous Manufacturing_pmi | K1: Nonmetallic Mineral Products_pmi | L1: Paper Products_pmi | M1: Petroleum & Coal Products_pmi | N1: Plastics & Rubber Products_pmi | O1: Primary Metals_pmi | P1: Printing & Related Support Activities_pmi | Q1: Textile Mills_pmi | R1: Transportation Equipment_pmi | S1: Wood Products_pmi
A2: 43831 | B2: -7 | C2: 2 | D2: 5 | E2: -6 | F2: 1 | G2: 6 | H2: 8 | I2: -1 | J2: 4 | K2: 3 | L2: 0 | M2: -5 | N2: 0 | O2: -2 | P2: -8 | Q2: -4 | R2: -3 | S2: 7
A3: 43862 | B3: 0 | C3: 1 | D3: 6 | E3: 4 | F3: 3 | G3: 7 | H3: 13 | I3: 2 | J3: 5 | K3: -1 | L3: 10 | M3: -3 | N3: 12 | O3: 8 | P3: 11 | Q3: 9 | R3: -2 | S3: 14
A4: 43891 | B4: 8 | C4: 5 | D4: 4 | E4: 0 | F4: -2 | G4: 9 | H4: -3 | I4: -1 | J4: 2 | K4: 0 | L4: 6 | M4: -6 | N4: 1 | O4: 3 | P4: 10 | Q4: -5 | R4: -4 | S4: 7
A5: 43922 | B5: 0 | C5: -1 | D5: -3 | E5: -7 | F5: -11 | G5: 1 | H5: -14 | I5: -9 | J5: -4 | K5: -10 | L5: 2 | M5: -6 | N5: -8 | O5: -2 | P5: -15 | Q5: -12 | R5: -13 | S5: -5
A6: 43952 | B6: 4 | C6: -3 | D6: -2 | E6: -4 | F6: -7 | G6: 3 | H6: 5 | I6: -6 | J6: -5 | K6: 6 | L6: 2 | M6: -8 | N6: -1 | O6: -10 | P6: -11 | Q6: 0 | R6: -9 | S6: 1
A7: 43983 | B7: 9 | C7: 5 | D7: 7 | E7: 1 | F7: -2 | G7: 8 | H7: 11 | I7: -1 | J7: 4 | K7: 3 | L7: 2 | M7: 0 | N7: 6 | O7: -3 | P7: 10 | Q7: 13 | R7: -4 | S7: 12
A8: 44013 | B8: 6 | C8: 7 | D8: 5 | E8: 1 | F8: -1 | G8: 9 | H8: 12 | I8: -2 | J8: 2 | K8: 0 | L8: 0 | M8: 3 | N8: 8 | O8: 4 | P8: 10 | Q8: 11 | R8: -3 | S8: 13
A9: 44044 | B9: 6 | C9: 11 | D9: 10 | E9: 3 | F9: 8 | G9: 13 | H9: -1 | I9: 7 | J9: 4 | K9: 5 | L9: 2 | M9: -2 | N9: 14 | O9: 9 | P9: -3 | Q9: 12 | R9: 1 | S9: 15
A10: 44094 | B10: -4 | C10: 7 | D10: 2 | E10: 10 | F10: 8 | G10: 12 | H10: 11 | I10: 4 | J10: 6 | K10: 9 | L10: 14 | M10: -2 | N10: 5 | O10: -1 | P10: -3 | Q10: 3 | R10: 1 | S10: 13
A11: 44105 | B11: 15 | C11: 6 | D11: 4 | E11: 2 | F11: 14 | G11: 12 | H11: 9 | I11: 10 | J11: 1 | K11: 13 | L11: 8 | M11: 0 | N11: 11 | O11: 5 | P11: -1 | Q11: -2 | R11: 3 | S11: 7
A12: 44136 | B12: 16 | C12: 8 | D12: 6 | E12: 12 | F12: 11 | G12: 1 | H12: 2 | I12: 7 | J12: 4 | K12: 15 | L12: 5 | M12: -1 | N12: 10 | O12: 9 | P12: -2 | Q12: 14 | R12: 3 | S12: 13
A13: 44166 | B13: 16 | C13: 7 | D13: 11 | E13: 3 | F13: 13 | G13: 2 | H13: 15 | I13: 12 | J13: 1 | K13: -1 | L13: 8 | M13: 6 | N13: 9 | O13: 5 | P13: -2 | Q13: 4 | R13: 10 | S13: 14
... A71: 45931 | B71: -11 | C71: -4 | D71: -1 | E71: -5 | F71: 2 | G71: 5 | H71: -10 | I71: -3 | J71: -2 | K71: 1 | L71: -9 | M71: -6 | N71: 3 | O71: 6 | P71: -8 | Q71: -12 | R71: 4 | S71: -7

Sheet manu_rank
A1: dates | B1: Apparel, Leather & Allied Products_rnk | C1: Chemical Products_rnk | D1: Computer & Electronic Products_rnk | E1: Electrical Equipment, Appliances & Components_rnk | F1: Fabricated Metal Products_rnk | G1: Food, Beverage & Tobacco Products_rnk | H1: Furniture & Related Products_rnk | I1: Machinery_rnk | J1: Miscellaneous Manufacturing_rnk | K1: Nonmetallic Mineral Products_rnk | L1: Paper Products_rnk | M1: Petroleum & Coal Products_rnk | N1: Plastics & Rubber Products_rnk | O1: Primary Metals_rnk | P1: Printing & Related Support Activities_rnk | Q1: Textile Mills_rnk | R1: Transportation Equipment_rnk | S1: Wood Products_rnk
A2: 43831 | B2: =_xlfn.RANK.AVG(manu_pmi!B2,manu_pmi!$B2:$S2,1) -> 2 | C2: =_xlfn.RANK.AVG(manu_pmi!C2,manu_pmi!$B2:$S2,1) -> 12 | D2: =_xlfn.RANK.AVG(manu_pmi!D2,manu_pmi!$B2:$S2,1) -> 15 | E2: =_xlfn.RANK.AVG(manu_pmi!E2,manu_pmi!$B2:$S2,1) -> 3 | F2: =_xlfn.RANK.AVG(manu_pmi!F2,manu_pmi!$B2:$S2,1) -> 11 | G2: =_xlfn.RANK.AVG(manu_pmi!G2,manu_pmi!$B2:$S2,1) -> 16 | H2: =_xlfn.RANK.AVG(manu_pmi!H2,manu_pmi!$B2:$S2,1) -> 18 | I2: =_xlfn.RANK.AVG(manu_pmi!I2,manu_pmi!$B2:$S2,1) -> 8 | ... S2: =_xlfn.RANK.AVG(manu_pmi!S2,manu_pmi!$B2:$S2,1) -> 17
A3: 43862 | B3: =_xlfn.RANK.AVG(manu_pmi!B3,manu_pmi!$B3:$S3,1) -> 4 | C3: =_xlfn.RANK.AVG(manu_pmi!C3,manu_pmi!$B3:$S3,1) -> 5 | D3: =_xlfn.RANK.AVG(manu_pmi!D3,manu_pmi!$B3:$S3,1) -> 10 | E3: =_xlfn.RANK.AVG(manu_pmi!E3,manu_pmi!$B3:$S3,1) -> 8 | F3: =_xlfn.RANK.AVG(manu_pmi!F3,manu_pmi!$B3:$S3,1) -> 7 | G3: =_xlfn.RANK.AVG(manu_pmi!G3,manu_pmi!$B3:$S3,1) -> 11 | H3: =_xlfn.RANK.AVG(manu_pmi!H3,manu_pmi!$B3:$S3,1) -> 17 | I3: =_xlfn.RANK.AVG(manu_pmi!I3,manu_pmi!$B3:$S3,1) -> 6 | ... S3: =_xlfn.RANK.AVG(manu_pmi!S3,manu_pmi!$B3:$S3,1) -> 18
A4: 43891 | B4: =_xlfn.RANK.AVG(manu_pmi!B4,manu_pmi!$B4:$S4,1) -> 16 | C4: =_xlfn.RANK.AVG(manu_pmi!C4,manu_pmi!$B4:$S4,1) -> 13 | D4: =_xlfn.RANK.AVG(manu_pmi!D4,manu_pmi!$B4:$S4,1) -> 12 | E4: =_xlfn.RANK.AVG(manu_pmi!E4,manu_pmi!$B4:$S4,1) -> 7.5 | F4: =_xlfn.RANK.AVG(manu_pmi!F4,manu_pmi!$B4:$S4,1) -> 5 | G4: =_xlfn.RANK.AVG(manu_pmi!G4,manu_pmi!$B4:$S4,1) -> 17 | H4: =_xlfn.RANK.AVG(manu_pmi!H4,manu_pmi!$B4:$S4,1) -> 4 | I4: =_xlfn.RANK.AVG(manu_pmi!I4,manu_pmi!$B4:$S4,1) -> 6 | ... S4: =_xlfn.RANK.AVG(manu_pmi!S4,manu_pmi!$B4:$S4,1) -> 15
A5: 43922 | B5: =_xlfn.RANK.AVG(manu_pmi!B5,manu_pmi!$B5:$S5,1) -> 16 | C5: =_xlfn.RANK.AVG(manu_pmi!C5,manu_pmi!$B5:$S5,1) -> 15 | D5: =_xlfn.RANK.AVG(manu_pmi!D5,manu_pmi!$B5:$S5,1) -> 13 | E5: =_xlfn.RANK.AVG(manu_pmi!E5,manu_pmi!$B5:$S5,1) -> 9 | F5: =_xlfn.RANK.AVG(manu_pmi!F5,manu_pmi!$B5:$S5,1) -> 5 | G5: =_xlfn.RANK.AVG(manu_pmi!G5,manu_pmi!$B5:$S5,1) -> 17 | H5: =_xlfn.RANK.AVG(manu_pmi!H5,manu_pmi!$B5:$S5,1) -> 2 | I5: =_xlfn.RANK.AVG(manu_pmi!I5,manu_pmi!$B5:$S5,1) -> 7 | ... S5: =_xlfn.RANK.AVG(manu_pmi!S5,manu_pmi!$B5:$S5,1) -> 11
A6: 43952 | B6: =_xlfn.RANK.AVG(manu_pmi!B6,manu_pmi!$B6:$S6,1) -> 16 | C6: =_xlfn.RANK.AVG(manu_pmi!C6,manu_pmi!$B6:$S6,1) -> 9 | D6: =_xlfn.RANK.AVG(manu_pmi!D6,manu_pmi!$B6:$S6,1) -> 10 | E6: =_xlfn.RANK.AVG(manu_pmi!E6,manu_pmi!$B6:$S6,1) -> 8 | F6: =_xlfn.RANK.AVG(manu_pmi!F6,manu_pmi!$B6:$S6,1) -> 5 | G6: =_xlfn.RANK.AVG(manu_pmi!G6,manu_pmi!$B6:$S6,1) -> 15 | H6: =_xlfn.RANK.AVG(manu_pmi!H6,manu_pmi!$B6:$S6,1) -> 17 | I6: =_xlfn.RANK.AVG(manu_pmi!I6,manu_pmi!$B6:$S6,1) -> 6 | ... S6: =_xlfn.RANK.AVG(manu_pmi!S6,manu_pmi!$B6:$S6,1) -> 13
A7: 43983 | B7: =_xlfn.RANK.AVG(manu_pmi!B7,manu_pmi!$B7:$S7,1) -> 14 | C7: =_xlfn.RANK.AVG(manu_pmi!C7,manu_pmi!$B7:$S7,1) -> 10 | D7: =_xlfn.RANK.AVG(manu_pmi!D7,manu_pmi!$B7:$S7,1) -> 12 | E7: =_xlfn.RANK.AVG(manu_pmi!E7,manu_pmi!$B7:$S7,1) -> 6 | F7: =_xlfn.RANK.AVG(manu_pmi!F7,manu_pmi!$B7:$S7,1) -> 3 | G7: =_xlfn.RANK.AVG(manu_pmi!G7,manu_pmi!$B7:$S7,1) -> 13 | H7: =_xlfn.RANK.AVG(manu_pmi!H7,manu_pmi!$B7:$S7,1) -> 16 | I7: =_xlfn.RANK.AVG(manu_pmi!I7,manu_pmi!$B7:$S7,1) -> 4 | ... S7: =_xlfn.RANK.AVG(manu_pmi!S7,manu_pmi!$B7:$S7,1) -> 17
A8: 44013 | B8: =_xlfn.RANK.AVG(manu_pmi!B8,manu_pmi!$B8:$S8,1) -> 11 | C8: =_xlfn.RANK.AVG(manu_pmi!C8,manu_pmi!$B8:$S8,1) -> 12 | D8: =_xlfn.RANK.AVG(manu_pmi!D8,manu_pmi!$B8:$S8,1) -> 10 | E8: =_xlfn.RANK.AVG(manu_pmi!E8,manu_pmi!$B8:$S8,1) -> 6 | F8: =_xlfn.RANK.AVG(manu_pmi!F8,manu_pmi!$B8:$S8,1) -> 3 | G8: =_xlfn.RANK.AVG(manu_pmi!G8,manu_pmi!$B8:$S8,1) -> 14 | H8: =_xlfn.RANK.AVG(manu_pmi!H8,manu_pmi!$B8:$S8,1) -> 17 | I8: =_xlfn.RANK.AVG(manu_pmi!I8,manu_pmi!$B8:$S8,1) -> 2 | ... S8: =_xlfn.RANK.AVG(manu_pmi!S8,manu_pmi!$B8:$S8,1) -> 18
A9: 44044 | B9: =_xlfn.RANK.AVG(manu_pmi!B9,manu_pmi!$B9:$S9,1) -> 9 | C9: =_xlfn.RANK.AVG(manu_pmi!C9,manu_pmi!$B9:$S9,1) -> 14 | D9: =_xlfn.RANK.AVG(manu_pmi!D9,manu_pmi!$B9:$S9,1) -> 13 | E9: =_xlfn.RANK.AVG(manu_pmi!E9,manu_pmi!$B9:$S9,1) -> 6 | F9: =_xlfn.RANK.AVG(manu_pmi!F9,manu_pmi!$B9:$S9,1) -> 11 | G9: =_xlfn.RANK.AVG(manu_pmi!G9,manu_pmi!$B9:$S9,1) -> 16 | H9: =_xlfn.RANK.AVG(manu_pmi!H9,manu_pmi!$B9:$S9,1) -> 3 | I9: =_xlfn.RANK.AVG(manu_pmi!I9,manu_pmi!$B9:$S9,1) -> 10 | ... S9: =_xlfn.RANK.AVG(manu_pmi!S9,manu_pmi!$B9:$S9,1) -> 18
A10: 44094 | B10: =_xlfn.RANK.AVG(manu_pmi!B10,manu_pmi!$B10:$S10,1) -> 1 | C10: =_xlfn.RANK.AVG(manu_pmi!C10,manu_pmi!$B10:$S10,1) -> 11 | D10: =_xlfn.RANK.AVG(manu_pmi!D10,manu_pmi!$B10:$S10,1) -> 6 | E10: =_xlfn.RANK.AVG(manu_pmi!E10,manu_pmi!$B10:$S10,1) -> 14 | F10: =_xlfn.RANK.AVG(manu_pmi!F10,manu_pmi!$B10:$S10,1) -> 12 | G10: =_xlfn.RANK.AVG(manu_pmi!G10,manu_pmi!$B10:$S10,1) -> 16 | H10: =_xlfn.RANK.AVG(manu_pmi!H10,manu_pmi!$B10:$S10,1) -> 15 | I10: =_xlfn.RANK.AVG(manu_pmi!I10,manu_pmi!$B10:$S10,1) -> 8 | ... S10: =_xlfn.RANK.AVG(manu_pmi!S10,manu_pmi!$B10:$S10,1) -> 17
A11: 44105 | B11: =_xlfn.RANK.AVG(manu_pmi!B11,manu_pmi!$B11:$S11,1) -> 18 | C11: =_xlfn.RANK.AVG(manu_pmi!C11,manu_pmi!$B11:$S11,1) -> 9 | D11: =_xlfn.RANK.AVG(manu_pmi!D11,manu_pmi!$B11:$S11,1) -> 7 | E11: =_xlfn.RANK.AVG(manu_pmi!E11,manu_pmi!$B11:$S11,1) -> 5 | F11: =_xlfn.RANK.AVG(manu_pmi!F11,manu_pmi!$B11:$S11,1) -> 17 | G11: =_xlfn.RANK.AVG(manu_pmi!G11,manu_pmi!$B11:$S11,1) -> 15 | H11: =_xlfn.RANK.AVG(manu_pmi!H11,manu_pmi!$B11:$S11,1) -> 12 | I11: =_xlfn.RANK.AVG(manu_pmi!I11,manu_pmi!$B11:$S11,1) -> 13 | ... S11: =_xlfn.RANK.AVG(manu_pmi!S11,manu_pmi!$B11:$S11,1) -> 10
A12: 44136 | B12: =_xlfn.RANK.AVG(manu_pmi!B12,manu_pmi!$B12:$S12,1) -> 18 | C12: =_xlfn.RANK.AVG(manu_pmi!C12,manu_pmi!$B12:$S12,1) -> 10 | D12: =_xlfn.RANK.AVG(manu_pmi!D12,manu_pmi!$B12:$S12,1) -> 8 | E12: =_xlfn.RANK.AVG(manu_pmi!E12,manu_pmi!$B12:$S12,1) -> 14 | F12: =_xlfn.RANK.AVG(manu_pmi!F12,manu_pmi!$B12:$S12,1) -> 13 | G12: =_xlfn.RANK.AVG(manu_pmi!G12,manu_pmi!$B12:$S12,1) -> 3 | H12: =_xlfn.RANK.AVG(manu_pmi!H12,manu_pmi!$B12:$S12,1) -> 4 | I12: =_xlfn.RANK.AVG(manu_pmi!I12,manu_pmi!$B12:$S12,1) -> 9 | ... S12: =_xlfn.RANK.AVG(manu_pmi!S12,manu_pmi!$B12:$S12,1) -> 15
A13: 44166 | B13: =_xlfn.RANK.AVG(manu_pmi!B13,manu_pmi!$B13:$S13,1) -> 18 | C13: =_xlfn.RANK.AVG(manu_pmi!C13,manu_pmi!$B13:$S13,1) -> 9 | D13: =_xlfn.RANK.AVG(manu_pmi!D13,manu_pmi!$B13:$S13,1) -> 13 | E13: =_xlfn.RANK.AVG(manu_pmi!E13,manu_pmi!$B13:$S13,1) -> 5 | F13: =_xlfn.RANK.AVG(manu_pmi!F13,manu_pmi!$B13:$S13,1) -> 15 | G13: =_xlfn.RANK.AVG(manu_pmi!G13,manu_pmi!$B13:$S13,1) -> 4 | H13: =_xlfn.RANK.AVG(manu_pmi!H13,manu_pmi!$B13:$S13,1) -> 17 | I13: =_xlfn.RANK.AVG(manu_pmi!I13,manu_pmi!$B13:$S13,1) -> 14 | ... S13: =_xlfn.RANK.AVG(manu_pmi!S13,manu_pmi!$B13:$S13,1) -> 16
... A36: 44866 | B36: =_xlfn.RANK.AVG(manu_pmi!B36,manu_pmi!$B36:$S36,1) -> 18 | C36: =_xlfn.RANK.AVG(manu_pmi!C36,manu_pmi!$B36:$S36,1) -> 7 | D36: =_xlfn.RANK.AVG(manu_pmi!D36,manu_pmi!$B36:$S36,1) -> 9 | E36: =_xlfn.RANK.AVG(manu_pmi!E36,manu_pmi!$B36:$S36,1) -> 12 | F36: =_xlfn.RANK.AVG(manu_pmi!F36,manu_pmi!$B36:$S36,1) -> 5 | G36: =_xlfn.RANK.AVG(manu_pmi!G36,manu_pmi!$B36:$S36,1) -> 10 | H36: =_xlfn.RANK.AVG(manu_pmi!H36,manu_pmi!$B36:$S36,1) -> 6 | I36: =_xlfn.RANK.AVG(manu_pmi!I36,manu_pmi!$B36:$S36,1) -> 11 | ... S36: =_xlfn.RANK.AVG(manu_pmi!S36,manu_pmi!$B36:$S36,1) -> 2
A37: 44896 | B37: 8 | C37: 3 | D37: 9 | E37: 6 | F37: 2 | G37: 11 | H37: 7 | I37: 10 | J37: 13 | K37: 15 | L37: 4 | M37: 17 | N37: 5 | O37: 18 | P37: 15 | Q37: 15 | R37: 12 | S37: 1
A38: 44927 | B38: 5 | C38: 11 | D38: 15 | E38: 7 | F38: 10 | G38: 13 | H38: 4 | I38: 12 | J38: 18 | K38: 9 | L38: 3 | M38: 14 | N38: 6 | O38: 8 | P38: 2 | Q38: 16 | R38: 17 | S38: 1
A39: 44958 | B39: 18 | C39: 9 | D39: 11 | E39: 15 | F39: 12 | G39: 8 | H39: 5 | I39: 13 | J39: 14 | K39: 6 | L39: 2 | M39: 16 | N39: 7 | O39: 10 | P39: 1 | Q39: 4 | R39: 17 | S39: 3
A40: 44986 | B40: 8 | C40: 9 | D40: 10 | E40: 11 | F40: 16 | G40: 7 | H40: 1 | I40: 13 | J40: 17 | K40: 2 | L40: 5 | M40: 15 | N40: 4 | O40: 14 | P40: 18 | Q40: 3 | R40: 12 | S40: 6
A41: 45017 | B41: 17 | C41: 6 | D41: 9 | E41: 4 | F41: 15 | G41: 10 | H41: 1 | I41: 7 | J41: 11 | K41: 3 | L41: 12.5 | M41: 16 | N41: 5 | O41: 8 | P41: 18 | Q41: 12.5 | R41: 14 | S41: 2
A42: 45047 | B42: 3 | C42: 8 | D42: 10 | E42: 11 | F42: 15 | G42: 9 | H42: 17 | I42: 13 | J42: 14 | K42: 18 | L42: 5 | M42: 7 | N42: 12 | O42: 2 | P42: 6 | Q42: 4 | R42: 16 | S42: 1
A43: 45078 | B43: 13 | C43: 4 | D43: 7 | E43: 6 | F43: 9 | G43: 10 | H43: 13 | I43: 11 | J43: 5 | K43: 17 | L43: 8 | M43: 13 | N43: 1 | O43: 16 | P43: 18 | Q43: 3 | R43: 15 | S43: 2
A44: 45108 | B44: 1 | C44: 7 | D44: 6 | E44: 10 | F44: 13 | G44: 9 | H44: 17 | I44: 16 | J44: 12 | K44: 15 | L44: 3 | M44: 18 | N44: 2 | O44: 8 | P44: 11 | Q44: 4 | R44: 14 | S44: 5
A45: 45139 | B45: 1 | C45: 8 | D45: 9 | E45: 7 | F45: 5 | G45: 16 | H45: 2 | I45: 13 | J45: 14 | K45: 12 | L45: 10 | M45: 15 | N45: 3 | O45: 4 | P45: 18 | Q45: 6 | R45: 17 | S45: 11
A46: 45170 | B46: 12.5 | C46: 10 | D46: 7 | E46: 9 | F46: 5 | G46: 17 | H46: 2 | I46: 8 | J46: 12.5 | K46: 18 | L46: 4 | M46: 14 | N46: 3 | O46: 15 | P46: 1 | Q46: 16 | R46: 11 | S46: 6
A47: 45200 | B47: 15 | C47: 12 | D47: 7 | E47: 3 | F47: 5 | G47: 18 | H47: 8 | I47: 4 | J47: 10 | K47: 15 | L47: 9 | M47: 15 | N47: 17 | O47: 11 | P47: 1 | Q47: 2 | R47: 13 | S47: 6
A48: 45231 | B48: 5 | C48: 11 | D48: 4 | E48: 3 | F48: 12 | G48: 18 | H48: 9 | I48: 7 | J48: 10 | K48: 17 | L48: 1 | M48: 15 | N48: 14 | O48: 8 | P48: 2 | Q48: 6 | R48: 16 | S48: 13
... A71: 45931 | B71: 2 | C71: 9 | D71: 12 | E71: 8 | F71: 14 | G71: 17 | H71: 3 | I71: 10 | J71: 11 | K71: 13 | L71: 4 | M71: 7 | N71: 15 | O71: 18 | P71: 5 | Q71: 1 | R71: 16 | S71: 6

Sheet manu_rank_pct
A1: dates | B1: Apparel, Leather & Allied Products_rnk | C1: Chemical Products_rnk | D1: Computer & Electronic Products_rnk | E1: Electrical Equipment, Appliances & Components_rnk | F1: Fabricated Metal Products_rnk | G1: Food, Beverage & Tobacco Products_rnk | H1: Furniture & Related Products_rnk | I1: Machinery_rnk | J1: Miscellaneous Manufacturing_rnk | K1: Nonmetallic Mineral Products_rnk | L1: Paper Products_rnk | M1: Petroleum & Coal Products_rnk | N1: Plastics & Rubber Products_rnk | O1: Primary Metals_rnk | P1: Printing & Related Support Activities_rnk | Q1: Textile Mills_rnk | R1: Transportation Equipment_rnk | S1: Wood Products_rnk
A2: 43831 | B2: =manu_rank!B2/171 -> 0.011695906 | C2: =manu_rank!C2/171 -> 0.070175439 | D2: =manu_rank!D2/171 -> 0.087719298 | E2: =manu_rank!E2/171 -> 0.01754386 | F2: =manu_rank!F2/171 -> 0.064327485 | G2: =manu_rank!G2/171 -> 0.093567251 | H2: =manu_rank!H2/171 -> 0.10526316 | I2: =manu_rank!I2/171 -> 0.046783626 | ... S2: =manu_rank!S2/171 -> 0.099415205
A3: 43862 | B3: =manu_rank!B3/171 -> 0.023391813 | C3: =manu_rank!C3/171 -> 0.029239766 | D3: =manu_rank!D3/171 -> 0.058479532 | E3: =manu_rank!E3/171 -> 0.046783626 | F3: =manu_rank!F3/171 -> 0.040935673 | G3: =manu_rank!G3/171 -> 0.064327485 | H3: =manu_rank!H3/171 -> 0.099415205 | I3: =manu_rank!I3/171 -> 0.035087719 | ... S3: =manu_rank!S3/171 -> 0.10526316
A4: 43891 | B4: =manu_rank!B4/171 -> 0.093567251 | C4: =manu_rank!C4/171 -> 0.076023392 | D4: =manu_rank!D4/171 -> 0.070175439 | E4: =manu_rank!E4/171 -> 0.043859649 | F4: =manu_rank!F4/171 -> 0.029239766 | G4: =manu_rank!G4/171 -> 0.099415205 | H4: =manu_rank!H4/171 -> 0.023391813 | I4: =manu_rank!I4/171 -> 0.035087719 | ... S4: =manu_rank!S4/171 -> 0.087719298
A5: 43922 | B5: =manu_rank!B5/171 -> 0.093567251 | C5: =manu_rank!C5/171 -> 0.087719298 | D5: =manu_rank!D5/171 -> 0.076023392 | E5: =manu_rank!E5/171 -> 0.052631579 | F5: =manu_rank!F5/171 -> 0.029239766 | G5: =manu_rank!G5/171 -> 0.099415205 | H5: =manu_rank!H5/171 -> 0.011695906 | I5: =manu_rank!I5/171 -> 0.040935673 | ... S5: =manu_rank!S5/171 -> 0.064327485
A6: 43952 | B6: =manu_rank!B6/171 -> 0.093567251 | C6: =manu_rank!C6/171 -> 0.052631579 | D6: =manu_rank!D6/171 -> 0.058479532 | E6: =manu_rank!E6/171 -> 0.046783626 | F6: =manu_rank!F6/171 -> 0.029239766 | G6: =manu_rank!G6/171 -> 0.087719298 | H6: =manu_rank!H6/171 -> 0.099415205 | I6: =manu_rank!I6/171 -> 0.035087719 | ... S6: =manu_rank!S6/171 -> 0.076023392
A7: 43983 | B7: =manu_rank!B7/171 -> 0.081871345 | C7: =manu_rank!C7/171 -> 0.058479532 | D7: =manu_rank!D7/171 -> 0.070175439 | E7: =manu_rank!E7/171 -> 0.035087719 | F7: =manu_rank!F7/171 -> 0.01754386 | G7: =manu_rank!G7/171 -> 0.076023392 | H7: =manu_rank!H7/171 -> 0.093567251 | I7: =manu_rank!I7/171 -> 0.023391813 | ... S7: =manu_rank!S7/171 -> 0.099415205
A8: 44013 | B8: =manu_rank!B8/171 -> 0.064327485 | C8: =manu_rank!C8/171 -> 0.070175439 | D8: =manu_rank!D8/171 -> 0.058479532 | E8: =manu_rank!E8/171 -> 0.035087719 | F8: =manu_rank!F8/171 -> 0.01754386 | G8: =manu_rank!G8/171 -> 0.081871345 | H8: =manu_rank!H8/171 -> 0.099415205 | I8: =manu_rank!I8/171 -> 0.011695906 | ... S8: =manu_rank!S8/171 -> 0.10526316
A9: 44044 | B9: =manu_rank!B9/171 -> 0.052631579 | C9: =manu_rank!C9/171 -> 0.081871345 | D9: =manu_rank!D9/171 -> 0.076023392 | E9: =manu_rank!E9/171 -> 0.035087719 | F9: =manu_rank!F9/171 -> 0.064327485 | G9: =manu_rank!G9/171 -> 0.093567251 | H9: =manu_rank!H9/171 -> 0.01754386 | I9: =manu_rank!I9/171 -> 0.058479532 | ... S9: =manu_rank!S9/171 -> 0.10526316
A10: 44094 | B10: =manu_rank!B10/171 -> 0.0058479532 | C10: =manu_rank!C10/171 -> 0.064327485 | D10: =manu_rank!D10/171 -> 0.035087719 | E10: =manu_rank!E10/171 -> 0.081871345 | F10: =manu_rank!F10/171 -> 0.070175439 | G10: =manu_rank!G10/171 -> 0.093567251 | H10: =manu_rank!H10/171 -> 0.087719298 | I10: =manu_rank!I10/171 -> 0.046783626 | ... S10: =manu_rank!S10/171 -> 0.099415205
A11: 44105 | B11: =manu_rank!B11/171 -> 0.10526316 | C11: =manu_rank!C11/171 -> 0.052631579 | D11: =manu_rank!D11/171 -> 0.040935673 | E11: =manu_rank!E11/171 -> 0.029239766 | F11: =manu_rank!F11/171 -> 0.099415205 | G11: =manu_rank!G11/171 -> 0.087719298 | H11: =manu_rank!H11/171 -> 0.070175439 | I11: =manu_rank!I11/171 -> 0.076023392 | ... S11: =manu_rank!S11/171 -> 0.058479532
A12: 44136 | B12: =manu_rank!B12/171 -> 0.10526316 | C12: =manu_rank!C12/171 -> 0.058479532 | D12: =manu_rank!D12/171 -> 0.046783626 | E12: =manu_rank!E12/171 -> 0.081871345 | F12: =manu_rank!F12/171 -> 0.076023392 | G12: =manu_rank!G12/171 -> 0.01754386 | H12: =manu_rank!H12/171 -> 0.023391813 | I12: =manu_rank!I12/171 -> 0.052631579 | ... S12: =manu_rank!S12/171 -> 0.087719298
A13: 44166 | B13: =manu_rank!B13/171 -> 0.10526316 | C13: =manu_rank!C13/171 -> 0.052631579 | D13: =manu_rank!D13/171 -> 0.076023392 | E13: =manu_rank!E13/171 -> 0.029239766 | F13: =manu_rank!F13/171 -> 0.087719298 | G13: =manu_rank!G13/171 -> 0.023391813 | H13: =manu_rank!H13/171 -> 0.099415205 | I13: =manu_rank!I13/171 -> 0.081871345 | ... S13: =manu_rank!S13/171 -> 0.093567251
... A71: 45931 | B71: =manu_rank!B71/171 -> 0.011695906 | C71: =manu_rank!C71/171 -> 0.052631579 | D71: =manu_rank!D71/171 -> 0.070175439 | E71: =manu_rank!E71/171 -> 0.046783626 | F71: =manu_rank!F71/171 -> 0.081871345 | G71: =manu_rank!G71/171 -> 0.099415205 | H71: =manu_rank!H71/171 -> 0.01754386 | I71: =manu_rank!I71/171 -> 0.058479532 | ... S71: =manu_rank!S71/171 -> 0.035087719

Sheet manu_no
A1: dates | B1: Apparel, Leather & Allied Products_no | C1: Chemical Products_no | D1: Computer & Electronic Products_no | E1: Electrical Equipment, Appliances & Components_no | F1: Fabricated Metal Products_no | G1: Food, Beverage & Tobacco Products_no | H1: Furniture & Related Products_no | I1: Machinery_no | J1: Miscellaneous Manufacturing_no | K1: Nonmetallic Mineral Products_no | L1: Paper Products_no | M1: Petroleum & Coal Products_no | N1: Plastics & Rubber Products_no | O1: Primary Metals_no | P1: Printing & Related Support Activities_no | Q1: Textile Mills_no | R1: Transportation Equipment_no | S1: Wood Products_no
A2: 43831 | B2: -3 | C2: 3 | D2: 6 | E2: -2 | F2: 2 | G2: 5 | H2: 9 | I2: 1 | J2: 7 | K2: 0 | L2: 0 | M2: 0 | N2: 4 | O2: 8 | P2: -5 | Q2: -4 | R2: -1 | S2: 10
A3: 43862 | B3: 12 | C3: 1 | D3: 7 | E3: 11 | F3: 4 | G3: 2 | H3: 8 | I3: 3 | J3: 6 | K3: 5 | L3: 15 | M3: -2 | N3: 10 | O3: 13 | P3: 14 | Q3: 9 | R3: -1 | S3: 16
A4: 43891 | B4: 7 | C4: 2 | D4: 1 | E4: 5 | F4: -2 | G4: 6 | H4: -4 | I4: -1 | J4: -3 | K4: -5 | L4: 3 | M4: -9 | N4: 4 | O4: -7 | P4: 8 | Q4: -6 | R4: -8 | S4: 9
A5: 43922 | B5: 0 | C5: -1 | D5: -4 | E5: -7 | F5: -9 | G5: 2 | H5: -10 | I5: -8 | J5: -5 | K5: -13 | L5: 1 | M5: -11 | N5: -6 | O5: -2 | P5: -14 | Q5: -15 | R5: -12 | S5: -3
A6: 43952 | B6: 0 | C6: -3 | D6: -6 | E6: -1 | F6: -9 | G6: 2 | H6: 0 | I6: -4 | J6: -8 | K6: 3 | L6: 1 | M6: -7 | N6: -5 | O6: -10 | P6: -12 | Q6: 4 | R6: -11 | S6: -2
A7: 43983 | B7: 0 | C7: 6 | D7: 1 | E7: 4 | F7: -2 | G7: 7 | H7: 5 | I7: 2 | J7: 3 | K7: 0 | L7: 0 | M7: 0 | N7: 10 | O7: 0 | P7: 8 | Q7: 11 | R7: -1 | S7: 9
A8: 44013 | B8: 0 | C8: 9 | D8: 2 | E8: 8 | F8: 6 | G8: 7 | H8: 12 | I8: 1 | J8: 4 | K8: 0 | L8: -1 | M8: 5 | N8: 10 | O8: 11 | P8: 0 | Q8: -2 | R8: 3 | S8: 13
A9: 44044 | B9: 0 | C9: 11 | D9: 12 | E9: 1 | F9: 5 | G9: 7 | H9: 4 | I9: 9 | J9: 3 | K9: 10 | L9: 8 | M9: 6 | N9: 14 | O9: 15 | P9: -1 | Q9: 0 | R9: 2 | S9: 13
A10: 44094 | B10: -3 | C10: 2 | D10: 0 | E10: 11 | F10: 5 | G10: 6 | H10: 9 | I10: 3 | J10: -1 | K10: 4 | L10: 8 | M10: 0 | N10: 10 | O10: 0 | P10: 7 | Q10: -2 | R10: 1 | S10: 12
A11: 44105 | B11: 16 | C11: 5 | D11: 9 | E11: 11 | F11: 12 | G11: 7 | H11: 10 | I11: 6 | J11: 1 | K11: 2 | L11: 8 | M11: 4 | N11: 14 | O11: 13 | P11: 0 | Q11: -1 | R11: 3 | S11: 15
A12: 44136 | B12: 15 | C12: 7 | D12: 5 | E12: 11 | F12: 10 | G12: 3 | H12: 0 | I12: 6 | J12: 4 | K12: 8 | L12: 9 | M12: -1 | N12: 14 | O12: 2 | P12: -2 | Q12: 13 | R12: 1 | S12: 12
A13: 44166 | B13: 13 | C13: 3 | D13: 8 | E13: 2 | F13: 7 | G13: 1 | H13: 11 | I13: 9 | J13: -1 | K13: -3 | L13: 0 | M13: 10 | N13: 5 | O13: 4 | P13: 0 | Q13: -2 | R13: 6 | S13: 12
... A71: 45931 | B71: -11 | C71: -4 | D71: -3 | E71: -1 | F71: 2 | G71: 0 | H71: -7 | I71: -1 | J71: -2 | K71: -6 | L71: -9 | M71: -8 | N71: 3 | O71: 4 | P71: 0 | Q71: -10 | R71: 1 | S71: 0

Sheet ISM Non-Manu
W1: https://etfdb.com/etf/XLV/#etf-holdings&sort_name=weight&sort_order=desc&page=1 | AB1: https://money.usnews.com/investing/stocks/metal-fabrication
B2: WIKIPEDIA | C2: 3 | W2: https://www.nasdaq.com/markets/barchart-sectors.aspx | AB2: https://etfdb.com/etfs/ | AD2: https://etfdb.com/etfs/
B3: Yahoo Finance Screener | C3: 6 | W3: https://www.barchart.com/stocks/sectors/rankings | AD3: https://www.instituteforsupplymanagement.org/news/content.cfm?ItemNumber=28859
B4: Link(s) | C4: Past __ Mnths | D4: ( + ) Count | E4: Link | F4: Link | G4: Link | H4: Link | I4: Link | J4: Link | K4: Link | L4: Link | M4: Link | N4: Link | O4: Link | P4: Link | Q4: Link | R4: Link | S4: Link | T4: Link | W4: https://www.macrotrends.net/stocks/sector/2/consumer-discretionary
B5: Sectors | C5: 3 | E5: 43556 | F5: 43586 | G5: 43617 | H5: 43647 | I5: 43678 | J5: 43709 | K5: 43739 | L5: 43770 | M5: 43800 | N5: 43831 | O5: 43862 | P5: 43891 | Q5: 43922 | R5: 43952 | S5: 43983 | T5: 44013 | U5: 44044 | V5: 44094 | W5: 44105 | X5: 44136 | Y5: 44166 | Z5: 44197 | AA5: 44228 | AB5: 44256 | AC5: 44287 | AD5: 44317 | AE5: 44348 | AF5: 44378 | AG5: 44409 | AH5: 44440 | AI5: 44470 | AJ5: 44501 | AK5: 44531 | AL5: 44562 | AM5: 44593 | AN5: 44621 | AO5: 44652 | AP5: 44682 | AQ5: 44713 | AR5: 44743 | AS5: 44774 | AT5: 44805 | AU5: 44835 | AV5: 44866 | AW5: 44896 | AX5: 44927 | AY5: 44958 | AZ5: 44986 | BA5: 45017 | BB5: 45047 | BC5: 45078 | BD5: 45108 | BE5: 45139 | BF5: 45170 | BG5: 45200 | BH5: 45231 | BI5: 45261 | BJ5: 45292 | BK5: 45323 | BL5: 45352 | BM5: 45383 | BN5: 45413 | BO5: 45444 | BP5: 45474 | BQ5: 45505 | BR5: 45536 | BS5: 45566 | BT5: 45597 | BU5: 45627 | BV5: 45658 | BW5: 45689 | BX5: 45717 | BY5: 45748 | BZ5: 45778 | CA5: 45809 | CB5: 45839 | CC5: 45870 | CD5: 45901 | CE5: 45931
A6: AVERAGE | E6: =AVERAGE(E7:E24) -> 6.6666667 | F6: =AVERAGE(F7:F24) -> 7.5 | G6: =AVERAGE(G7:G24) -> 7.6666667 | H6: =AVERAGE(H7:H24) -> 4.2222222 | I6: =AVERAGE(I7:I24) -> 7.5 | J6: =AVERAGE(J7:J24) -> 4.5 | K6: =AVERAGE(K7:K24) -> 4.2222222 | L6: =AVERAGE(L7:L24) -> 3.5 | ... CE6: =AVERAGE(CE7:CE24) -> 2.5
A7: PMI Itself | B7: Accommodation & Food Services | D7: =SUM(S7:X7) -> 60 | E7: 12 | F7: 16 | G7: 13 | H7: 13 | I7: 15 | J7: 8 | K7: 6 | L7: 9 | M7: 6 | N7: 7 | O7: 16 | P7: 0 | Q7: -6 | R7: -6 | S7: 13 | T7: 2 | U7: 12 | V7: 9 | W7: 14 | X7: 10 | Y7: -3 | Z7: 6 | AA7: 17 | AB7: 12 | AC7: 1 | AD7: 6 | AE7: 10 | AF7: 15 | AG7: 17 | AH7: 11 | AI7: 8 | AJ7: 1 | AK7: 16 | AL7: 1 | AM7: -1 | AN7: 12 | AO7: 13 | AP7: 7 | AQ7: 7 | AR7: 0 | AS7: 0 | AT7: -3 | AU7: 12 | AV7: 4 | AW7: 5 | AX7: 4 | AY7: 1 | AZ7: 10 | BA7: 11 | BB7: 11 | BC7: 15 | BD7: 12 | BE7: 12 | BF7: -3 | BG7: 0 | BH7: 8 | BI7: 8 | BJ7: 5 | BK7: 10 | BL7: 12 | BM7: 12 | BN7: -2 | BO7: 0 | BP7: 9 | BQ7: -3 | BR7: 10 | BS7: 11 | BT7: 14 | BU7: 3 | BV7: 13 | BW7: 4 | BX7: 10 | BY7: 11 | BZ7: 10 | CA7: 0 | CB7: -7 | CC7: -4 | CD7: 10 | CE7: 11
B8: Agriculture, Forestry, Fishing & Hunting | D8: =SUM(S8:X8) -> 41 | E8: 11 | F8: 0 | G8: 0 | H8: -4 | I8: 8 | J8: 9 | K8: 13 | L8: -5 | M8: 0 | N8: 12 | O8: -1 | P8: 0 | Q8: -15 | R8: 4 | S8: 14 | T8: 3 | U8: 3 | V8: 5 | W8: 12 | X8: 4 | Y8: 7 | Z8: 7 | AA8: 4 | AB8: 13 | AC8: -1 | AD8: 4 | AE8: -1 | AF8: 0 | AG8: 4 | AH8: -1 | AI8: 6 | AJ8: 15 | AK8: 0 | AL8: -3 | AM8: -2 | AN8: -1 | AO8: 1 | AP8: -3 | AQ8: 4 | AR8: -3 | AS8: -2 | AT8: 12 | AU8: 15 | AV8: 11 | AW8: 0 | AX8: 10 | AY8: 13 | AZ8: 6 | BA8: -2 | BB8: -6 | BC8: -3 | BD8: -3 | BE8: -5 | BF8: -5 | BG8: -4 | BH8: 15 | BI8: 9 | BJ8: 9 | BK8: 5 | BL8: 10 | BM8: 10 | BN8: -4 | BO8: -9 | BP8: -8 | BQ8: -7 | BR8: -4 | BS8: 0 | BT8: 10 | BU8: -4 | BV8: 14 | BW8: 10 | BX8: 4 | BY8: -6 | BZ8: -5 | CA8: -6 | CB8: -3 | CC8: 0 | CD8: -6 | CE8: 4
B9: Arts, Entertainment & Recreation | D9: =SUM(S9:X9) -> 45 | E9: 0 | F9: -1 | G9: -1 | H9: -5 | I9: 4 | J9: 0 | K9: 5 | L9: 10 | M9: 10 | N9: -3 | O9: -2 | P9: -7 | Q9: -16 | R9: -13 | S9: 5 | T9: 15 | U9: 15 | V9: 16 | W9: -2 | X9: -4 | Y9: -4 | Z9: -4 | AA9: 13 | AB9: 18 | AC9: 17 | AD9: 15 | AE9: 16 | AF9: 17 | AG9: -1 | AH9: 16 | AI9: 15 | AJ9: 7 | AK9: 8 | AL9: -2 | AM9: -3 | AN9: 16 | AO9: 2 | AP9: 4 | AQ9: 14 | AR9: 0 | AS9: -1 | AT9: -2 | AU9: 14 | AV9: 0 | AW9: 7 | AX9: -6 | AY9: 4 | AZ9: 12 | BA9: 14 | BB9: 6 | BC9: 14 | BD9: -2 | BE9: 10 | BF9: -4 | BG9: 12 | BH9: 12 | BI9: -8 | BJ9: -3 | BK9: -3 | BL9: 0 | BM9: -4 | BN9: -3 | BO9: 0 | BP9: 10 | BQ9: 10 | BR9: 0 | BS9: 0 | BT9: 13 | BU9: 8 | BV9: 0 | BW9: 0 | BX9: -4 | BY9: 6 | BZ9: 9 | CA9: 7 | CB9: -2 | CC9: 10 | CD9: 0 | CE9: -6
B10: Construction | D10: =SUM(S10:X10) -> 59 | E10: 13 | F10: 13 | G10: 10 | H10: 8 | I10: 11 | J10: 11 | K10: 4 | L10: -2 | M10: -1 | N10: 4 | O10: 10 | P10: 4 | Q10: -11 | R10: -11 | S10: 9 | T10: 9 | U10: 9 | V10: 8 | W10: 15 | X10: 9 | Y10: 2 | Z10: 13 | AA10: 14 | AB10: 14 | AC10: 14 | AD10: 16 | AE10: 7 | AF10: 7 | AG10: 15 | AH10: 10 | AI10: 12 | AJ10: 9 | AK10: 14 | AL10: 15 | AM10: 14 | AN10: 14 | AO10: 17 | AP10: 13 | AQ10: 15 | AR10: 9 | AS10: 11 | AT10: 2 | AU10: 11 | AV10: 9 | AW10: -2 | AX10: -4 | AY10: 11 | AZ10: 2 | BA10: 3 | BB10: 5 | BC10: 4 | BD10: 13 | BE10: 4 | BF10: 6 | BG10: 9 | BH10: 3 | BI10: -2 | BJ10: 4 | BK10: 14 | BL10: 8 | BM10: 11 | BN10: 7 | BO10: 5 | BP10: 7 | BQ10: -5 | BR10: 5 | BS10: 9 | BT10: 2 | BU10: 0 | BV10: 4 | BW10: 6 | BX10: 3 | BY10: -1 | BZ10: -3 | CA10: -5 | CB10: -6 | CC10: -1 | CD10: -5 | CE10: -2
B11: Educational Services | D11: =SUM(S11:X11) -> 30 | E11: 3 | F11: 15 | G11: 9 | H11: -1 | I11: 0 | J11: -4 | K11: -5 | L11: 0 | M11: -6 | N11: 9 | O11: 5 | P11: -1 | Q11: -4 | R11: -10 | S11: 0 | T11: 10 | U11: 4 | V11: 6 | W11: 11 | X11: -1 | Y11: 1 | Z11: -3 | AA11: 3 | AB11: 2 | AC11: 3 | AD11: 1 | AE11: 2 | AF11: 3 | AG11: 14 | AH11: 14 | AI11: 10 | AJ11: 2 | AK11: 1 | AL11: 7 | AM11: 12 | AN11: 17 | AO11: 10 | AP11: 11 | AQ11: 1 | AR11: 8 | AS11: 10 | AT11: 13 | AU11: 5 | AV11: 1 | AW11: -1 | AX11: 5 | AY11: 6 | AZ11: 11 | BA11: 6 | BB11: 1 | BC11: 11 | BD11: 4 | BE11: 5 | BF11: 1 | BG11: 4 | BH11: 1 | BI11: -4 | BJ11: 2 | BK11: 2 | BL11: 9 | BM11: 6 | BN11: 10 | BO11: 2 | BP11: -2 | BQ11: 2 | BR11: 2 | BS11: 4 | BT11: -1 | BU11: -5 | BV11: 8 | BW11: -1 | BX11: -3 | BY11: 2 | BZ11: 5 | CA11: -1 | CB11: -4 | CC11: 7 | CD11: 5 | CE11: 1
B12: Finance & Insurance | D12: =SUM(S12:X12) -> 33 | E12: 2 | F12: 3 | G12: 14 | H12: 5 | I12: 6 | J12: 5 | K12: 3 | L12: 7 | M12: 1 | N12: 6 | O12: 13 | P12: 5 | Q12: 1 | R12: 3 | S12: 3 | T12: 6 | U12: 5 | V12: 4 | W12: 10 | X12: 5 | Y12: 9 | Z12: 11 | AA12: 7 | AB12: 8 | AC12: 7 | AD12: 11 | AE12: 3 | AF12: 2 | AG12: 3 | AH12: 1 | AI12: 4 | AJ12: 4 | AK12: 4 | AL12: 6 | AM12: 6 | AN12: 4 | AO12: 6 | AP12: 0 | AQ12: 5 | AR12: -1 | AS12: 4 | AT12: 4 | AU12: 4 | AV12: 0 | AW12: 1 | AX12: -2 | AY12: 5 | AZ12: -5 | BA12: 2 | BB12: -1 | BC12: 3 | BD12: -1 | BE12: 3 | BF12: 7 | BG12: 8 | BH12: 5 | BI12: -1 | BJ12: -1 | BK12: 6 | BL12: 2 | BM12: 4 | BN12: 3 | BO12: 3 | BP12: 3 | BQ12: 4 | BR12: 6 | BS12: 10 | BT12: 8 | BU12: 9 | BV12: 10 | BW12: 13 | BX12: 8 | BY12: -4 | BZ12: -4 | CA12: 0 | CB12: 9 | CC12: 0 | CD12: 3 | CE12: -4
B13: Health Care & Social Assistance | D13: =SUM(S13:X13) -> 75 | E13: 9 | F13: 5 | G13: 12 | H13: 1 | I13: 5 | J13: 2 | K13: 7 | L13: 11 | M13: 8 | N13: 10 | O13: 9 | P13: 9 | Q13: -1 | R13: -2 | S13: 10 | T13: 14 | U13: 14 | V13: 12 | W13: 13 | X13: 12 | Y13: 11 | Z13: 9 | AA13: 10 | AB13: 6 | AC13: 5 | AD13: 5 | AE13: 6 | AF13: 6 | AG13: 7 | AH13: 5 | AI13: 7 | AJ13: 8 | AK13: 9 | AL13: 13 | AM13: 7 | AN13: 1 | AO13: 4 | AP13: 2 | AQ13: 10 | AR13: 4 | AS13: 6 | AT13: 5 | AU13: 2 | AV13: 8 | AW13: 10 | AX13: 2 | AY13: 2 | AZ13: 3 | BA13: 5 | BB13: -2 | BC13: 1 | BD13: 5 | BE13: -2 | BF13: 8 | BG13: 3 | BH13: 14 | BI13: 7 | BJ13: 10 | BK13: 11 | BL13: 1 | BM13: 3 | BN13: 12 | BO13: 6 | BP13: 2 | BQ13: 5 | BR13: 7 | BS13: 2 | BT13: 12 | BU13: 6 | BV13: 9 | BW13: 7 | BX13: -2 | BY13: 5 | BZ13: 2 | CA13: -3 | CB13: 1 | CC13: 3 | CD13: 9 | CE13: 7
B14: Information | D14: =SUM(S14:X14) -> 8 | E14: 1 | F14: 2 | G14: 5 | H14: 7 | I14: 3 | J14: 3 | K14: 1 | L14: 4 | M14: 5 | N14: 2 | O14: 2 | P14: 1 | Q14: -7 | R14: 1 | S14: 4 | T14: 1 | U14: -2 | V14: 2 | W14: 2 | X14: 1 | Y14: 6 | Z14: 1 | AA14: 5 | AB14: 4 | AC14: 2 | AD14: 7 | AE14: 4 | AF14: 10 | AG14: 13 | AH14: 6 | AI14: 11 | AJ14: 3 | AK14: 3 | AL14: -1 | AM14: 2 | AN14: 9 | AO14: -1 | AP14: -1 | AQ14: 3 | AR14: 1 | AS14: 9 | AT14: 8 | AU14: 8 | AV14: -1 | AW14: -3 | AX14: -3 | AY14: -2 | AZ14: 1 | BA14: 1 | BB14: -3 | BC14: -1 | BD14: 2 | BE14: 6 | BF14: 3 | BG14: 1 | BH14: -3 | BI14: -5 | BJ14: -7 | BK14: 3 | BL14: -1 | BM14: -5 | BN14: 2 | BO14: -1 | BP14: -3 | BQ14: 6 | BR14: 3 | BS14: 13 | BT14: 4 | BU14: -2 | BV14: 5 | BW14: 2 | BX14: -1 | BY14: 3 | BZ14: 3 | CA14: 2 | CB14: 3 | CC14: 12 | CD14: 7 | CE14: 3
B15: Management of Companies & Support Services | D15: =SUM(S15:X15) -> 47 | E15: 5 | F15: 14 | G15: 4 | H15: 3 | I15: 1 | J15: 6 | K15: 8 | L15: 5 | M15: 9 | N15: 11 | O15: 15 | P15: 3 | Q15: -5 | R15: -5 | S15: -1 | T15: 5 | U15: 7 | V15: 14 | W15: 9 | X15: 13 | Y15: 14 | Z15: 8 | AA15: 6 | AB15: 15 | AC15: 15 | AD15: 10 | AE15: 11 | AF15: 14 | AG15: 5 | AH15: 15 | AI15: 5 | AJ15: 14 | AK15: 12 | AL15: 4 | AM15: 11 | AN15: 5 | AO15: 15 | AP15: 9 | AQ15: 17 | AR15: 10 | AS15: 3 | AT15: 1 | AU15: -2 | AV15: -3 | AW15: 3 | AX15: 7 | AY15: -1 | AZ15: 7 | BA15: 0 | BB15: 10 | BC15: 10 | BD15: 10 | BE15: -1 | BF15: -2 | BG15: 2 | BH15: 6 | BI15: -3 | BJ15: 1 | BK15: 7 | BL15: 7 | BM15: 7 | BN15: 4 | BO15: 7 | BP15: 6 | BQ15: -2 | BR15: 11 | BS15: -1 | BT15: 7 | BU15: -1 | BV15: 3 | BW15: -3 | BX15: -7 | BY15: -3 | BZ15: -6 | CA15: 6 | CB15: 6 | CC15: -3 | CD15: -4 | CE15: -5
B16: Mining | D16: =SUM(S16:X16) -> 2 | E16: 4 | F16: 6 | G16: 12 | H16: 2 | I16: 2 | J16: 10 | K16: -1 | L16: -4 | M16: -2 | N16: -2 | O16: 14 | P16: -4 | Q16: -9 | R16: -14 | S16: -3 | T16: -2 | U16: -3 | V16: 0 | W16: 7 | X16: 3 | Y16: 4 | Z16: 4 | AA16: 1 | AB16: 16 | AC16: 6 | AD16: 12 | AE16: 8 | AF16: 1 | AG16: 12 | AH16: 9 | AI16: 1 | AJ16: 11 | AK16: -1 | AL16: 5 | AM16: 9 | AN16: 2 | AO16: 9 | AP16: 14 | AQ16: 18 | AR16: 13 | AS16: 14 | AT16: 15 | AU16: 16 | AV16: 12 | AW16: 6 | AX16: -5 | AY16: 0 | AZ16: 8 | BA16: -3 | BB16: -7 | BC16: -2 | BD16: -4 | BE16: -4 | BF16: 11 | BG16: -3 | BH16: -2 | BI16: -6 | BJ16: -4 | BK16: -2 | BL16: -4 | BM16: 8 | BN16: -1 | BO16: -5 | BP16: 8 | BQ16: 9 | BR16: 9 | BS16: 8 | BT16: -3 | BU16: 0 | BV16: 12 | BW16: 9 | BX16: 0 | BY16: 9 | BZ16: 7 | CA16: -4 | CB16: -5 | CC16: 9 | CD16: -7 | CE16: 0
B17: Other Services | D17: =SUM(S17:X17) -> -7 | E17: 7 | F17: 4 | G17: 15 | H17: 6 | I17: 9 | J17: -3 | K17: -4 | L17: -1 | M17: 2 | N17: -4 | O17: 11 | P17: -3 | Q17: -13 | R17: -12 | S17: -2 | T17: -3 | U17: -1 | V17: 1 | W17: 1 | X17: -3 | Y17: -2 | Z17: 5 | AA17: 2 | AB17: 1 | AC17: 8 | AD17: 8 | AE17: 15 | AF17: 9 | AG17: 11 | AH17: 7 | AI17: 14 | AJ17: 6 | AK17: 10 | AL17: 8 | AM17: 1 | AN17: 11 | AO17: 5 | AP17: 3 | AQ17: 16 | AR17: 7 | AS17: 1 | AT17: 14 | AU17: 9 | AV17: 10 | AW17: -4 | AX17: 8 | AY17: 7 | AZ17: 13 | BA17: 13 | BB17: 4 | BC17: 7 | BD17: 14 | BE17: 11 | BF17: 10 | BG17: 10 | BH17: 7 | BI17: 5 | BJ17: 3 | BK17: 0 | BL17: 3 | BM17: -6 | BN17: 11 | BO17: 8 | BP17: -1 | BQ17: 7 | BR17: -5 | BS17: -2 | BT17: 0 | BU17: 0 | BV17: -3 | BW17: 14 | BX17: -5 | BY17: 0 | BZ17: -8 | CA17: 10 | CB17: 7 | CC17: -2 | CD17: 8 | CE17: -1
B18: Professional, Scientific & Technical Services | D18: =SUM(S18:X18) -> 12 | E18: 14 | F18: 7 | G18: 8 | H18: 11 | I18: 10 | J18: 1 | K18: 11 | L18: 2 | M18: 3 | N18: 1 | O18: 4 | P18: -5 | Q18: -8 | R18: -9 | S18: 1 | T18: -1 | U18: 1 | V18: -1 | W18: 6 | X18: 6 | Y18: 5 | Z18: 3 | AA18: 8 | AB18: 5 | AC18: 4 | AD18: 2 | AE18: 1 | AF18: 4 | AG18: 1 | AH18: 8 | AI18: 3 | AJ18: 5 | AK18: 6 | AL18: 9 | AM18: 5 | AN18: 3 | AO18: 11 | AP18: 5 | AQ18: 9 | AR18: 5 | AS18: 2 | AT18: 6 | AU18: 6 | AV18: 5 | AW18: 2 | AX18: 1 | AY18: 10 | AZ18: 7 | BA18: 7 | BB18: 9 | BC18: 5 | BD18: 6 | BE18: 1 | BF18: 5 | BG18: -1 | BH18: -1 | BI18: 2 | BJ18: 8 | BK18: 8 | BL18: 11 | BM18: -2 | BN18: 1 | BO18: 1 | BP18: -4 | BQ18: -1 | BR18: -2 | BS18: 3 | BT18: 3 | BU18: -3 | BV18: -1 | BW18: 3 | BX18: -6 | BY18: -5 | BZ18: 1 | CA18: -2 | CB18: -1 | CC18: 6 | CD18: -3 | CE18: 2
B19: Public Administration | D19: =SUM(S19:X19) -> 23 | E19: 10 | F19: 8 | G19: 7 | H19: 4 | I19: 14 | J19: 7 | K19: 2 | L19: 1 | M19: -3 | N19: 3 | O19: 8 | P19: 7 | Q19: 2 | R19: 2 | S19: 2 | T19: 7 | U19: 6 | V19: 7 | W19: -1 | X19: 2 | Y19: 3 | Z19: 2 | AA19: 12 | AB19: 9 | AC19: 11 | AD19: 3 | AE19: 5 | AF19: 8 | AG19: 9 | AH19: 3 | AI19: 2 | AJ19: 10 | AK19: 5 | AL19: 12 | AM19: 4 | AN19: 7 | AO19: 12 | AP19: 1 | AQ19: 12 | AR19: 11 | AS19: 5 | AT19: 11 | AU19: 3 | AV19: 7 | AW19: 8 | AX19: 6 | AY19: 12 | AZ19: 9 | BA19: 9 | BB19: 2 | BC19: 12 | BD19: 11 | BE19: 7 | BF19: 4 | BG19: 7 | BH19: 4 | BI19: 1 | BJ19: 7 | BK19: 12 | BL19: 0 | BM19: 2 | BN19: 5 | BO19: -8 | BP19: 4 | BQ19: 3 | BR19: 8 | BS19: 7 | BT19: 9 | BU19: 4 | BV19: 2 | BW19: 1 | BX19: 6 | BY19: -2 | BZ19: 8 | CA19: 4 | CB19: 5 | CC19: 2 | CD19: 6 | CE19: -3
... B24: Wholesale Trade | D24: =SUM(S24:X24) -> 59 | E24: 6 | F24: 9 | G24: 1 | H24: -2 | I24: -1 | J24: -1 | K24: -2 | L24: -3 | M24: -4 | N24: -5 | O24: 7 | P24: 2 | Q24: -12 | R24: -7 | S24: 12 | T24: 11 | U24: 10 | V24: 11 | W24: 8 | X24: 7 | Y24: 13 | Z24: 12 | AA24: 16 | AB24: 17 | AC24: 16 | AD24: 17 | AE24: 13 | AF24: 16 | AG24: 6 | AH24: 2 | AI24: 9 | AJ24: 12 | AK24: 15 | AL24: 2 | AM24: 10 | AN24: 13 | AO24: 7 | AP24: 6 | AQ24: 11 | AR24: 2 | AS24: 7 | AT24: 9 | AU24: 1 | AV24: -2 | AW24: -5 | AX24: -1 | AY24: -4 | AZ24: -4 | BA24: -1 | BB24: -4 | BC24: 8 | BD24: 1 | BE24: -3 | BF24: -1 | BG24: -2 | BH24: 2 | BI24: -7 | BJ24: -2 | BK24: 4 | BL24: 4 | BM24: 1 | BN24: 8 | BO24: -3 | BP24: -6 | BQ24: -4 | BR24: -3 | BS24: 1 | BT24: 11 | BU24: 2 | BV24: 11 | BW24: 12 | BX24: 7 | BY24: 10 | BZ24: -1 | CA24: 5 | CB24: 10 | CC24: 11 | CD24: 4 | CE24: 9
A26: PMI Rank | B26: Accommodation & Food Services | D26: =AVERAGE(S26:X26) -> 13 | P26: =_xlfn.RANK.AVG(P7,P$7:P$24,1) -> 8.5 | Q26: =_xlfn.RANK.AVG(Q7,Q$7:Q$24,1) -> 11 | R26: =_xlfn.RANK.AVG(R7,R$7:R$24,1) -> 9 | S26: =_xlfn.RANK.AVG(S7,S$7:S$24,1) -> 17 | T26: =_xlfn.RANK.AVG(T7,T$7:T$24,1) -> 5 | U26: =_xlfn.RANK.AVG(U7,U$7:U$24,1) -> 15 | V26: =_xlfn.RANK.AVG(V7,V$7:V$24,1) -> 11 | W26: =_xlfn.RANK.AVG(W7,W$7:W$24,1) -> 16 | ... CE26: =_xlfn.RANK.AVG(CE7,CE$7:CE$24,1) -> 18
B27: Agriculture, Forestry, Fishing & Hunting | D27: =AVERAGE(S27:X27) -> 9.8333333 | P27: =_xlfn.RANK.AVG(P8,$P$7:$P$24,1) -> 8.5 | Q27: =_xlfn.RANK.AVG(Q8,Q$7:Q$24,1) -> 2 | R27: =_xlfn.RANK.AVG(R8,R$7:R$24,1) -> 18 | S27: =_xlfn.RANK.AVG(S8,S$7:S$24,1) -> 18 | T27: =_xlfn.RANK.AVG(T8,T$7:T$24,1) -> 6 | U27: =_xlfn.RANK.AVG(U8,U$7:U$24,1) -> 6 | V27: =_xlfn.RANK.AVG(V8,V$7:V$24,1) -> 7 | W27: =_xlfn.RANK.AVG(W8,W$7:W$24,1) -> 14 | X27: =_xlfn.RANK.AVG(X8,X$7:X$24,1) -> 8 | ... CE27: =_xlfn.RANK.AVG(CE8,CE$7:CE$24,1) -> 11
B28: Arts, Entertainment & Recreation | D28: =AVERAGE(S28:X28) -> 10.833333 | P28: =_xlfn.RANK.AVG(P9,$P$7:$P$24,1) -> 1 | Q28: =_xlfn.RANK.AVG(Q9,Q$7:Q$24,1) -> 1 | R28: =_xlfn.RANK.AVG(R9,R$7:R$24,1) -> 2 | S28: =_xlfn.RANK.AVG(S9,S$7:S$24,1) -> 9 | T28: =_xlfn.RANK.AVG(T9,T$7:T$24,1) -> 18 | U28: =_xlfn.RANK.AVG(U9,U$7:U$24,1) -> 18 | V28: =_xlfn.RANK.AVG(V9,V$7:V$24,1) -> 18 | W28: =_xlfn.RANK.AVG(W9,W$7:W$24,1) -> 1 | X28: =_xlfn.RANK.AVG(X9,X$7:X$24,1) -> 1 | ... CE28: =_xlfn.RANK.AVG(CE9,CE$7:CE$24,1) -> 1
B29: Construction | D29: =AVERAGE(S29:X29) -> 12.833333 | P29: =_xlfn.RANK.AVG(P10,$P$7:$P$24,1) -> 13 | Q29: =_xlfn.RANK.AVG(Q10,Q$7:Q$24,1) -> 6 | R29: =_xlfn.RANK.AVG(R10,R$7:R$24,1) -> 4 | S29: =_xlfn.RANK.AVG(S10,S$7:S$24,1) -> 13 | T29: =_xlfn.RANK.AVG(T10,T$7:T$24,1) -> 12 | U29: =_xlfn.RANK.AVG(U10,U$7:U$24,1) -> 12 | V29: =_xlfn.RANK.AVG(V10,V$7:V$24,1) -> 10 | W29: =_xlfn.RANK.AVG(W10,W$7:W$24,1) -> 17 | X29: =_xlfn.RANK.AVG(X10,X$7:X$24,1) -> 13 | ... CE29: =_xlfn.RANK.AVG(CE10,CE$7:CE$24,1) -> 5
B30: Educational Services | D30: =AVERAGE(S30:X30) -> 8.1666667 | P30: =_xlfn.RANK.AVG(P11,$P$7:$P$24,1) -> 7 | Q30: =_xlfn.RANK.AVG(Q11,Q$7:Q$24,1) -> 13 | R30: =_xlfn.RANK.AVG(R11,R$7:R$24,1) -> 5 | S30: =_xlfn.RANK.AVG(S11,S$7:S$24,1) -> 4 | T30: =_xlfn.RANK.AVG(T11,T$7:T$24,1) -> 13 | U30: =_xlfn.RANK.AVG(U11,U$7:U$24,1) -> 7 | V30: =_xlfn.RANK.AVG(V11,V$7:V$24,1) -> 8 | W30: =_xlfn.RANK.AVG(W11,W$7:W$24,1) -> 13 | X30: =_xlfn.RANK.AVG(X11,X$7:X$24,1) -> 4 | ... CE30: =_xlfn.RANK.AVG(CE11,CE$7:CE$24,1) -> 8
B31: Finance & Insurance | D31: =AVERAGE(S31:X31) -> 8.5 | P31: =_xlfn.RANK.AVG(P12,$P$7:$P$24,1) -> 14 | Q31: =_xlfn.RANK.AVG(Q12,Q$7:Q$24,1) -> 17 | R31: =_xlfn.RANK.AVG(R12,R$7:R$24,1) -> 17 | S31: =_xlfn.RANK.AVG(S12,S$7:S$24,1) -> 7 | T31: =_xlfn.RANK.AVG(T12,T$7:T$24,1) -> 9 | U31: =_xlfn.RANK.AVG(U12,U$7:U$24,1) -> 8 | V31: =_xlfn.RANK.AVG(V12,V$7:V$24,1) -> 6 | W31: =_xlfn.RANK.AVG(W12,W$7:W$24,1) -> 12 | X31: =_xlfn.RANK.AVG(X12,X$7:X$24,1) -> 9 | ... CE31: =_xlfn.RANK.AVG(CE12,CE$7:CE$24,1) -> 3
B32: Health Care & Social Assistance | D32: =AVERAGE(S32:X32) -> 15.5 | P32: =_xlfn.RANK.AVG(P13,$P$7:$P$24,1) -> 18 | Q32: =_xlfn.RANK.AVG(Q13,Q$7:Q$24,1) -> 16 | R32: =_xlfn.RANK.AVG(R13,R$7:R$24,1) -> 13 | S32: =_xlfn.RANK.AVG(S13,S$7:S$24,1) -> 14 | T32: =_xlfn.RANK.AVG(T13,T$7:T$24,1) -> 17 | U32: =_xlfn.RANK.AVG(U13,U$7:U$24,1) -> 17 | V32: =_xlfn.RANK.AVG(V13,V$7:V$24,1) -> 14 | W32: =_xlfn.RANK.AVG(W13,W$7:W$24,1) -> 15 | X32: =_xlfn.RANK.AVG(X13,X$7:X$24,1) -> 16 | ... CE32: =_xlfn.RANK.AVG(CE13,CE$7:CE$24,1) -> 14
B33: Information | D33: =AVERAGE(S33:X33) -> 4.5 | P33: =_xlfn.RANK.AVG(P14,$P$7:$P$24,1) -> 10 | Q33: =_xlfn.RANK.AVG(Q14,Q$7:Q$24,1) -> 10 | R33: =_xlfn.RANK.AVG(R14,R$7:R$24,1) -> 15 | S33: =_xlfn.RANK.AVG(S14,S$7:S$24,1) -> 8 | T33: =_xlfn.RANK.AVG(T14,T$7:T$24,1) -> 4 | U33: =_xlfn.RANK.AVG(U14,U$7:U$24,1) -> 2 | V33: =_xlfn.RANK.AVG(V14,V$7:V$24,1) -> 4 | W33: =_xlfn.RANK.AVG(W14,W$7:W$24,1) -> 4 | X33: =_xlfn.RANK.AVG(X14,X$7:X$24,1) -> 5 | ... CE33: =_xlfn.RANK.AVG(CE14,CE$7:CE$24,1) -> 10
B34: Management of Companies & Support Services | D34: =AVERAGE(S34:X34) -> 10.833333 | P34: =_xlfn.RANK.AVG(P15,$P$7:$P$24,1) -> 12 | Q34: =_xlfn.RANK.AVG(Q15,Q$7:Q$24,1) -> 12 | R34: =_xlfn.RANK.AVG(R15,R$7:R$24,1) -> 10 | S34: =_xlfn.RANK.AVG(S15,S$7:S$24,1) -> 3 | T34: =_xlfn.RANK.AVG(T15,T$7:T$24,1) -> 8 | U34: =_xlfn.RANK.AVG(U15,U$7:U$24,1) -> 10 | V34: =_xlfn.RANK.AVG(V15,V$7:V$24,1) -> 16 | W34: =_xlfn.RANK.AVG(W15,W$7:W$24,1) -> 11 | X34: =_xlfn.RANK.AVG(X15,X$7:X$24,1) -> 17 | ... CE34: =_xlfn.RANK.AVG(CE15,CE$7:CE$24,1) -> 2
B35: Mining | D35: =AVERAGE(S35:X35) -> 3.6666667 | P35: =_xlfn.RANK.AVG(P16,$P$7:$P$24,1) -> 4 | Q35: =_xlfn.RANK.AVG(Q16,Q$7:Q$24,1) -> 8 | R35: =_xlfn.RANK.AVG(R16,R$7:R$24,1) -> 1 | S35: =_xlfn.RANK.AVG(S16,S$7:S$24,1) -> 1 | T35: =_xlfn.RANK.AVG(T16,T$7:T$24,1) -> 2 | U35: =_xlfn.RANK.AVG(U16,U$7:U$24,1) -> 1 | V35: =_xlfn.RANK.AVG(V16,V$7:V$24,1) -> 2 | W35: =_xlfn.RANK.AVG(W16,W$7:W$24,1) -> 9 | X35: =_xlfn.RANK.AVG(X16,X$7:X$24,1) -> 7 | ... CE35: =_xlfn.RANK.AVG(CE16,CE$7:CE$24,1) -> 7
B36: Other Services | D36: =AVERAGE(S36:X36) -> 2.3333333 | P36: =_xlfn.RANK.AVG(P17,$P$7:$P$24,1) -> 5 | Q36: =_xlfn.RANK.AVG(Q17,Q$7:Q$24,1) -> 4 | R36: =_xlfn.RANK.AVG(R17,R$7:R$24,1) -> 3 | S36: =_xlfn.RANK.AVG(S17,S$7:S$24,1) -> 2 | T36: =_xlfn.RANK.AVG(T17,T$7:T$24,1) -> 1 | U36: =_xlfn.RANK.AVG(U17,U$7:U$24,1) -> 3 | V36: =_xlfn.RANK.AVG(V17,V$7:V$24,1) -> 3 | W36: =_xlfn.RANK.AVG(W17,W$7:W$24,1) -> 3 | X36: =_xlfn.RANK.AVG(X17,X$7:X$24,1) -> 2 | ... CE36: =_xlfn.RANK.AVG(CE17,CE$7:CE$24,1) -> 6
B37: Professional, Scientific & Technical Services | D37: =AVERAGE(S37:X37) -> 5.1666667 | P37: =_xlfn.RANK.AVG(P18,$P$7:$P$24,1) -> 3 | Q37: =_xlfn.RANK.AVG(Q18,Q$7:Q$24,1) -> 9 | R37: =_xlfn.RANK.AVG(R18,R$7:R$24,1) -> 6 | S37: =_xlfn.RANK.AVG(S18,S$7:S$24,1) -> 5 | T37: =_xlfn.RANK.AVG(T18,T$7:T$24,1) -> 3 | U37: =_xlfn.RANK.AVG(U18,U$7:U$24,1) -> 4 | V37: =_xlfn.RANK.AVG(V18,V$7:V$24,1) -> 1 | W37: =_xlfn.RANK.AVG(W18,W$7:W$24,1) -> 8 | X37: =_xlfn.RANK.AVG(X18,X$7:X$24,1) -> 10 | ... CE37: =_xlfn.RANK.AVG(CE18,CE$7:CE$24,1) -> 9
B38: Public Administration | D38: =AVERAGE(S38:X38) -> 7 | P38: =_xlfn.RANK.AVG(P19,$P$7:$P$24,1) -> 16 | Q38: =_xlfn.RANK.AVG(Q19,Q$7:Q$24,1) -> 18 | R38: =_xlfn.RANK.AVG(R19,R$7:R$24,1) -> 16 | S38: =_xlfn.RANK.AVG(S19,S$7:S$24,1) -> 6 | T38: =_xlfn.RANK.AVG(T19,T$7:T$24,1) -> 10 | U38: =_xlfn.RANK.AVG(U19,U$7:U$24,1) -> 9 | V38: =_xlfn.RANK.AVG(V19,V$7:V$24,1) -> 9 | W38: =_xlfn.RANK.AVG(W19,W$7:W$24,1) -> 2 | X38: =_xlfn.RANK.AVG(X19,X$7:X$24,1) -> 6 | ... CE38: =_xlfn.RANK.AVG(CE19,CE$7:CE$24,1) -> 4
... B43: Wholesale Trade | D43: =AVERAGE(S43:X43) -> 12.833333 | P43: =_xlfn.RANK.AVG(P24,$P$7:$P$24,1) -> 11 | Q43: =_xlfn.RANK.AVG(Q24,Q$7:Q$24,1) -> 5 | R43: =_xlfn.RANK.AVG(R24,R$7:R$24,1) -> 8 | S43: =_xlfn.RANK.AVG(S24,S$7:S$24,1) -> 16 | T43: =_xlfn.RANK.AVG(T24,T$7:T$24,1) -> 14 | U43: =_xlfn.RANK.AVG(U24,U$7:U$24,1) -> 13 | V43: =_xlfn.RANK.AVG(V24,V$7:V$24,1) -> 13 | W43: =_xlfn.RANK.AVG(W24,W$7:W$24,1) -> 10 | X43: =_xlfn.RANK.AVG(X24,X$7:X$24,1) -> 11 | ... CE43: =_xlfn.RANK.AVG(CE24,CE$7:CE$24,1) -> 16
A45: BUSINESS ACTIVITY | B45: Accommodation & Food Services | D45: =SUM(S45:X45) -> 59 | K45: 0 | L45: 3 | M45: -4 | N45: 5 | O45: 13 | P45: 4 | Q45: -2 | R45: -5 | S45: 14 | T45: 5 | U45: 2 | V45: 13 | W45: 15 | X45: 10 | Y45: -4 | Z45: 6 | AA45: 14 | AB45: 14 | AC45: 10 | AD45: 4 | AE45: 4 | AF45: 12 | AG45: 9 | AH45: 6 | AI45: 3 | AJ45: 0 | AK45: 15 | AL45: -4 | AM45: -1 | AN45: 8 | AO45: 13 | AP45: 5 | AQ45: 12 | AR45: -3 | AS45: -2 | AT45: -2 | AU45: 7 | AV45: 12 | AW45: 8 | AX45: 6 | AY45: 1 | AZ45: 0 | BA45: 13 | BB45: 13 | BC45: 15 | BD45: 12 | BE45: 12 | BF45: -2 | BG45: -2 | BH45: 0 | BI45: 9 | BJ45: 0 | BK45: 9 | BL45: 12 | BM45: 13 | BN45: 10 | BO45: 9 | BP45: 10 | BQ45: 0 | BR45: 8 | BS45: 0 | BT45: 13
B46: Agriculture, Forestry, Fishing & Hunting | D46: =SUM(S46:X46) -> 28 | K46: 13 | L46: -7 | M46: 0 | N46: 12 | O46: 0 | P46: 0 | Q46: -16 | R46: 3 | S46: 15 | T46: 6 | U46: -3 | V46: -1 | W46: 12 | X46: -1 | Y46: 6 | Z46: 0 | AA46: -2 | AB46: 12 | AC46: -1 | AD46: 3 | AE46: -1 | AF46: 0 | AG46: -0.5 | AH46: -1 | AI46: -1 | AJ46: 8 | AK46: -2 | AL46: -6 | AM46: -2 | AN46: -2 | AO46: 0 | AP46: -3 | AQ46: 0 | AR46: -4 | AS46: -3 | AT46: 6 | AU46: 14 | AV46: 7 | AW46: 0 | AX46: 12 | AY46: 14 | AZ46: 9 | BA46: 0 | BB46: -2 | BC46: -2 | BD46: -2 | BE46: -3 | BF46: -3 | BG46: 0 | BH46: 11 | BI46: 12 | BJ46: 10 | BK46: 12 | BL46: 11 | BM46: 12 | BN46: -1 | BO46: -4 | BP46: -3 | BQ46: -3 | BR46: -2 | BS46: 0 | BT46: 7
B47: Arts, Entertainment & Recreation | D47: =SUM(S47:X47) -> 36 | K47: 10 | L47: 7 | M47: 8 | N47: -3 | O47: -3 | P47: -9 | Q47: -17 | R47: -8 | S47: 0 | T47: 11 | U47: 13 | V47: 16 | W47: 0 | X47: -4 | Y47: 0 | Z47: 0 | AA47: 13 | AB47: 17 | AC47: 17 | AD47: 17 | AE47: 16 | AF47: 17 | AG47: 16.5 | AH47: 16 | AI47: 10 | AJ47: 0 | AK47: 9 | AL47: -7 | AM47: -3 | AN47: 13 | AO47: 0 | AP47: 10 | AQ47: 11 | AR47: 0 | AS47: -1 | AT47: -1 | AU47: 11 | AV47: 0 | AW47: 0 | AX47: 0 | AY47: 0 | AZ47: 13 | BA47: 12 | BB47: 9 | BC47: 14 | BD47: -3 | BE47: 6 | BF47: 0 | BG47: 13 | BH47: 9 | BI47: -4 | BJ47: -1 | BK47: -4 | BL47: 0 | BM47: -3 | BN47: -2 | BO47: 0 | BP47: 11 | BQ47: 9 | BR47: 0 | BS47: 0 | BT47: 14
B48: Construction | D48: =SUM(S48:X48) -> 37 | K48: 7 | L48: -5 | M48: 1 | N48: 6 | O48: 4 | P48: 3 | Q48: -7 | R48: -11 | S48: 8 | T48: 4 | U48: 6 | V48: 4 | W48: 10 | X48: 5 | Y48: -2 | Z48: 10 | AA48: 6 | AB48: 5 | AC48: 8 | AD48: 13 | AE48: 8 | AF48: 5 | AG48: 4 | AH48: 3 | AI48: 4 | AJ48: 6 | AK48: 8 | AL48: 6 | AM48: 7 | AN48: 6 | AO48: 6 | AP48: 12 | AQ48: 14 | AR48: 7 | AS48: 7 | AT48: 0 | AU48: 13 | AV48: 8 | AW48: 1 | AX48: 4 | AY48: 11 | AZ48: 5 | BA48: 2 | BB48: 10 | BC48: 1 | BD48: 10 | BE48: 4 | BF48: -1 | BG48: 9 | BH48: -2 | BI48: -3 | BJ48: 0 | BK48: 7 | BL48: 2 | BM48: 4 | BN48: 4 | BO48: 8 | BP48: 9 | BQ48: -2 | BR48: 10 | BS48: 5 | BT48: 0
B49: Educational Services | D49: =SUM(S49:X49) -> 34 | K49: -3 | L49: 0 | M49: -7 | N49: 2 | O49: 5 | P49: -6 | Q49: -10 | R49: -12 | S49: 3 | T49: 12 | U49: 3 | V49: 8 | W49: 7 | X49: 1 | Y49: -1 | Z49: -1 | AA49: 8 | AB49: 2 | AC49: 9 | AD49: 5 | AE49: 2 | AF49: 2 | AG49: 8.5 | AH49: 15 | AI49: 13 | AJ49: 1 | AK49: -1 | AL49: -1 | AM49: 12 | AN49: 12 | AO49: 12 | AP49: 11 | AQ49: 5 | AR49: 11 | AS49: 8 | AT49: 11 | AU49: 10 | AV49: 0 | AW49: 2 | AX49: 7 | AY49: 6 | AZ49: 11 | BA49: 11 | BB49: 3 | BC49: 11 | BD49: 4 | BE49: 5 | BF49: 3 | BG49: 4 | BH49: 1 | BI49: -1 | BJ49: 2 | BK49: 1 | BL49: 9 | BM49: 7 | BN49: 7 | BO49: 6 | BP49: 3 | BQ49: 2 | BR49: 7 | BS49: 3 | BT49: 2
B50: Finance & Insurance | D50: =SUM(S50:X50) -> 35 | K50: 5 | L50: 5 | M50: 2 | N50: 7 | O50: 9 | P50: 1 | R50: 2 | S50: 5 | T50: 2 | U50: 4 | V50: 7 | W50: 8 | X50: 9 | Y50: 3 | Z50: 9 | AA50: 4 | AB50: 9 | AC50: 7 | AD50: 15 | AE50: 5 | AF50: 3 | AG50: 5.5 | AH50: 8 | AI50: 7 | AJ50: 5 | AK50: 6 | AL50: 2 | AM50: 8 | AN50: 3 | AO50: 1 | AP50: 0 | AQ50: 7 | AR50: -1 | AS50: 1 | AT50: 8 | AU50: 4 | AV50: -1 | AW50: 3 | AX50: 2 | AY50: 4 | AZ50: -2 | BA50: 1 | BB50: 2 | BC50: 13 | BD50: 1 | BE50: 7 | BF50: 6 | BG50: 12 | BH50: 8 | BI50: 8 | BJ50: 3 | BK50: 11 | BL50: 10 | BM50: 11 | BN50: 2 | BO50: 7 | BP50: 7 | BQ50: 4 | BR50: 6 | BS50: 9 | BT50: 12
B51: Health Care & Social Assistance | D51: =SUM(S51:X51) -> 61 | K51: 3 | L51: 8 | M51: 7 | N51: 10 | O51: 6 | P51: 5 | Q51: -4 | R51: -6 | S51: 11 | T51: 9 | U51: 9 | V51: 9 | W51: 11 | X51: 12 | Y51: 10 | Z51: 5 | AA51: 3 | AB51: 6 | AC51: 6 | AD51: 8 | AE51: 6 | AF51: 10 | AG51: 11.5 | AH51: 13 | AI51: 11 | AJ51: 11 | AK51: 11 | AL51: 7 | AM51: 1 | AN51: -1 | AO51: 4 | AP51: 1 | AQ51: 4 | AR51: 4 | AS51: 2 | AT51: 9 | AU51: 1 | AV51: 6 | AW51: 9 | AX51: 5 | AY51: 5 | AZ51: 1 | BA51: 4 | BB51: 1 | BC51: 4 | BD51: -1 | BE51: 0 | BF51: 11 | BG51: 3 | BH51: 10 | BI51: 11 | BJ51: 9 | BK51: 6 | BL51: 1 | BM51: 3 | BN51: 9 | BO51: 4 | BP51: 1 | BQ51: 3 | BR51: 4 | BS51: 0 | BT51: 9
B52: Information | D52: =SUM(S52:X52) -> 6 | K52: 1 | L52: 1 | M52: 6 | N52: 3 | O52: -2 | P52: -1 | Q52: -3 | R52: -1 | S52: 2 | T52: -1 | U52: -2 | V52: 3 | W52: 2 | X52: 2 | Y52: 8 | Z52: 1 | AA52: 2 | AB52: 4 | AC52: 2 | AD52: 9 | AE52: 10 | AF52: 11 | AG52: 10.5 | AH52: 10 | AI52: 15 | AJ52: 4 | AK52: 3 | AL52: -5 | AM52: 0 | AN52: 7 | AO52: 0 | AP52: -1 | AQ52: 3 | AR52: 1 | AS52: 9 | AT52: 13 | AU52: 12 | AV52: 5 | AW52: -1 | AX52: -1 | AY52: 10 | AZ52: 12 | BA52: 3 | BB52: -1 | BC52: 5 | BD52: 5 | BE52: 9 | BF52: 7 | BG52: 7 | BH52: -3 | BI52: 1 | BJ52: -3 | BK52: 2 | BL52: 0 | BM52: -1 | BN52: 0 | BO52: 2 | BP52: 6 | BQ52: 5 | BR52: 3 | BS52: 6 | BT52: 11
B53: Management of Companies & Support Services | D53: =SUM(S53:X53) -> 54 | K53: 4 | L53: 4 | M53: 9 | N53: 11 | O53: 12 | P53: 0 | Q53: -9 | R53: -3 | S53: 6 | T53: 3 | U53: 11 | V53: 12 | W53: 9 | X53: 13 | Y53: 11 | Z53: 0 | AA53: 7 | AB53: 15 | AC53: 15 | AD53: 7 | AE53: 14 | AF53: 16 | AG53: 14 | AH53: 12 | AI53: 6 | AJ53: 16 | AK53: 10 | AL53: 1 | AM53: 13 | AN53: 2 | AO53: 5 | AP53: 9 | AQ53: 15 | AR53: 9 | AS53: 0 | AT53: 0 | AU53: -1 | AV53: 0 | AW53: 6 | AX53: 8 | AY53: 3 | AZ53: 10 | BA53: -1 | BB53: 12 | BC53: 0 | BD53: 13 | BE53: 0 | BF53: 1 | BG53: 5 | BH53: 5 | BI53: -2 | BJ53: 7 | BK53: 5 | BL53: 7 | BM53: 2 | BN53: 8 | BO53: 3 | BP53: 8 | BQ53: 0 | BR53: 11 | BS53: -1 | BT53: 4
B54: Mining | D54: =SUM(S54:X54) -> 21 | K54: 12 | L54: -4 | M54: -1 | N54: -4 | O54: 11 | P54: -8 | Q54: -5 | R54: -13 | S54: 0 | T54: -3 | U54: -1 | V54: 5 | W54: 14 | X54: 6 | Y54: 5 | Z54: 0 | AA54: 5 | AB54: 16 | AC54: 12 | AD54: 14 | AE54: 3 | AF54: 1 | AG54: 1.5 | AH54: 2 | AI54: 9 | AJ54: 3 | AK54: -3 | AL54: 0 | AM54: 10 | AN54: 0 | AO54: 11 | AP54: 13 | AQ54: 10 | AR54: 13 | AS54: 0 | AT54: 14 | AU54: 15 | AV54: 11 | AW54: 10 | AX54: -3 | AY54: 0 | AZ54: 8 | BA54: -2 | BB54: -3 | BC54: -1 | BD54: 0 | BE54: -2 | BF54: 10 | BG54: 0 | BH54: -4 | BI54: 5 | BJ54: -2 | BK54: -2 | BL54: -2 | BM54: 10 | BN54: -3 | BO54: -5 | BP54: 0 | BQ54: 7 | BR54: 0 | BS54: 0 | BT54: 0
B55: Other Services | D55: =SUM(S55:X55) -> 2 | K55: -2 | L55: -6 | M55: 4 | N55: -1 | O55: 1 | P55: -7 | Q55: -13 | R55: -10 | S55: -1 | T55: -2 | U55: 0 | V55: 2 | W55: 5 | X55: -2 | Y55: -5 | Z55: 0 | AA55: -1 | AB55: -1 | AC55: 3 | AD55: 6 | AE55: 15 | AF55: 6 | AG55: 5 | AH55: 4 | AI55: 5 | AJ55: 7 | AK55: 7 | AL55: 0 | AM55: 3 | AN55: 10 | AO55: 2 | AP55: 0 | AQ55: 13 | AR55: 6 | AS55: 0 | AT55: 12 | AU55: 5 | AV55: 10 | AW55: -3 | AX55: 9 | AY55: 8 | AZ55: 14 | BA55: 14 | BB55: 7 | BC55: 7 | BD55: 14 | BE55: 11 | BF55: 9 | BG55: 11 | BH55: 0 | BI55: 6 | BJ55: 0 | BK55: -3 | BL55: 0 | BM55: -4 | BN55: 11 | BO55: 10 | BP55: 0 | BQ55: 8 | BR55: -3 | BS55: -2 | BT55: -1
B56: Professional, Scientific & Technical Services | D56: =SUM(S56:X56) -> 17 | K56: 9 | L56: -1 | M56: 5 | N56: 1 | O56: 2 | P56: -4 | Q56: -11 | R56: -7 | S56: 4 | T56: 0 | U56: 0 | V56: 1 | W56: 4 | X56: 8 | Y56: 2 | Z56: 4 | AA56: 1 | AB56: 1 | AC56: 4 | AD56: 2 | AE56: 1 | AF56: 4 | AG56: 7.5 | AH56: 11 | AI56: 2 | AJ56: 2 | AK56: 2 | AL56: 3 | AM56: 4 | AN56: 1 | AO56: 7 | AP56: 6 | AQ56: 9 | AR56: 5 | AS56: 3 | AT56: 3 | AU56: 6 | AV56: 4 | AW56: 0 | AX56: 3 | AY56: 7 | AZ56: 6 | BA56: 5 | BB56: 4 | BC56: 3 | BD56: 3 | BE56: -1 | BF56: 4 | BG56: -1 | BH56: -1 | BI56: 3 | BJ56: 5 | BK56: 3 | BL56: 5 | BM56: 0 | BN56: 1 | BO56: 0 | BP56: -1 | BQ56: -1 | BR56: 1 | BS56: 2 | BT56: 3
B57: Public Administration | D57: =SUM(S57:X57) -> 23 | K57: 2 | L57: -3 | M57: -3 | N57: 8 | O57: 8 | P57: 2 | Q57: -1 | R57: 0 | S57: 1 | T57: 7 | U57: 7 | V57: 6 | W57: -1 | X57: 3 | Y57: 0 | Z57: 3 | AA57: 10 | AB57: 8 | AC57: 14 | AD57: 1 | AE57: 7 | AF57: 8 | AG57: 6.5 | AH57: 5 | AI57: 1 | AJ57: 9 | AK57: 1 | AL57: 5 | AM57: 6 | AN57: 5 | AO57: 10 | AP57: 3 | AQ57: 1 | AR57: 10 | AS57: 4 | AT57: 4 | AU57: 0 | AV57: 9 | AW57: 7 | AX57: 10 | AY57: 13 | AZ57: 7 | BA57: 10 | BB57: 5 | BC57: 8 | BD57: 8 | BE57: 8 | BF57: 5 | BG57: 8 | BH57: 2 | BI57: 2 | BJ57: 6 | BK57: 8 | BL57: 3 | BM57: 6 | BN57: 3 | BO57: -2 | BP57: 5 | BQ57: 1 | BR57: 9 | BS57: 4 | BT57: 8
B58: Real Estate, Rental & Leasing | D58: =SUM(S58:X58) -> 56 | K58: 8 | L58: 9 | M58: -5 | N58: 0 | O58: 10 | P58: 0 | Q58: -12 | R58: 0 | S58: 13 | T58: 8 | U58: 10 | V58: 15 | W58: 13 | X58: -3 | Y58: -3 | Z58: 8 | AA58: -3 | AB58: 11 | AC58: 1 | AD58: 12 | AE58: -2 | AF58: 13 | AG58: 13.5 | AH58: 14 | AI58: 17 | AJ58: 14 | AK58: 5 | AL58: -2 | AM58: -4 | AN58: 0 | AO58: 14 | AP58: 8 | AQ58: 0 | AR58: 12 | AS58: 11 | AT58: 5 | AU58: -2 | AV58: 13 | AW58: -4 | AX58: 0 | AY58: -2 | AZ58: 0 | BA58: 0 | BB58: -4 | BC58: 12 | BD58: 11 | BE58: 10 | BF58: 14 | BG58: -3 | BH58: 6 | BI58: -5 | BJ58: -4 | BK58: 0 | BL58: 0 | BM58: -2 | BN58: 13 | BO58: -6 | BP58: 0 | BQ58: 0 | BR58: 12 | BS58: 0 | BT58: -2
B59: Retail Trade | D59: =SUM(S59:X59) -> 32 | K59: 0 | L59: 2 | M59: 10 | N59: 0 | O59: 0 | P59: -5 | Q59: -14 | R59: 1 | S59: 10 | T59: 13 | U59: 1 | V59: 0 | W59: 1 | X59: 7 | Y59: 7 | Z59: -2 | AA59: 0 | AB59: 3 | AC59: 11 | AD59: 18 | AE59: 9 | AF59: 14 | AG59: 15.5 | AH59: 17 | AI59: 16 | AJ59: 15 | AK59: 13 | AL59: 8 | AM59: 2 | AN59: 0 | AO59: 0 | AP59: -2 | AQ59: 0 | AR59: -2 | AS59: 0 | AT59: 2 | AU59: 3 | AV59: 3 | AW59: 11 | AX59: -2 | AY59: 12 | AZ59: 3 | BA59: 7 | BB59: 11 | BC59: 2 | BD59: 2 | BE59: 1 | BF59: 13 | BG59: 1 | BH59: 3 | BI59: 10 | BJ59: -5 | BK59: 13 | BL59: 8 | BM59: 5 | BN59: 0 | BO59: -3 | BP59: 0 | BQ59: -4 | BR59: 0 | BS59: 8 | BT59: 10
B60: Transportation & Warehousing | D60: =SUM(S60:X60) -> 67 | K60: 6 | M60: 3 | N60: 9 | O60: 7 | P60: -3 | Q60: -15 | R60: -2 | S60: 7 | T60: 14 | U60: 5 | V60: 11 | W60: 16 | X60: 14 | Y60: 9 | Z60: 0 | AA60: 11 | AB60: 7 | AC60: 5 | AD60: 10 | AE60: 11 | AF60: 9 | AG60: 5 | AH60: 1 | AI60: 14 | AJ60: 13 | AK60: 14 | AL60: -3 | AM60: 11 | AN60: 4 | AO60: 8 | AP60: 2 | AQ60: 2 | AR60: 2 | AS60: 5 | AT60: 1 | AU60: 9 | AV60: 2 | AW60: 4 | AX60: -4 | AY60: 2 | AZ60: 2 | BA60: 9 | BB60: 6 | BC60: 9 | BD60: 9 | BE60: 0 | BF60: 8 | BG60: 10 | BH60: 7 | BI60: 7 | BJ60: 1 | BK60: -1 | BL60: -1 | BM60: 1 | BN60: 12 | BO60: 1 | BP60: 4 | BQ60: 6 | BR60: 5 | BS60: 7 | BT60: 6
B61: Utilities | D61: =SUM(S61:X61) -> 53 | K61: 11 | L61: 6 | M61: -2 | N61: 4 | O61: -1 | P61: 0 | Q61: -6 | R61: -9 | S61: 9 | T61: 1 | U61: 12 | V61: 14 | W61: 6 | X61: 11 | Y61: 1 | Z61: 2 | AA61: 9 | AB61: 10 | AC61: 13 | AD61: 11 | AE61: 13 | AF61: 7 | AG61: 8 | AH61: 9 | AI61: 12 | AJ61: 10 | AK61: 4 | AL61: 4 | AM61: 5 | AN61: 9 | AO61: 9 | AP61: 7 | AQ61: 8 | AR61: 8 | AS61: 10 | AT61: 7 | AU61: 8 | AV61: 0 | AW61: 5 | AX61: 11 | AY61: 9 | AZ61: 4 | BA61: 8 | BB61: 8 | BC61: 6 | BD61: 7 | BE61: 2 | BF61: 12 | BG61: 2 | BH61: 4 | BI61: 4 | BJ61: 8 | BK61: 4 | BL61: 6 | BM61: 8 | BN61: 5 | BO61: 5 | BP61: 2 | BQ61: 0 | BR61: 2 | BS61: 1 | BT61: 1
B62: Wholesale Trade | D62: =SUM(S62:X62) -> 47 | K62: -1 | L62: -2 | M62: -6 | N62: -2 | O62: 3 | P62: -2 | Q62: -8 | R62: -4 | S62: 12 | T62: 10 | U62: 8 | V62: 10 | W62: 3 | X62: 4 | Y62: 4 | Z62: 7 | AA62: 12 | AB62: 13 | AC62: 16 | AD62: 16 | AE62: 12 | AF62: 15 | AG62: 11 | AH62: 7 | AI62: 8 | AJ62: 12 | AK62: 12 | AL62: 0 | AM62: 9 | AN62: 11 | AO62: 3 | AP62: 4 | AQ62: 6 | AR62: 3 | AS62: 6 | AT62: 10 | AU62: 2 | AV62: 1 | AW62: -2 | AX62: 1 | AY62: -1 | AZ62: -1 | BA62: 6 | BB62: 0 | BC62: 10 | BD62: 6 | BE62: 3 | BF62: 2 | BG62: 6 | BH62: 0 | BI62: 0 | BJ62: 4 | BK62: 10 | BL62: 4 | BM62: 9 | BN62: 6 | BO62: -1 | BP62: -2 | BQ62: 0 | BR62: -1 | BS62: 0 | BT62: 5
A64: Average | J64: =AVERAGE(J65:J82) -> #DIV/0! | K64: =AVERAGE(K65:K82) -> 1.8888889 | L64: =AVERAGE(L65:L82) -> 3.7777778 | M64: =AVERAGE(M65:M82) -> 1.8888889 | N64: =AVERAGE(N65:N82) -> 2.5 | O64: =AVERAGE(O65:O82) -> 7.5 | P64: =AVERAGE(P65:P82) -> -1.6666667 | Q64: =AVERAGE(Q65:Q82) -> -7.3888889 | ... CE64: =AVERAGE(CE65:CE82) -> 3.5
A65: NEW ORDERS | B65: Accommodation & Food Services | D65: =SUM(S65:X65) -> 44 | K65: 8 | L65: 4 | M65: 5 | N65: 8 | O65: 16 | P65: 3 | Q65: -2 | R65: -5 | S65: 14 | T65: 0 | U65: 9 | V65: 5 | W65: 12 | X65: 4 | Y65: -2 | Z65: -2 | AA65: 10 | AB65: 13 | AC65: 1 | AD65: 3 | AE65: 10 | AF65: 10 | AG65: 12 | AH65: 3 | AI65: 9 | AJ65: 3 | AK65: 12 | AL65: -3 | AM65: -3 | AN65: 5 | AO65: 10 | AP65: 5 | AQ65: 13 | AR65: -4 | AS65: 0 | AT65: 0 | AU65: 7 | AV65: 9 | AW65: 0 | AX65: 10 | AY65: 5 | AZ65: 12 | BA65: 14 | BB65: 11 | BC65: 13 | BD65: 12 | BE65: 12 | BF65: -2 | BG65: 5 | BH65: 0 | BI65: 8 | BJ65: 0 | BK65: 11 | BL65: 8 | BM65: 12 | BN65: 0 | BO65: -5 | BP65: 8 | BQ65: -3 | BR65: 8 | BS65: 12 | BT65: 12 | BU65: 0 | BV65: 10 | BW65: -3 | BX65: 6 | BY65: 8 | BZ65: 6 | CA65: 0 | CB65: -7 | CC65: -1 | CD65: 9 | CE65: 12
B66: Agriculture, Forestry, Fishing & Hunting | D66: =SUM(S66:X66) -> 17 | K66: 9 | L66: -4 | M66: 0 | N66: 10 | O66: 9 | P66: 0 | Q66: -15 | R66: 1 | S66: 15 | T66: 0 | U66: -4 | V66: -2 | W66: 8 | X66: 0 | Y66: -3 | Z66: 6 | AA66: 0 | AB66: 6 | AC66: -1 | AD66: 5 | AE66: -1 | AF66: 0 | AG66: 0 | AH66: -1 | AI66: 0 | AJ66: 10 | AK66: -2 | AL66: 0 | AM66: 0 | AN66: -2 | AO66: 0 | AP66: -2 | AQ66: 0 | AR66: -5 | AS66: -1 | AT66: 4 | AU66: 9 | AV66: 8 | AW66: 0 | AX66: 11 | AY66: 13 | AZ66: 5 | BA66: 0 | BB66: 0 | BC66: -3 | BD66: -1 | BE66: -3 | BF66: -4 | BG66: -3 | BH66: 11 | BI66: 9 | BJ66: 8 | BK66: 0 | BL66: 7 | BM66: 11 | BN66: 0 | BO66: -6 | BP66: -6 | BQ66: -5 | BR66: -2 | BS66: -3 | BT66: 6 | BU66: 0 | BV66: 9 | BW66: 0 | BX66: 0 | BY66: 0 | BZ66: 0 | CA66: -4 | CB66: -4 | CC66: 0 | CD66: -4 | CE66: 8
B67: Arts, Entertainment & Recreation | D67: =SUM(S67:X67) -> 43 | K67: 0 | L67: 0 | M67: 8 | N67: 0 | O67: -1 | P67: -8 | Q67: -16 | R67: -9 | S67: 11 | T67: 9 | U67: 12 | V67: 14 | W67: 0 | X67: -3 | Y67: -5 | Z67: -3 | AA67: 0 | AB67: 17 | AC67: 17 | AD67: 11 | AE67: 16 | AF67: 16 | AG67: -3 | AH67: 16 | AI67: 8 | AJ67: 9 | AK67: 8 | AL67: -4 | AM67: -2 | AN67: 15 | AO67: 0 | AP67: 14 | AQ67: 9 | AR67: 0 | AS67: 0 | AT67: -2 | AU67: 0 | AV67: 0 | AW67: -7 | AX67: 0 | AY67: 0 | AZ67: 11 | BA67: 16 | BB67: 0 | BC67: 12 | BD67: -3 | BE67: 8 | BF67: -3 | BG67: 10 | BH67: 0 | BI67: -5 | BJ67: -3 | BK67: -1 | BL67: 0 | BM67: 0 | BN67: -3 | BO67: -4 | BP67: 10 | BQ67: 8 | BR67: 0 | BS67: 0 | BT67: 13 | BU67: 7 | BV67: 0 | BW67: 8 | BX67: 0 | BY67: 0 | BZ67: 5 | CA67: 0 | CB67: -5 | CC67: 11 | CD67: 0 | CE67: -5
B68: Construction | D68: =SUM(S68:X68) -> 34 | K68: 0 | L68: 2 | M68: -3 | N68: 2 | O68: 12 | P68: 1 | Q68: -7 | R68: -8 | S68: 7 | T68: 5 | U68: 1 | V68: 0 | W68: 14 | X68: 7 | Y68: 3 | Z68: 4 | AA68: 9 | AB68: 3 | AC68: 7 | AD68: 13 | AE68: 1 | AF68: 1 | AG68: 9 | AH68: 8 | AI68: 5 | AJ68: 15 | AK68: 13 | AL68: 9 | AM68: 10 | AN68: 7 | AO68: 5 | AP68: 15 | AQ68: -2 | AR68: 3 | AS68: 0 | AT68: 0 | AU68: 5 | AV68: 3 | AW68: -2 | AX68: 0 | AY68: 12 | AZ68: 7 | BA68: 1 | BB68: 4 | BC68: 4 | BD68: 8 | BE68: -2 | BF68: 1 | BG68: -2 | BH68: 3 | BI68: -2 | BJ68: 0 | BK68: 8 | BL68: 2 | BM68: 9 | BN68: 1 | BO68: 5 | BP68: 7 | BQ68: -4 | BR68: 1 | BS68: 4 | BT68: 0 | BU68: -3 | BV68: 2 | BW68: 10 | BX68: 0 | BY68: -3 | BZ68: -1 | CA68: -1 | CB68: -6 | CC68: -2 | CD68: -5 | CE68: -4
B69: Educational Services | D69: =SUM(S69:X69) -> 37 | K69: -5 | L69: 0 | M69: -6 | N69: 3 | O69: 4 | P69: -6 | Q69: -9 | R69: -12 | S69: 0 | T69: 8 | U69: 7 | V69: 9 | W69: 10 | X69: 3 | Y69: 0 | Z69: -1 | AA69: 3 | AB69: 1 | AC69: 6 | AD69: 7 | AE69: 3 | AF69: 4 | AG69: 10 | AH69: 13 | AI69: 4 | AJ69: 1 | AK69: -1 | AL69: 1 | AM69: 9 | AN69: 14 | AO69: 9 | AP69: 13 | AQ69: -1 | AR69: 9 | AS69: 12 | AT69: 10 | AU69: 2 | AV69: -1 | AW69: -4 | AX69: 7 | AY69: 7 | AZ69: 6 | BA69: 9 | BB69: 8 | BC69: 11 | BD69: 7 | BE69: 7 | BF69: 5 | BG69: 9 | BH69: 2 | BI69: -3 | BJ69: 4 | BK69: 1 | BL69: 5 | BM69: 3 | BN69: 8 | BO69: -3 | BP69: 1 | BQ69: 4 | BR69: 7 | BS69: 3 | BT69: -1 | BU69: -4 | BV69: 8 | BW69: -1 | BX69: -1 | BY69: 5 | BZ69: 3 | CA69: 1 | CB69: -3 | CC69: 12 | CD69: 3 | CE69: 1
B70: Finance & Insurance | D70: =SUM(S70:X70) -> 28 | K70: 1 | L70: 7 | M70: 7 | N70: 6 | O70: 10 | P70: 0 | Q70: 1 | R70: 0 | S70: 2 | T70: 2 | U70: 4 | V70: 2 | W70: 9 | X70: 9 | Y70: 5 | Z70: 7 | AA70: 2 | AB70: 4 | AC70: 4 | AD70: 16 | AE70: 5 | AF70: 5 | AG70: 5 | AH70: 3 | AI70: 3 | AJ70: 5 | AK70: 4 | AL70: 3 | AM70: 5 | AN70: 3 | AO70: 1 | AP70: 4 | AQ70: 3 | AR70: 0 | AS70: 2 | AT70: 2 | AU70: 4 | AV70: 0 | AW70: 0 | AX70: 2 | AY70: 4 | AZ70: -2 | BA70: 8 | BB70: 1 | BC70: 6 | BD70: 1 | BE70: 2 | BF70: 4 | BG70: 11 | BH70: 6 | BI70: 3 | BJ70: 1 | BK70: 7 | BL70: 3 | BM70: 5 | BN70: 6 | BO70: 0 | BP70: 4 | BQ70: 5 | BR70: 6 | BS70: 11 | BT70: 3 | BU70: 6 | BV70: 7 | BW70: 9 | BX70: 5 | BY70: -2 | BZ70: 0 | CA70: 7 | CB70: 5 | CC70: 4 | CD70: 2 | CE70: -2
B71: Health Care & Social Assistance | D71: =SUM(S71:X71) -> 63 | K71: 5 | L71: 10 | M71: 6 | N71: 5 | O71: 5 | P71: 4 | Q71: -1 | R71: -3 | S71: 10 | T71: 11 | U71: 8 | V71: 11 | W71: 13 | X71: 10 | Y71: 8 | Z71: 0 | AA71: 1 | AB71: 10 | AC71: 5 | AD71: 12 | AE71: 7 | AF71: 9 | AG71: 6 | AH71: 5 | AI71: 7 | AJ71: 12 | AK71: 5 | AL71: 7 | AM71: 0 | AN71: -1 | AO71: 3 | AP71: 2 | AQ71: 5 | AR71: 1 | AS71: 4 | AT71: 5 | AU71: 1 | AV71: 4 | AW71: 4 | AX71: 1 | AY71: 1 | AZ71: 1 | BA71: 12 | BB71: 0 | BC71: 2 | BD71: 2 | BE71: -1 | BF71: 7 | BG71: 3 | BH71: 7 | BI71: 6 | BJ71: 6 | BK71: 6 | BL71: 1 | BM71: 1 | BN71: 5 | BO71: 1 | BP71: -1 | BQ71: 1 | BR71: 3 | BS71: -1 | BT71: 5 | BU71: 2 | BV71: 4 | BW71: 6 | BX71: 1 | BY71: 1 | BZ71: 0 | CA71: 0 | CB71: -1 | CC71: 5 | CD71: 7 | CE71: 5
B72: Information | D72: =SUM(S72:X72) -> 3 | K72: 2 | L72: 9 | M72: 4 | N72: 0 | O72: 2 | P72: -1 | Q72: -5 | R72: 0 | S72: 4 | T72: 0 | U72: -2 | V72: 1 | W72: 1 | X72: -1 | Y72: 4 | Z72: 2 | AA72: 0 | AB72: 2 | AC72: 2 | AD72: 10 | AE72: 6 | AF72: 3 | AG72: 13 | AH72: 4 | AI72: 11 | AJ72: 2 | AK72: 0 | AL72: -2 | AM72: -1 | AN72: 6 | AO72: -1 | AP72: -1 | AQ72: 0 | AR72: -2 | AS72: 10 | AT72: 8 | AU72: 12 | AV72: -2 | AW72: -5 | AX72: -3 | AY72: -2 | AZ72: 8 | BA72: 2 | BB72: 0 | BC72: -1 | BD72: 6 | BE72: 4 | BF72: 10 | BG72: 1 | BH72: -2 | BI72: 0 | BJ72: -4 | BK72: 12 | BL72: 0 | BM72: -2 | BN72: 2 | BO72: -1 | BP72: -4 | BQ72: 6 | BR72: 4 | BS72: 10 | BT72: 9 | BU72: -2 | BV72: -2 | BW72: 0 | BX72: 2 | BY72: 3 | BZ72: 1 | CA72: 0 | CB72: 0 | CC72: 10 | CD72: 5 | CE72: 3
B73: Management of Companies & Support Services | D73: =SUM(S73:X73) -> 44 | K73: 4 | L73: 5 | M73: 9 | N73: 9 | O73: 14 | P73: -2 | Q73: -3 | R73: -11 | S73: 3 | T73: 4 | U73: 6 | V73: 8 | W73: 11 | X73: 12 | Y73: 10 | Z73: 0 | AA73: 5 | AB73: 15 | AC73: 15 | AD73: 9 | AE73: 15 | AF73: 14 | AG73: 0 | AH73: 7 | AI73: 10 | AJ73: 16 | AK73: 9 | AL73: 6 | AM73: 11 | AN73: 12 | AO73: 12 | AP73: 11 | AQ73: 11 | AR73: 4 | AS73: 3 | AT73: 0 | AU73: 0 | AV73: -4 | AW73: 3 | AX73: 5 | AY73: 3 | AZ73: 2 | BA73: 3 | BB73: 10 | BC73: 7 | BD73: 10 | BE73: 0 | BF73: -1 | BG73: 0 | BH73: 4 | BI73: 4 | BJ73: 0 | BK73: 10 | BL73: 0 | BM73: 0 | BN73: 0 | BO73: 3 | BP73: 5 | BQ73: 0 | BR73: 10 | BS73: 5 | BT73: 11 | BU73: 0 | BV73: -1 | BW73: -4 | BX73: -2 | BY73: -4 | BZ73: -6 | CA73: 0 | CB73: 2 | CC73: 6 | CD73: -2 | CE73: -3
B74: Mining | D74: =SUM(S74:X74) -> 15 | K74: -1 | L74: -3 | M74: -1 | N74: 0 | O74: 13 | P74: -3 | Q74: -13 | R74: -14 | S74: 0 | T74: -2 | U74: -5 | V74: 4 | W74: 7 | X74: 11 | Y74: 0 | Z74: 0 | AA74: 0 | AB74: 16 | AC74: 8 | AD74: 14 | AE74: 9 | AF74: -1 | AG74: 7 | AH74: 11 | AI74: 0 | AJ74: 13 | AK74: -3 | AL74: 0 | AM74: 7 | AN74: 9 | AO74: 0 | AP74: 12 | AQ74: 12 | AR74: 10 | AS74: 11 | AT74: 13 | AU74: 13 | AV74: 7 | AW74: 0 | AX74: -2 | AY74: -3 | AZ74: 4 | BA74: -1 | BB74: 0 | BC74: -4 | BD74: -2 | BE74: 0 | BF74: 9 | BG74: 0 | BH74: 0 | BI74: -4 | BJ74: -5 | BK74: 0 | BL74: -2 | BM74: 8 | BN74: 0 | BO74: 0 | BP74: 9 | BQ74: 0 | BR74: 0 | BS74: 0 | BT74: -3 | BU74: 0 | BW74: 11 | BX74: 0 | BY74: 0 | BZ74: -7 | CA74: -3 | CB74: 0 | CC74: 0 | CD74: 0 | CE74: 0
B75: Other Services | D75: =SUM(S75:X75) -> 9 | K75: -6 | L75: -2 | M75: -2 | N75: -2 | O75: 6 | P75: -9 | Q75: -8 | R75: -13 | S75: -1 | T75: 0 | U75: 0 | V75: 7 | W75: 5 | X75: -2 | Y75: -1 | Z75: 0 | AA75: -1 | AB75: 0 | AC75: 14 | AD75: 8 | AE75: 13 | AF75: 12 | AG75: 8 | AH75: 15 | AI75: 14 | AJ75: 8 | AK75: 7 | AL75: 0 | AM75: 0 | AN75: 8 | AO75: 2 | AP75: 3 | AQ75: 10 | AR75: 6 | AS75: 0 | AT75: 12 | AU75: 11 | AV75: 11 | AW75: -6 | AX75: 8 | AY75: 11 | AZ75: 10 | BA75: 15 | BB75: 9 | BC75: 5 | BD75: 13 | BE75: 11 | BF75: 8 | BG75: 8 | BH75: 0 | BI75: 5 | BJ75: 0 | BK75: 0 | BL75: 6 | BM75: -3 | BN75: 10 | BO75: 0 | BP75: 0 | BQ75: 7 | BR75: -3 | BS75: 8 | BT75: 0 | BU75: 0 | BV75: -4 | BW75: 7 | BX75: 0 | BY75: 0 | BZ75: -4 | CA75: 8 | CB75: 3 | CC75: 0 | CD75: 8 | CE75: 7
B76: Professional, Scientific & Technical Services | D76: =SUM(S76:X76) -> 17 | K76: 3 | L76: 3 | M76: 2 | N76: -1 | O76: 3 | P76: -5 | Q76: -10 | R76: -7 | S76: 5 | T76: -1 | U76: -1 | V76: 0 | W76: 6 | X76: 8 | Y76: 1 | Z76: 1 | AA76: 6 | AB76: 9 | AC76: 3 | AD76: 2 | AE76: 2 | AF76: 2 | AG76: 1 | AH76: 12 | AI76: 2 | AJ76: 4 | AK76: 3 | AL76: 4 | AM76: 2 | AN76: 4 | AO76: 7 | AP76: 8 | AQ76: 2 | AR76: 2 | AS76: 1 | AT76: 3 | AU76: 6 | AV76: 2 | AW76: -1 | AX76: 3 | AY76: 9 | AZ76: 3 | BA76: 5 | BB76: 7 | BC76: 3 | BD76: 4 | BE76: 0 | BF76: 0 | BG76: -1 | BH76: -1 | BI76: -1 | BJ76: 7 | BK76: 3 | BL76: 11 | BM76: -1 | BN76: -1 | BO76: 0 | BP76: -2 | BQ76: -2 | BR76: 0 | BS76: 1 | BT76: 4 | BU76: -1 | BV76: -3 | BW76: 1 | BX76: -4 | BY76: -5 | BZ76: 0 | CA76: 6 | CB76: 0 | CC76: 2 | CD76: -1 | CE76: 4
B77: Public Administration | D77: =SUM(S77:X77) -> 20 | K77: -2 | L77: 1 | M77: -5 | N77: 7 | O77: 8 | P77: 2 | Q77: 2 | R77: -1 | S77: 1 | T77: 6 | U77: 10 | V77: 3 | W77: -1 | X77: 1 | Y77: 2 | Z77: 0 | AA77: 8 | AB77: 11 | AC77: 11 | AD77: 1 | AE77: 4 | AF77: 11 | AG77: 4 | AH77: 9 | AI77: 1 | AJ77: 11 | AK77: 1 | AL77: 8 | AM77: 4 | AN77: 2 | AO77: 6 | AP77: 1 | AQ77: 1 | AR77: 8 | AS77: 7 | AT77: 7 | AU77: 0 | AV77: 6 | AW77: 0 | AX77: 6 | AY77: 10 | AZ77: 9 | BA77: 11 | BB77: 2 | BC77: 10 | BD77: 9 | BE77: 5 | BF77: 6 | BG77: 7 | BH77: 5 | BI77: 0 | BJ77: 3 | BK77: 9 | BL77: -1 | BM77: 2 | BN77: 3 | BO77: -2 | BP77: 6 | BQ77: 3 | BR77: 9 | BS77: 6 | BT77: 10 | BU77: 3 | BV77: 3 | BW77: 3 | BX77: 4 | BY77: -1 | BZ77: 4 | CA77: 2 | CB77: 4 | CC77: 3 | CD77: 6 | CE77: -1
B78: Real Estate, Rental & Leasing | D78: =SUM(S78:X78) -> 30 | K78: 7 | L78: 12 | M78: 0 | N78: -4 | O78: 15 | P78: 5 | Q78: -6 | R78: 0 | S78: 13 | T78: 7 | U78: -3 | V78: 13 | W78: 0 | X78: 0 | Y78: -4 | Z78: 8 | AA78: -2 | AB78: 5 | AC78: 10 | AD78: 4 | AE78: 0 | AF78: 13 | AG78: -2 | AH78: 14 | AI78: 13 | AJ78: 7 | AK78: 0 | AL78: 0 | AM78: 0 | AN78: 11 | AO78: 11 | AP78: 10 | AQ78: 7 | AR78: 11 | AS78: 8 | AT78: 9 | AU78: -2 | AV78: 12 | AW78: -8 | AX78: 4 | AY78: 14 | AZ78: -4 | BA78: 10 | BB78: 0 | BC78: 0 | BD78: 0 | BE78: 10 | BF78: 0 | BG78: -4 | BH78: 10 | BI78: -6 | BJ78: -2 | BK78: 0 | BL78: 0 | BM78: 6 | BN78: 0 | BO78: 0 | BP78: -5 | BQ78: 0 | BR78: 11 | BS78: 0 | BT78: -2 | BU78: -6 | BV78: -5 | BW78: 0 | BX78: -3 | BY78: 4 | BZ78: -5 | CA78: -2 | CB78: -2 | CC78: 1 | CD78: -6 | CE78: 9
B79: Retail Trade | D79: =SUM(S79:X79) -> 33 | K79: -4 | L79: 11 | M79: 10 | N79: -3 | O79: 0 | P79: -7 | Q79: -14 | R79: -2 | S79: 9 | T79: 12 | U79: 3 | V79: -1 | W79: 4 | X79: 6 | Y79: 9 | Z79: 0 | AA79: 0 | AB79: 8 | AC79: 12 | AD79: 18 | AE79: 11 | AF79: 7 | AG79: 11 | AH79: 17 | AI79: 16 | AJ79: 17 | AK79: 6 | AL79: 10 | AM79: 1 | AN79: 0 | AO79: 0 | AP79: 0 | AQ79: 0 | AR79: -3 | AS79: 5 | AT79: 11 | AU79: 8 | AV79: 10 | AW79: 2 | AX79: 0 | AY79: 6 | AZ79: -3 | BA79: 13 | BB79: 5 | BC79: -2 | BD79: 0 | BE79: 9 | BF79: 12 | BG79: 12 | BH79: 9 | BI79: 2 | BJ79: -6 | BK79: 13 | BL79: 9 | BM79: 4 | BN79: -2 | BO79: -7 | BP79: 0 | BQ79: 0 | BR79: 5 | BS79: 7 | BT79: 7 | BU79: 4 | BV79: 1 | BW79: -2 | BX79: 3 | BY79: 2 | BZ79: -2 | CA79: 0 | CB79: 0 | CC79: 8 | CD79: -3 | CE79: 11
B80: Transportation & Warehousing | D80: =SUM(S80:X80) -> 45 | K80: 6 | L80: 8 | M80: 3 | N80: 0 | O80: 11 | P80: 0 | Q80: -4 | R80: -4 | S80: 6 | T80: 3 | U80: 2 | V80: 6 | W80: 15 | X80: 13 | Y80: 7 | Z80: 3 | AA80: 7 | AB80: 7 | AC80: 9 | AD80: 15 | AE80: 14 | AF80: 6 | AG80: 2 | AH80: 10 | AI80: 15 | AJ80: 18 | AK80: 10 | AL80: 2 | AM80: 6 | AN80: 1 | AO80: 8 | AP80: 6 | AQ80: 8 | AR80: 7 | AS80: 0 | AT80: -1 | AU80: 10 | AV80: 5 | AW80: 5 | AX80: -4 | AY80: 2 | AZ80: 0 | BA80: 6 | BB80: 3 | BC80: 8 | BD80: 11 | BE80: 6 | BF80: 11 | BG80: 6 | BH80: 8 | BI80: 7 | BJ80: -1 | BK80: 4 | BL80: 0 | BM80: 0 | BN80: 4 | BO80: 0 | BP80: 3 | BQ80: 2 | BR80: 2 | BS80: 9 | BT80: 2 | BU80: 5 | BV80: 5 | BW80: 2 | BX80: 9 | BY80: 6 | BZ80: 0 | CA80: 5 | CB80: 6 | CC80: 9 | CD80: 0 | CE80: 6
B81: Utilities | D81: =SUM(S81:X81) -> 39 | K81: 10 | L81: 6 | M81: 1 | N81: 4 | O81: 1 | P81: 0 | Q81: -12 | R81: -10 | S81: 8 | T81: 1 | U81: 11 | V81: 12 | W81: 2 | X81: 5 | Y81: 0 | Z81: 0 | AA81: 4 | AB81: 12 | AC81: 13 | AD81: 6 | AE81: 8 | AF81: 8 | AG81: 3 | AH81: 6 | AI81: 12 | AJ81: 6 | AK81: 2 | AL81: 5 | AM81: 8 | AN81: 10 | AO81: 13 | AP81: 9 | AQ81: 6 | AR81: 5 | AS81: 9 | AT81: 1 | AU81: 3 | AV81: 1 | AW81: 1 | AX81: 9 | AY81: 8 | AZ81: 0 | BA81: 4 | BB81: 6 | BC81: 1 | BD81: 3 | BE81: 3 | BF81: 3 | BG81: 4 | BH81: 1 | BI81: 1 | BJ81: 5 | BK81: 5 | BL81: 4 | BM81: 7 | BN81: 7 | BO81: 4 | BP81: 2 | BQ81: -1 | BR81: 0 | BS81: 2 | BT81: 1 | BU81: 1 | BV81: 0 | BW81: 4 | BX81: 7 | BY81: 0 | BZ81: 2 | CA81: 3 | CB81: 1 | CC81: 7 | CD81: 1 | CE81: 2
B82: Wholesale Trade | D82: =SUM(S82:X82) -> 42 | K82: -3 | L82: -1 | M82: -4 | N82: 1 | O82: 7 | P82: -4 | Q82: -11 | R82: -6 | S82: 12 | T82: 10 | U82: 5 | V82: 10 | W82: 3 | X82: 2 | Y82: 6 | Z82: 5 | AA82: 11 | AB82: 14 | AC82: 16 | AD82: 17 | AE82: 12 | AF82: 15 | AG82: -1 | AH82: 1 | AI82: 6 | AJ82: 14 | AK82: 11 | AL82: -1 | AM82: 3 | AN82: 13 | AO82: 4 | AP82: 7 | AQ82: 4 | AR82: -1 | AS82: 6 | AT82: 6 | AU82: -1 | AV82: -3 | AW82: -3 | AX82: -1 | AY82: -1 | AZ82: -1 | BA82: 7 | BB82: -1 | BC82: 9 | BD82: 5 | BE82: 1 | BF82: 2 | BG82: 2 | BH82: 0 | BI82: 0 | BJ82: 2 | BK82: 2 | BL82: 10 | BM82: 10 | BN82: 9 | BO82: 2 | BP82: -3 | BQ82: 0 | BR82: -1 | BS82: -2 | BT82: 8 | BU82: 0 | BV82: 6 | BW82: 5 | BX82: 8 | BY82: 7 | BZ82: -3 | CA82: 4 | CB82: 7 | CC82: 13 | CD82: 4 | CE82: 10
A84: EMPLOYMENT | B84: Accommodation & Food Services | K84: 4 | L84: 6
B85: Agriculture, Forestry, Fishing & Hunting | K85: 9 | L85: 11
B86: Arts, Entertainment & Recreation | K86: 0 | L86: 13
B87: Construction | K87: 2 | L87: -1
B88: Educational Services | K88: 0 | L88: 0
B89: Finance & Insurance | K89: 0 | L89: 7
B90: Health Care & Social Assistance | K90: 1 | L90: 9
B91: Information | K91: -2 | L91: -4
B92: Management of Companies & Support Services | K92: 6 | L92: 1
B93: Mining | K93: -4 | L93: -3
B94: Other Services | K94: -1 | L94: 10
B95: Professional, Scientific & Technical Services | K95: 10 | L95: 2
B96: Public Administration | K96: 7 | L96: 3
... B101: Wholesale Trade | K101: 3 | L101: -2
A103: SUPPLIER DELIVERABLES | B103: Accommodation & Food Services | K103: -8 | L103: -7
B104: Agriculture, Forestry, Fishing & Hunting | K104: 0 | L104: 3
B105: Arts, Entertainment & Recreation | K105: 0 | L105: 0
B106: Construction | K106: 1 | L106: 0
B107: Educational Services | K107: 0 | L107: 0
B108: Finance & Insurance | K108: 0 | L108: 0
B109: Health Care & Social Assistance | K109: -1 | L109: -2
B110: Information | K110: 0 | L110: -9
B111: Management of Companies & Support Services | K111: -3 | L111: -5
B112: Mining | K112: 2 | L112: -8
B113: Other Services | K113: -5 | L113: 0
B114: Professional, Scientific & Technical Services | K114: -2 | L114: -1
B115: Public Administration | K115: 0 | L115: -4
... B120: Wholesale Trade | K120: -4 | L120: -3
A122: INVENTORIES | B122: Accommodation & Food Services | K122: 3 | L122: 2
...

Sheet serv_pmi
A1: dates | B1: Accommodation & Food Services_pmi | C1: Agriculture, Forestry, Fishing & Hunting_pmi | D1: Arts, Entertainment & Recreation_pmi | E1: Construction_pmi | F1: Educational Services_pmi | G1: Finance & Insurance_pmi | H1: Health Care & Social Assistance_pmi | I1: Information_pmi | J1: Management of Companies & Support Services_pmi | K1: Mining_pmi | L1: Other Services_pmi | M1: Professional, Scientific & Technical Services_pmi | N1: Public Administration_pmi | O1: Real Estate, Rental & Leasing_pmi | P1: Retail Trade_pmi | Q1: Transportation & Warehousing_pmi | R1: Utilities_pmi | S1: Wholesale Trade_pmi
A2: 43831 | B2: 7 | C2: 12 | D2: -3 | E2: 4 | F2: 9 | G2: 6 | H2: 10 | I2: 2 | J2: 11 | K2: -2 | L2: -4 | M2: 1 | N2: 3 | O2: -1 | P2: 5 | Q2: -6 | R2: 8 | S2: -5
A3: 43862 | B3: 16 | C3: -1 | D3: -2 | E3: 10 | F3: 5 | G3: 13 | H3: 9 | I3: 2 | J3: 15 | K3: 14 | L3: 11 | M3: 4 | N3: 8 | O3: 12 | P3: 1 | Q3: 6 | R3: 3 | S3: 7
A4: 43891 | B4: 0 | C4: 0 | D4: -7 | E4: 4 | F4: -1 | G4: 5 | H4: 9 | I4: 1 | J4: 3 | K4: -4 | L4: -3 | M4: -5 | N4: 7 | O4: 8 | P4: -2 | Q4: -6 | R4: 6 | S4: 2
A5: 43922 | B5: -6 | C5: -15 | D5: -16 | E5: -11 | F5: -4 | G5: 1 | H5: -1 | I5: -7 | J5: -5 | K5: -9 | L5: -13 | M5: -8 | N5: 2 | O5: -3 | P5: -14 | Q5: -10 | R5: -2 | S5: -12
A6: 43952 | B6: -6 | C6: 4 | D6: -13 | E6: -11 | F6: -10 | G6: 3 | H6: -2 | I6: 1 | J6: -5 | K6: -14 | L6: -12 | M6: -9 | N6: 2 | O6: -4 | P6: -1 | Q6: -3 | R6: -8 | S6: -7
A7: 43983 | B7: 13 | C7: 14 | D7: 5 | E7: 9 | F7: 0 | G7: 3 | H7: 10 | I7: 4 | J7: -1 | K7: -3 | L7: -2 | M7: 1 | N7: 2 | O7: 11 | P7: 8 | Q7: 6 | R7: 7 | S7: 12
A8: 44013 | B8: 2 | C8: 3 | D8: 15 | E8: 9 | F8: 10 | G8: 6 | H8: 14 | I8: 1 | J8: 5 | K8: -2 | L8: -3 | M8: -1 | N8: 7 | O8: 4 | P8: 13 | Q8: 12 | R8: 8 | S8: 11
A9: 44044 | B9: 12 | C9: 3 | D9: 15 | E9: 9 | F9: 4 | G9: 5 | H9: 14 | I9: -2 | J9: 7 | K9: -3 | L9: -1 | M9: 1 | N9: 6 | O9: 2 | P9: 8 | Q9: 11 | R9: 13 | S9: 10
A10: 44094 | B10: 9 | C10: 5 | D10: 16 | E10: 8 | F10: 6 | G10: 4 | H10: 12 | I10: 2 | J10: 14 | K10: 0 | L10: 1 | M10: -1 | N10: 7 | O10: 10 | P10: 3 | Q10: 13 | R10: 15 | S10: 11
A11: 44105 | B11: 14 | C11: 12 | D11: -2 | E11: 15 | F11: 11 | G11: 10 | H11: 13 | I11: 2 | J11: 9 | K11: 7 | L11: 1 | M11: 6 | N11: -1 | O11: 3 | P11: 4 | Q11: 16 | R11: 5 | S11: 8
A12: 44136 | B12: 10 | C12: 4 | D12: -4 | E12: 9 | F12: -1 | G12: 5 | H12: 12 | I12: 1 | J12: 13 | K12: 3 | L12: -3 | M12: 6 | N12: 2 | O12: -2 | P12: 8 | Q12: 14 | R12: 11 | S12: 7
A13: 44166 | B13: -3 | C13: 7 | D13: -4 | E13: 2 | F13: 1 | G13: 9 | H13: 11 | I13: 6 | J13: 14 | K13: 4 | L13: -2 | M13: 5 | N13: 3 | O13: -1 | P13: 12 | Q13: 10 | R13: 8 | S13: 13
... A71: 45931 | B71: 11 | C71: 4 | D71: -6 | E71: -2 | F71: 1 | G71: -4 | H71: 7 | I71: 3 | J71: -5 | K71: 0 | L71: -1 | M71: 2 | N71: -3 | O71: 8 | P71: 10 | Q71: 5 | R71: 6 | S71: 9

Sheet serv_rank
A1: dates | B1: Accommodation & Food Services_rnk | C1: Agriculture, Forestry, Fishing & Hunting_rnk | D1: Arts, Entertainment & Recreation_rnk | E1: Construction_rnk | F1: Educational Services_rnk | G1: Finance & Insurance_rnk | H1: Health Care & Social Assistance_rnk | I1: Information_rnk | J1: Management of Companies & Support Services_rnk | K1: Mining_rnk | L1: Other Services_rnk | M1: Professional, Scientific & Technical Services_rnk | N1: Public Administration_rnk | O1: Real Estate, Rental & Leasing_rnk | P1: Retail Trade_rnk | Q1: Transportation & Warehousing_rnk | R1: Utilities_rnk | S1: Wholesale Trade_rnk
A2: 43831 | B2: =_xlfn.RANK.AVG(serv_pmi!B2,serv_pmi!$B2:$S2,1) -> 13 | C2: =_xlfn.RANK.AVG(serv_pmi!C2,serv_pmi!$B2:$S2,1) -> 18 | D2: =_xlfn.RANK.AVG(serv_pmi!D2,serv_pmi!$B2:$S2,1) -> 4 | E2: =_xlfn.RANK.AVG(serv_pmi!E2,serv_pmi!$B2:$S2,1) -> 10 | F2: =_xlfn.RANK.AVG(serv_pmi!F2,serv_pmi!$B2:$S2,1) -> 15 | G2: =_xlfn.RANK.AVG(serv_pmi!G2,serv_pmi!$B2:$S2,1) -> 12 | H2: =_xlfn.RANK.AVG(serv_pmi!H2,serv_pmi!$B2:$S2,1) -> 16 | I2: =_xlfn.RANK.AVG(serv_pmi!I2,serv_pmi!$B2:$S2,1) -> 8 | ... S2: =_xlfn.RANK.AVG(serv_pmi!S2,serv_pmi!$B2:$S2,1) -> 2
A3: 43862 | B3: =_xlfn.RANK.AVG(serv_pmi!B3,serv_pmi!$B3:$S3,1) -> 18 | C3: =_xlfn.RANK.AVG(serv_pmi!C3,serv_pmi!$B3:$S3,1) -> 2 | D3: =_xlfn.RANK.AVG(serv_pmi!D3,serv_pmi!$B3:$S3,1) -> 1 | E3: =_xlfn.RANK.AVG(serv_pmi!E3,serv_pmi!$B3:$S3,1) -> 12 | F3: =_xlfn.RANK.AVG(serv_pmi!F3,serv_pmi!$B3:$S3,1) -> 7 | G3: =_xlfn.RANK.AVG(serv_pmi!G3,serv_pmi!$B3:$S3,1) -> 15 | H3: =_xlfn.RANK.AVG(serv_pmi!H3,serv_pmi!$B3:$S3,1) -> 11 | I3: =_xlfn.RANK.AVG(serv_pmi!I3,serv_pmi!$B3:$S3,1) -> 4 | ... S3: =_xlfn.RANK.AVG(serv_pmi!S3,serv_pmi!$B3:$S3,1) -> 9
A4: 43891 | B4: =_xlfn.RANK.AVG(serv_pmi!B4,serv_pmi!$B4:$S4,1) -> 8.5 | C4: =_xlfn.RANK.AVG(serv_pmi!C4,serv_pmi!$B4:$S4,1) -> 8.5 | D4: =_xlfn.RANK.AVG(serv_pmi!D4,serv_pmi!$B4:$S4,1) -> 1 | E4: =_xlfn.RANK.AVG(serv_pmi!E4,serv_pmi!$B4:$S4,1) -> 13 | F4: =_xlfn.RANK.AVG(serv_pmi!F4,serv_pmi!$B4:$S4,1) -> 7 | G4: =_xlfn.RANK.AVG(serv_pmi!G4,serv_pmi!$B4:$S4,1) -> 14 | H4: =_xlfn.RANK.AVG(serv_pmi!H4,serv_pmi!$B4:$S4,1) -> 18 | I4: =_xlfn.RANK.AVG(serv_pmi!I4,serv_pmi!$B4:$S4,1) -> 10 | ... S4: =_xlfn.RANK.AVG(serv_pmi!S4,serv_pmi!$B4:$S4,1) -> 11
A5: 43922 | B5: =_xlfn.RANK.AVG(serv_pmi!B5,serv_pmi!$B5:$S5,1) -> 11 | C5: =_xlfn.RANK.AVG(serv_pmi!C5,serv_pmi!$B5:$S5,1) -> 2 | D5: =_xlfn.RANK.AVG(serv_pmi!D5,serv_pmi!$B5:$S5,1) -> 1 | E5: =_xlfn.RANK.AVG(serv_pmi!E5,serv_pmi!$B5:$S5,1) -> 6 | F5: =_xlfn.RANK.AVG(serv_pmi!F5,serv_pmi!$B5:$S5,1) -> 13 | G5: =_xlfn.RANK.AVG(serv_pmi!G5,serv_pmi!$B5:$S5,1) -> 17 | H5: =_xlfn.RANK.AVG(serv_pmi!H5,serv_pmi!$B5:$S5,1) -> 16 | I5: =_xlfn.RANK.AVG(serv_pmi!I5,serv_pmi!$B5:$S5,1) -> 10 | ... S5: =_xlfn.RANK.AVG(serv_pmi!S5,serv_pmi!$B5:$S5,1) -> 5
A6: 43952 | B6: =_xlfn.RANK.AVG(serv_pmi!B6,serv_pmi!$B6:$S6,1) -> 9 | C6: =_xlfn.RANK.AVG(serv_pmi!C6,serv_pmi!$B6:$S6,1) -> 18 | D6: =_xlfn.RANK.AVG(serv_pmi!D6,serv_pmi!$B6:$S6,1) -> 2 | E6: =_xlfn.RANK.AVG(serv_pmi!E6,serv_pmi!$B6:$S6,1) -> 4 | F6: =_xlfn.RANK.AVG(serv_pmi!F6,serv_pmi!$B6:$S6,1) -> 5 | G6: =_xlfn.RANK.AVG(serv_pmi!G6,serv_pmi!$B6:$S6,1) -> 17 | H6: =_xlfn.RANK.AVG(serv_pmi!H6,serv_pmi!$B6:$S6,1) -> 13 | I6: =_xlfn.RANK.AVG(serv_pmi!I6,serv_pmi!$B6:$S6,1) -> 15 | ... S6: =_xlfn.RANK.AVG(serv_pmi!S6,serv_pmi!$B6:$S6,1) -> 8
A7: 43983 | B7: =_xlfn.RANK.AVG(serv_pmi!B7,serv_pmi!$B7:$S7,1) -> 17 | C7: =_xlfn.RANK.AVG(serv_pmi!C7,serv_pmi!$B7:$S7,1) -> 18 | D7: =_xlfn.RANK.AVG(serv_pmi!D7,serv_pmi!$B7:$S7,1) -> 9 | E7: =_xlfn.RANK.AVG(serv_pmi!E7,serv_pmi!$B7:$S7,1) -> 13 | F7: =_xlfn.RANK.AVG(serv_pmi!F7,serv_pmi!$B7:$S7,1) -> 4 | G7: =_xlfn.RANK.AVG(serv_pmi!G7,serv_pmi!$B7:$S7,1) -> 7 | H7: =_xlfn.RANK.AVG(serv_pmi!H7,serv_pmi!$B7:$S7,1) -> 14 | I7: =_xlfn.RANK.AVG(serv_pmi!I7,serv_pmi!$B7:$S7,1) -> 8 | ... S7: =_xlfn.RANK.AVG(serv_pmi!S7,serv_pmi!$B7:$S7,1) -> 16
A8: 44013 | B8: =_xlfn.RANK.AVG(serv_pmi!B8,serv_pmi!$B8:$S8,1) -> 5 | C8: =_xlfn.RANK.AVG(serv_pmi!C8,serv_pmi!$B8:$S8,1) -> 6 | D8: =_xlfn.RANK.AVG(serv_pmi!D8,serv_pmi!$B8:$S8,1) -> 18 | E8: =_xlfn.RANK.AVG(serv_pmi!E8,serv_pmi!$B8:$S8,1) -> 12 | F8: =_xlfn.RANK.AVG(serv_pmi!F8,serv_pmi!$B8:$S8,1) -> 13 | G8: =_xlfn.RANK.AVG(serv_pmi!G8,serv_pmi!$B8:$S8,1) -> 9 | H8: =_xlfn.RANK.AVG(serv_pmi!H8,serv_pmi!$B8:$S8,1) -> 17 | I8: =_xlfn.RANK.AVG(serv_pmi!I8,serv_pmi!$B8:$S8,1) -> 4 | ... S8: =_xlfn.RANK.AVG(serv_pmi!S8,serv_pmi!$B8:$S8,1) -> 14
A9: 44044 | B9: =_xlfn.RANK.AVG(serv_pmi!B9,serv_pmi!$B9:$S9,1) -> 15 | C9: =_xlfn.RANK.AVG(serv_pmi!C9,serv_pmi!$B9:$S9,1) -> 6 | D9: =_xlfn.RANK.AVG(serv_pmi!D9,serv_pmi!$B9:$S9,1) -> 18 | E9: =_xlfn.RANK.AVG(serv_pmi!E9,serv_pmi!$B9:$S9,1) -> 12 | F9: =_xlfn.RANK.AVG(serv_pmi!F9,serv_pmi!$B9:$S9,1) -> 7 | G9: =_xlfn.RANK.AVG(serv_pmi!G9,serv_pmi!$B9:$S9,1) -> 8 | H9: =_xlfn.RANK.AVG(serv_pmi!H9,serv_pmi!$B9:$S9,1) -> 17 | I9: =_xlfn.RANK.AVG(serv_pmi!I9,serv_pmi!$B9:$S9,1) -> 2 | ... S9: =_xlfn.RANK.AVG(serv_pmi!S9,serv_pmi!$B9:$S9,1) -> 13
A10: 44094 | B10: =_xlfn.RANK.AVG(serv_pmi!B10,serv_pmi!$B10:$S10,1) -> 11 | C10: =_xlfn.RANK.AVG(serv_pmi!C10,serv_pmi!$B10:$S10,1) -> 7 | D10: =_xlfn.RANK.AVG(serv_pmi!D10,serv_pmi!$B10:$S10,1) -> 18 | E10: =_xlfn.RANK.AVG(serv_pmi!E10,serv_pmi!$B10:$S10,1) -> 10 | F10: =_xlfn.RANK.AVG(serv_pmi!F10,serv_pmi!$B10:$S10,1) -> 8 | G10: =_xlfn.RANK.AVG(serv_pmi!G10,serv_pmi!$B10:$S10,1) -> 6 | H10: =_xlfn.RANK.AVG(serv_pmi!H10,serv_pmi!$B10:$S10,1) -> 14 | I10: =_xlfn.RANK.AVG(serv_pmi!I10,serv_pmi!$B10:$S10,1) -> 4 | ... S10: =_xlfn.RANK.AVG(serv_pmi!S10,serv_pmi!$B10:$S10,1) -> 13
A11: 44105 | B11: =_xlfn.RANK.AVG(serv_pmi!B11,serv_pmi!$B11:$S11,1) -> 16 | C11: =_xlfn.RANK.AVG(serv_pmi!C11,serv_pmi!$B11:$S11,1) -> 14 | D11: =_xlfn.RANK.AVG(serv_pmi!D11,serv_pmi!$B11:$S11,1) -> 1 | E11: =_xlfn.RANK.AVG(serv_pmi!E11,serv_pmi!$B11:$S11,1) -> 17 | F11: =_xlfn.RANK.AVG(serv_pmi!F11,serv_pmi!$B11:$S11,1) -> 13 | G11: =_xlfn.RANK.AVG(serv_pmi!G11,serv_pmi!$B11:$S11,1) -> 12 | H11: =_xlfn.RANK.AVG(serv_pmi!H11,serv_pmi!$B11:$S11,1) -> 15 | I11: =_xlfn.RANK.AVG(serv_pmi!I11,serv_pmi!$B11:$S11,1) -> 4 | ... S11: =_xlfn.RANK.AVG(serv_pmi!S11,serv_pmi!$B11:$S11,1) -> 10
A12: 44136 | B12: =_xlfn.RANK.AVG(serv_pmi!B12,serv_pmi!$B12:$S12,1) -> 14 | C12: =_xlfn.RANK.AVG(serv_pmi!C12,serv_pmi!$B12:$S12,1) -> 8 | D12: =_xlfn.RANK.AVG(serv_pmi!D12,serv_pmi!$B12:$S12,1) -> 1 | E12: =_xlfn.RANK.AVG(serv_pmi!E12,serv_pmi!$B12:$S12,1) -> 13 | F12: =_xlfn.RANK.AVG(serv_pmi!F12,serv_pmi!$B12:$S12,1) -> 4 | G12: =_xlfn.RANK.AVG(serv_pmi!G12,serv_pmi!$B12:$S12,1) -> 9 | H12: =_xlfn.RANK.AVG(serv_pmi!H12,serv_pmi!$B12:$S12,1) -> 16 | I12: =_xlfn.RANK.AVG(serv_pmi!I12,serv_pmi!$B12:$S12,1) -> 5 | ... S12: =_xlfn.RANK.AVG(serv_pmi!S12,serv_pmi!$B12:$S12,1) -> 11
A13: 44166 | B13: =_xlfn.RANK.AVG(serv_pmi!B13,serv_pmi!$B13:$S13,1) -> 2 | C13: =_xlfn.RANK.AVG(serv_pmi!C13,serv_pmi!$B13:$S13,1) -> 11 | D13: =_xlfn.RANK.AVG(serv_pmi!D13,serv_pmi!$B13:$S13,1) -> 1 | E13: =_xlfn.RANK.AVG(serv_pmi!E13,serv_pmi!$B13:$S13,1) -> 6 | F13: =_xlfn.RANK.AVG(serv_pmi!F13,serv_pmi!$B13:$S13,1) -> 5 | G13: =_xlfn.RANK.AVG(serv_pmi!G13,serv_pmi!$B13:$S13,1) -> 13 | H13: =_xlfn.RANK.AVG(serv_pmi!H13,serv_pmi!$B13:$S13,1) -> 15 | I13: =_xlfn.RANK.AVG(serv_pmi!I13,serv_pmi!$B13:$S13,1) -> 10 | ... S13: =_xlfn.RANK.AVG(serv_pmi!S13,serv_pmi!$B13:$S13,1) -> 17
... A36: 44866 | B36: =_xlfn.RANK.AVG(serv_pmi!B36,serv_pmi!$B36:$S36,1) -> 9 | C36: =_xlfn.RANK.AVG(serv_pmi!C36,serv_pmi!$B36:$S36,1) -> 16 | D36: =_xlfn.RANK.AVG(serv_pmi!D36,serv_pmi!$B36:$S36,1) -> 4.5 | E36: =_xlfn.RANK.AVG(serv_pmi!E36,serv_pmi!$B36:$S36,1) -> 14 | F36: =_xlfn.RANK.AVG(serv_pmi!F36,serv_pmi!$B36:$S36,1) -> 6 | G36: =_xlfn.RANK.AVG(serv_pmi!G36,serv_pmi!$B36:$S36,1) -> 4.5 | H36: =_xlfn.RANK.AVG(serv_pmi!H36,serv_pmi!$B36:$S36,1) -> 13 | I36: =_xlfn.RANK.AVG(serv_pmi!I36,serv_pmi!$B36:$S36,1) -> 3 | ... S36: =_xlfn.RANK.AVG(serv_pmi!S36,serv_pmi!$B36:$S36,1) -> 2
A37: 44896 | B37: 12 | C37: 7 | D37: 14 | E37: 5 | F37: 6 | G37: 8 | H37: 17 | I37: 4 | J37: 10 | K37: 13 | L37: 3 | M37: 9 | N37: 15 | O37: 1 | P37: 18 | Q37: 11 | R37: 16 | S37: 2
A38: 44927 | B38: 12 | C38: 18 | D38: 3 | E38: 5 | F38: 13 | G38: 7 | H38: 10 | I38: 6 | J38: 15 | K38: 4 | L38: 16 | M38: 9 | N38: 14 | O38: 11 | P38: 2 | Q38: 1 | R38: 17 | S38: 8
A39: 44958 | B39: 6 | C39: 18 | D39: 9 | E39: 16 | F39: 11 | G39: 10 | H39: 7 | I39: 3 | J39: 4 | K39: 5 | L39: 12 | M39: 15 | N39: 17 | O39: 8 | P39: 14 | Q39: 2 | R39: 13 | S39: 1
A40: 44986 | B40: 15 | C40: 10 | D40: 17 | E40: 7 | F40: 16 | G40: 1 | H40: 8 | I40: 6 | J40: 11.5 | K40: 13 | L40: 18 | M40: 11.5 | N40: 14 | O40: 3 | P40: 5 | Q40: 4 | R40: 9 | S40: 2
A41: 45017 | B41: 15 | C41: 2 | D41: 18 | E41: 7 | F41: 10 | G41: 6 | H41: 9 | I41: 5 | J41: 4 | K41: 1 | L41: 17 | M41: 11 | N41: 13 | O41: 16 | P41: 8 | Q41: 12 | R41: 14 | S41: 3
A42: 45047 | B42: 18 | C42: 2 | D42: 13 | E42: 12 | F42: 8 | G42: 7 | H42: 6 | I42: 5 | J42: 17 | K42: 1 | L42: 11 | M42: 16 | N42: 9 | O42: 3 | P42: 14 | Q42: 10 | R42: 15 | S42: 4
A43: 45078 | B43: 18 | C43: 1 | D43: 17 | E43: 7 | F43: 14 | G43: 6 | H43: 4 | I43: 3 | J43: 13 | K43: 2 | L43: 10 | M43: 8 | N43: 15 | O43: 16 | P43: 5 | Q43: 12 | R43: 9 | S43: 11
A44: 45108 | B44: 16 | C44: 2 | D44: 3 | E44: 17 | F44: 8 | G44: 4 | H44: 9 | I44: 6 | J44: 14 | K44: 1 | L44: 18 | M44: 10 | N44: 15 | O44: 11 | P44: 7 | Q44: 13 | R44: 12 | S44: 5
A45: 45139 | B45: 17 | C45: 1 | D45: 15 | E45: 9 | F45: 10 | G45: 8 | H45: 4 | I45: 11 | J45: 5 | K45: 2 | L45: 16 | M45: 6 | N45: 12 | O45: 18 | P45: 13 | Q45: 7 | R45: 14 | S45: 3
A46: 45170 | B46: 3 | C46: 1 | D46: 2 | E46: 11 | F46: 6 | G46: 12 | H46: 13 | I46: 8 | J46: 4 | K46: 16 | L46: 15 | M46: 10 | N46: 9 | O46: 18 | P46: 17 | Q46: 7 | R46: 14 | S46: 5
A47: 45200 | B47: 6 | C47: 2 | D47: 18 | E47: 15 | F47: 10 | G47: 14 | H47: 9 | I47: 7 | J47: 8 | K47: 3 | L47: 16 | M47: 5 | N47: 13 | O47: 1 | P47: 17 | Q47: 12 | R47: 11 | S47: 4
A48: 45231 | B48: 11 | C48: 18 | D48: 15 | E48: 6 | F48: 4 | G48: 8 | H48: 17 | I48: 1 | J48: 9 | K48: 2 | L48: 10 | M48: 3 | N48: 7 | O48: 16 | P48: 13 | Q48: 14 | R48: 12 | S48: 5
... A71: 45931 | B71: 18 | C71: 11 | D71: 1 | E71: 5 | F71: 8 | G71: 3 | H71: 14 | I71: 10 | J71: 2 | K71: 7 | L71: 6 | M71: 9 | N71: 4 | O71: 15 | P71: 17 | Q71: 12 | R71: 13 | S71: 16

Sheet serv_rank_pct
A1: dates | B1: Accommodation & Food Services_rnk | C1: Agriculture, Forestry, Fishing & Hunting_rnk | D1: Arts, Entertainment & Recreation_rnk | E1: Construction_rnk | F1: Educational Services_rnk | G1: Finance & Insurance_rnk | H1: Health Care & Social Assistance_rnk | I1: Information_rnk | J1: Management of Companies & Support Services_rnk | K1: Mining_rnk | L1: Other Services_rnk | M1: Professional, Scientific & Technical Services_rnk | N1: Public Administration_rnk | O1: Real Estate, Rental & Leasing_rnk | P1: Retail Trade_rnk | Q1: Transportation & Warehousing_rnk | R1: Utilities_rnk | S1: Wholesale Trade_rnk
A2: 43831 | B2: =serv_rank!B2/171 -> 0.076023392 | C2: =serv_rank!C2/171 -> 0.10526316 | D2: =serv_rank!D2/171 -> 0.023391813 | E2: =serv_rank!E2/171 -> 0.058479532 | F2: =serv_rank!F2/171 -> 0.087719298 | G2: =serv_rank!G2/171 -> 0.070175439 | H2: =serv_rank!H2/171 -> 0.093567251 | I2: =serv_rank!I2/171 -> 0.046783626 | ... S2: =serv_rank!S2/171 -> 0.011695906
A3: 43862 | B3: =serv_rank!B3/171 -> 0.10526316 | C3: =serv_rank!C3/171 -> 0.011695906 | D3: =serv_rank!D3/171 -> 0.0058479532 | E3: =serv_rank!E3/171 -> 0.070175439 | F3: =serv_rank!F3/171 -> 0.040935673 | G3: =serv_rank!G3/171 -> 0.087719298 | H3: =serv_rank!H3/171 -> 0.064327485 | I3: =serv_rank!I3/171 -> 0.023391813 | ... S3: =serv_rank!S3/171 -> 0.052631579
A4: 43891 | B4: =serv_rank!B4/171 -> 0.049707602 | C4: =serv_rank!C4/171 -> 0.049707602 | D4: =serv_rank!D4/171 -> 0.0058479532 | E4: =serv_rank!E4/171 -> 0.076023392 | F4: =serv_rank!F4/171 -> 0.040935673 | G4: =serv_rank!G4/171 -> 0.081871345 | H4: =serv_rank!H4/171 -> 0.10526316 | I4: =serv_rank!I4/171 -> 0.058479532 | ... S4: =serv_rank!S4/171 -> 0.064327485
A5: 43922 | B5: =serv_rank!B5/171 -> 0.064327485 | C5: =serv_rank!C5/171 -> 0.011695906 | D5: =serv_rank!D5/171 -> 0.0058479532 | E5: =serv_rank!E5/171 -> 0.035087719 | F5: =serv_rank!F5/171 -> 0.076023392 | G5: =serv_rank!G5/171 -> 0.099415205 | H5: =serv_rank!H5/171 -> 0.093567251 | I5: =serv_rank!I5/171 -> 0.058479532 | ... S5: =serv_rank!S5/171 -> 0.029239766
A6: 43952 | B6: =serv_rank!B6/171 -> 0.052631579 | C6: =serv_rank!C6/171 -> 0.10526316 | D6: =serv_rank!D6/171 -> 0.011695906 | E6: =serv_rank!E6/171 -> 0.023391813 | F6: =serv_rank!F6/171 -> 0.029239766 | G6: =serv_rank!G6/171 -> 0.099415205 | H6: =serv_rank!H6/171 -> 0.076023392 | I6: =serv_rank!I6/171 -> 0.087719298 | ... S6: =serv_rank!S6/171 -> 0.046783626
A7: 43983 | B7: =serv_rank!B7/171 -> 0.099415205 | C7: =serv_rank!C7/171 -> 0.10526316 | D7: =serv_rank!D7/171 -> 0.052631579 | E7: =serv_rank!E7/171 -> 0.076023392 | F7: =serv_rank!F7/171 -> 0.023391813 | G7: =serv_rank!G7/171 -> 0.040935673 | H7: =serv_rank!H7/171 -> 0.081871345 | I7: =serv_rank!I7/171 -> 0.046783626 | ... S7: =serv_rank!S7/171 -> 0.093567251
A8: 44013 | B8: =serv_rank!B8/171 -> 0.029239766 | C8: =serv_rank!C8/171 -> 0.035087719 | D8: =serv_rank!D8/171 -> 0.10526316 | E8: =serv_rank!E8/171 -> 0.070175439 | F8: =serv_rank!F8/171 -> 0.076023392 | G8: =serv_rank!G8/171 -> 0.052631579 | H8: =serv_rank!H8/171 -> 0.099415205 | I8: =serv_rank!I8/171 -> 0.023391813 | ... S8: =serv_rank!S8/171 -> 0.081871345
A9: 44044 | B9: =serv_rank!B9/171 -> 0.087719298 | C9: =serv_rank!C9/171 -> 0.035087719 | D9: =serv_rank!D9/171 -> 0.10526316 | E9: =serv_rank!E9/171 -> 0.070175439 | F9: =serv_rank!F9/171 -> 0.040935673 | G9: =serv_rank!G9/171 -> 0.046783626 | H9: =serv_rank!H9/171 -> 0.099415205 | I9: =serv_rank!I9/171 -> 0.011695906 | ... S9: =serv_rank!S9/171 -> 0.076023392
A10: 44094 | B10: =serv_rank!B10/171 -> 0.064327485 | C10: =serv_rank!C10/171 -> 0.040935673 | D10: =serv_rank!D10/171 -> 0.10526316 | E10: =serv_rank!E10/171 -> 0.058479532 | F10: =serv_rank!F10/171 -> 0.046783626 | G10: =serv_rank!G10/171 -> 0.035087719 | H10: =serv_rank!H10/171 -> 0.081871345 | I10: =serv_rank!I10/171 -> 0.023391813 | ... S10: =serv_rank!S10/171 -> 0.076023392
A11: 44105 | B11: =serv_rank!B11/171 -> 0.093567251 | C11: =serv_rank!C11/171 -> 0.081871345 | D11: =serv_rank!D11/171 -> 0.0058479532 | E11: =serv_rank!E11/171 -> 0.099415205 | F11: =serv_rank!F11/171 -> 0.076023392 | G11: =serv_rank!G11/171 -> 0.070175439 | H11: =serv_rank!H11/171 -> 0.087719298 | I11: =serv_rank!I11/171 -> 0.023391813 | ... S11: =serv_rank!S11/171 -> 0.058479532
A12: 44136 | B12: =serv_rank!B12/171 -> 0.081871345 | C12: =serv_rank!C12/171 -> 0.046783626 | D12: =serv_rank!D12/171 -> 0.0058479532 | E12: =serv_rank!E12/171 -> 0.076023392 | F12: =serv_rank!F12/171 -> 0.023391813 | G12: =serv_rank!G12/171 -> 0.052631579 | H12: =serv_rank!H12/171 -> 0.093567251 | I12: =serv_rank!I12/171 -> 0.029239766 | ... S12: =serv_rank!S12/171 -> 0.064327485
A13: 44166 | B13: =serv_rank!B13/171 -> 0.011695906 | C13: =serv_rank!C13/171 -> 0.064327485 | D13: =serv_rank!D13/171 -> 0.0058479532 | E13: =serv_rank!E13/171 -> 0.035087719 | F13: =serv_rank!F13/171 -> 0.029239766 | G13: =serv_rank!G13/171 -> 0.076023392 | H13: =serv_rank!H13/171 -> 0.087719298 | I13: =serv_rank!I13/171 -> 0.058479532 | ... S13: =serv_rank!S13/171 -> 0.099415205
... A71: 45931 | B71: =serv_rank!B71/171 -> 0.10526316 | C71: =serv_rank!C71/171 -> 0.064327485 | D71: =serv_rank!D71/171 -> 0.0058479532 | E71: =serv_rank!E71/171 -> 0.029239766 | F71: =serv_rank!F71/171 -> 0.046783626 | G71: =serv_rank!G71/171 -> 0.01754386 | H71: =serv_rank!H71/171 -> 0.081871345 | I71: =serv_rank!I71/171 -> 0.058479532 | ... S71: =serv_rank!S71/171 -> 0.093567251

Sheet serv_no
A1: dates | B1: Accommodation & Food Services_no | C1: Agriculture, Forestry, Fishing & Hunting_no | D1: Arts, Entertainment & Recreation_no | E1: Construction_no | F1: Educational Services_no | G1: Finance & Insurance_no | H1: Health Care & Social Assistance_no | I1: Information_no | J1: Management of Companies & Support Services_no | K1: Mining_no | L1: Other Services_no | M1: Professional, Scientific & Technical Services_no | N1: Public Administration_no | O1: Real Estate, Rental & Leasing_no | P1: Retail Trade_no | Q1: Transportation & Warehousing_no | R1: Utilities_no | S1: Wholesale Trade_no
A2: 43831 | B2: 8 | C2: 10 | D2: 0 | E2: 2 | F2: 3 | G2: 6 | H2: 5 | I2: 0 | J2: 9 | K2: 0 | L2: -2 | M2: -1 | N2: 7 | O2: -4 | P2: -3 | Q2: 0 | R2: 4 | S2: 1
A3: 43862 | B3: 16 | C3: 9 | D3: -1 | E3: 12 | F3: 4 | G3: 10 | H3: 5 | I3: 2 | J3: 14 | K3: 13 | L3: 6 | M3: 3 | N3: 8 | O3: 15 | P3: 0 | Q3: 11 | R3: 1 | S3: 7
A4: 43891 | B4: 3 | C4: 0 | D4: -8 | E4: 1 | F4: -6 | G4: 0 | H4: 4 | I4: -1 | J4: -2 | K4: -3 | L4: -9 | M4: -5 | N4: 2 | O4: 5 | P4: -7 | Q4: 0 | R4: 0 | S4: -4
A5: 43922 | B5: -2 | C5: -15 | D5: -16 | E5: -7 | F5: -9 | G5: 1 | H5: -1 | I5: -5 | J5: -3 | K5: -13 | L5: -8 | M5: -10 | N5: 2 | O5: -6 | P5: -14 | Q5: -4 | R5: -12 | S5: -11
A6: 43952 | B6: -5 | C6: 1 | D6: -9 | E6: -8 | F6: -12 | G6: 0 | H6: -3 | I6: 0 | J6: -11 | K6: -14 | L6: -13 | M6: -7 | N6: -1 | O6: 0 | P6: -2 | Q6: -4 | R6: -10 | S6: -6
A7: 43983 | B7: 14 | C7: 15 | D7: 11 | E7: 7 | F7: 0 | G7: 2 | H7: 10 | I7: 4 | J7: 3 | K7: 0 | L7: -1 | M7: 5 | N7: 1 | O7: 13 | P7: 9 | Q7: 6 | R7: 8 | S7: 12
A8: 44013 | B8: 0 | C8: 0 | D8: 9 | E8: 5 | F8: 8 | G8: 2 | H8: 11 | I8: 0 | J8: 4 | K8: -2 | L8: 0 | M8: -1 | N8: 6 | O8: 7 | P8: 12 | Q8: 3 | R8: 1 | S8: 10
A9: 44044 | B9: 9 | C9: -4 | D9: 12 | E9: 1 | F9: 7 | G9: 4 | H9: 8 | I9: -2 | J9: 6 | K9: -5 | L9: 0 | M9: -1 | N9: 10 | O9: -3 | P9: 3 | Q9: 2 | R9: 11 | S9: 5
A10: 44094 | B10: 5 | C10: -2 | D10: 14 | E10: 0 | F10: 9 | G10: 2 | H10: 11 | I10: 1 | J10: 8 | K10: 4 | L10: 7 | M10: 0 | N10: 3 | O10: 13 | P10: -1 | Q10: 6 | R10: 12 | S10: 10
A11: 44105 | B11: 12 | C11: 8 | D11: 0 | E11: 14 | F11: 10 | G11: 9 | H11: 13 | I11: 1 | J11: 11 | K11: 7 | L11: 5 | M11: 6 | N11: -1 | O11: 0 | P11: 4 | Q11: 15 | R11: 2 | S11: 3
A12: 44136 | B12: 4 | C12: 0 | D12: -3 | E12: 7 | F12: 3 | G12: 9 | H12: 10 | I12: -1 | J12: 12 | K12: 11 | L12: -2 | M12: 8 | N12: 1 | O12: 0 | P12: 6 | Q12: 13 | R12: 5 | S12: 2
A13: 44166 | B13: -2 | C13: -3 | D13: -5 | E13: 3 | F13: 0 | G13: 5 | H13: 8 | I13: 4 | J13: 10 | K13: 0 | L13: -1 | M13: 1 | N13: 2 | O13: -4 | P13: 9 | Q13: 7 | R13: 0 | S13: 6
... A61: 45627 | B61: 0 | C61: 0 | D61: 7 | E61: -3 | F61: -4 | G61: 6 | H61: 2 | I61: -2 | J61: 0 | K61: 0 | L61: 0 | M61: -1 | N61: 3 | O61: -6 | P61: 4 | Q61: 5 | R61: 1 | S61: 0
A62: 45658 | B62: 10 | C62: 9 | D62: 0 | E62: 2 | F62: 8 | G62: 7 | H62: 4 | I62: -2 | J62: -1 | L62: -4 | M62: -3 | N62: 3 | O62: -5 | P62: 1 | Q62: 5 | R62: 0 | S62: 6
A63: 45689 | B63: -3 | C63: 0 | D63: 8 | E63: 10 | F63: -1 | G63: 9 | H63: 6 | I63: 0 | J63: -4 | K63: 11 | L63: 7 | M63: 1 | N63: 3 | O63: 0 | P63: -2 | Q63: 2 | R63: 4 | S63: 5
A64: 45717 | B64: 6 | C64: 0 | D64: 0 | E64: 0 | F64: -1 | G64: 5 | H64: 1 | I64: 2 | J64: -2 | K64: 0 | L64: 0 | M64: -4 | N64: 4 | O64: -3 | P64: 3 | Q64: 9 | R64: 7 | S64: 8
A65: 45748 | B65: 8 | C65: 0 | D65: 0 | E65: -3 | F65: 5 | G65: -2 | H65: 1 | I65: 3 | J65: -4 | K65: 0 | L65: 0 | M65: -5 | N65: -1 | O65: 4 | P65: 2 | Q65: 6 | R65: 0 | S65: 7
A66: 45778 | B66: 6 | C66: 0 | D66: 5 | E66: -1 | F66: 3 | G66: 0 | H66: 0 | I66: 1 | J66: -6 | K66: -7 | L66: -4 | M66: 0 | N66: 4 | O66: -5 | P66: -2 | Q66: 0 | R66: 2 | S66: -3
A67: 45809 | B67: 0 | C67: -4 | D67: 0 | E67: -1 | F67: 1 | G67: 7 | H67: 0 | I67: 0 | J67: 0 | K67: -3 | L67: 8 | M67: 6 | N67: 2 | O67: -2 | P67: 0 | Q67: 5 | R67: 3
A68: 45839 | B68: 0 | C68: -4 | D68: 0 | E68: -1 | F68: 1 | G68: 7 | H68: 0 | I68: 0 | J68: 0 | K68: -3 | L68: 8 | M68: 6 | N68: 2 | O68: -2 | P68: 0 | Q68: 5 | R68: 3
A69: 45870 | B69: -1 | C69: 0 | D69: 11 | E69: -2 | F69: 12 | G69: 4 | H69: 5 | I69: 10 | J69: 6 | K69: 0 | L69: 0 | M69: 2 | N69: 3 | O69: 1 | P69: 8 | Q69: 9 | R69: 7 | S69: 13
A70: 45901 | B70: 9 | C70: -4 | D70: 0 | E70: -5 | F70: 3 | G70: 2 | H70: 7 | I70: 5 | J70: -2 | K70: 0 | L70: 8 | M70: -1 | N70: 6 | O70: -6 | P70: -3 | Q70: 0 | R70: 1 | S70: 4
A71: 45931 | B71: 12 | C71: 8 | D71: -5 | E71: -4 | F71: 1 | G71: -2 | H71: 5 | I71: 3 | J71: -3 | K71: 0 | L71: 7 | M71: 4 | N71: -1 | O71: 9 | P71: 11 | Q71: 6 | R71: 2 | S71: 10

Sheet QUAL
B2: Date | C2: Group | D2: Position | E2: Sector | F2: Comments
B3: 45017 | C3: Manu | D3: -1 | E3: Chemical Products | F3: Business continues to contract, albeit slowly year over year. We are burning existing inventory when possible and catching up on orders. Suppliers are shipping materials at a faster pace, especially to get the payable process started at the end of the first quarter. Employment is steady, with manpower decisions based on expected order flow in the second quarter, which is subject to change. Staffing levels in our sector are not decreasing, but employment openings are slowing across the economy, which reduces the pool of replacement candidates. We are currently projecting that the third quarter will see some improvement in business, especially in our metals coating for the aerospace industry. But unforeseen circumstances — international or domestic — could change things quickly.
B4: 45017 | C4: Manu | D4: -1 | E4: Computer & Electronic Products | F4: Having invested heavily to de-risk the supply chain over the last three years due to COVID-19, we are looking to reset with a number of our suppliers to reduce inventory, which has grown steadily over that period. Lead times are generally coming down, although electronic components are still a concern
B5: 45017 | C5: Manu | D5: -1 | E5: Electrical Equipment, Appliances & Components | F5: Sales continue to be soft, similar to 2019 pre-COVID. Expect softness to last for as long as another two years
B6: 45017 | C6: Manu | D6: 1 | E6: Fabricated Metal Products | F6: Faster deliveries and shorter lead times from suppliers. … Customers starting to talk build rate reductions for the second half of 2023.
B7: 45017 | C7: Manu | D7: -1 | E7: Food, Beverage & Tobacco Products | F7: Pricing pressures continue to plague daily operations. After consecutive years of inflation and aggressive pricing to our retailers, we are starting to see resistance in the willingness to pass along pricing to end consumers. Discounting has entered into conversations
B8: 45017 | C8: Manu | D8: -1 | E8: Machinery | F8: Customers seem to be quite heavy on inventory (as is my employer). This has made for a significant slowdown in sales orders for the last number of months
B9: 45017 | C9: Manu | D9: -1 | E9: Miscellaneous Manufacturing | F9: Business conditions remain strong, with sales and bookings exceeding plan. The backlog continues to grow due to increased bookings and supply chain constraints on electronic components
B10: 45017 | C10: Manu | D10: -1 | E10: Plastics & Rubber Products | F10: Business is picking up a bit in the automotive and construction industries — not on par with 2022 but beginning to look better
B11: 45017 | C11: Manu | D11: 0 | E11: Primary Metals | F11: We seem to be in a season of contradictions. Business is slowing, but in some ways, it isn’t. Prices for some commodities are stabilizing, but not for others. Some product shortages are over, others aren’t. Trucking is more plentiful, except when it isn’t. There’s uncertainty one day, but not the next. The next couple of months should provide answers — or not. It’s hard to make projections at the moment.
B12: 45017 | C12: Manu | D12: 1 | E12: Transportation Equipment | F12: Business is steady. Closely monitoring demand going forward to detect a negative trend
B13: 45017 | C13: Serv | D13: 1 | E13: Accommodation & Food Services | F13: Lead times are improving. Suppliers are struggling with how to position themselves with pricing; those keeping prices higher despite a drop in input costs are at risk of losing their business to those that are willing to adjust prices in line with lower input costs
B14: 45017 | C14: Serv | D14: 1 | E14: Construction | F14: High mortgage rates continue to weigh on new residential construction. With demand down, material suppliers are curtailing production to maintain pricing levels. Labor continues to be constrained, but some negotiation room is developing as the slowdown drags on
... B438: 45627 | C438: Serv | D438: 1 | E438: Wholesale Trade | F438: Customers are slowing down, and they are cutting back their inventories in preparation for the end of the year, so our sales are slowing down
B439: 45292 | C439: Manu | E439: Chemical Products | F439: Customer orders slightly stronger than expected. Seeing more general price increases for chemicals/raw materials. No International Longshoremen’s Association strike is a tremendous help
B440: 45658 | C440: Manu | E440: Transportation Equipment | F440: Alleviating supply chain conditions are noticeably pivoting back into acute shortage situations, with headwinds following. For aerospace and defense companies, critical minerals supply chains are tightening dramatically due to Chinese restrictions. Concerns are growing of an environment of more supply chain shortages
B441: 45658 | C441: Manu | E441: Computer & Electronic Products | F441: As the U.S. administration transfers, we will continue to monitor impact of tariffs on materials used for manufacturing. China stimulus is helping us win orders and increase use of services and consumables. Cost pressures remain for all materials and parts but are starting to stabilize
B442: 45658 | C442: Manu | E442: Food, Beverage & Tobacco Products | F442: Volume in 2025 is targeting 2-percent growth. The organization is mindful of potential tariffs and what to do with re-routing or cost increases in supply chains that are impacted
B443: 45658 | C443: Manu | E443: Machinery | F443: Although we are in our busy season, our demand for the first two weeks of 2025 has outpaced normal levels for this period of time
B444: 45658 | C444: Manu | E444: Electrical Equipment, Appliances & Components | F444: Business is slowly improving
B445: 45658 | C445: Manu | E445: Fabricated Metal Products | F445: Capital equipment sales are starting 2025 off strong. Normally, we see a soft start to the year, so this strong start is unusual
B446: 45658 | C446: Manu | E446: Miscellaneous Manufacturing | F446: New orders are still good but decreasing compared to previous quarters. Working through current backlog
B447: 45658 | C447: Manu | E447: Primary Metals | F447: Automotive order demand continues to be consistent and on a steady pace. Beginning to look at hiring additional team members once again. Pricing is holding firm. Having to work overtime to cover plant inefficiency to date
B448: 45658 | C448: Manu | E448: Textile Mills | F448: Looking forward to a year of strong customer demand and higher sales than 2024
B449: 45658 | C449: Serv | E449: Construction | F449: Expecting considerable new projects to move to execution by second quarter in the energy market within the U.S.
B450: 45658 | C450: Serv | E450: Educational Services | F450: Business conditions seem to be stable for us at this time
... B639: 45931 | C639: Serv | E639: Wholesale Trade | F639: Business seems to be picking up. Multifamily is a big driver. I think most projects that have been postponed are finally coming to fruition as lumber prices have found a bottom. The outlook is better with the Fed’s plan to continue with rate cuts. Home prices coupled with elevated interest rates continue to keep a lid on sales. Home affordability is still a bit out of reach for a large portion of potential buyers

Sheet serv_biz_act
A1: dates | B1: Accommodation & Food Services_biza | C1: Agriculture, Forestry, Fishing & Hunting_biza | D1: Arts, Entertainment & Recreation_biza | E1: Construction_biza | F1: Educational Services_biza | G1: Finance & Insurance_biza | H1: Health Care & Social Assistance_biza | I1: Information_biza | J1: Management of Companies & Support Services_biza | K1: Mining_biza | L1: Other Services_biza | M1: Professional, Scientific & Technical Services_biza | N1: Public Administration_biza | O1: Real Estate, Rental & Leasing_biza | P1: Retail Trade_biza | Q1: Transportation & Warehousing_biza | R1: Utilities_biza | S1: Wholesale Trade_biza
A2: 43831 | B2: 5 | C2: 12 | D2: -3 | E2: 6 | F2: 2 | G2: 7 | H2: 10 | I2: 3 | J2: 11 | K2: -4 | L2: -1 | M2: 1 | N2: 8 | O2: 0 | P2: 0 | Q2: 9 | R2: 4 | S2: -2
A3: 43862 | B3: 13 | C3: 0 | D3: -3 | E3: 4 | F3: 5 | G3: 9 | H3: 6 | I3: -2 | J3: 12 | K3: 11 | L3: 1 | M3: 2 | N3: 8 | O3: 10 | P3: 0 | Q3: 7 | R3: -1 | S3: 3
A4: 43891 | B4: 4 | C4: 0 | D4: -9 | E4: 3 | F4: -6 | G4: 1 | H4: 5 | I4: -1 | J4: 0 | K4: -8 | L4: -7 | M4: -4 | N4: 2 | O4: 0 | P4: -5 | Q4: -3 | R4: 0 | S4: -2
A5: 43922 | B5: -2 | C5: -16 | D5: -17 | E5: -7 | F5: -10 | H5: -4 | I5: -3 | J5: -9 | K5: -5 | L5: -13 | M5: -11 | N5: -1 | O5: -12 | P5: -14 | Q5: -15 | R5: -6 | S5: -8
A6: 43952 | B6: -5 | C6: 3 | D6: -8 | E6: -11 | F6: -12 | G6: 2 | H6: -6 | I6: -1 | J6: -3 | K6: -13 | L6: -10 | M6: -7 | N6: 0 | O6: 0 | P6: 1 | Q6: -2 | R6: -9 | S6: -4
A7: 43983 | B7: 14 | C7: 15 | D7: 0 | E7: 8 | F7: 3 | G7: 5 | H7: 11 | I7: 2 | J7: 6 | K7: 0 | L7: -1 | M7: 4 | N7: 1 | O7: 13 | P7: 10 | Q7: 7 | R7: 9 | S7: 12
A8: 44013 | B8: 5 | C8: 6 | D8: 11 | E8: 4 | F8: 12 | G8: 2 | H8: 9 | I8: -1 | J8: 3 | K8: -3 | L8: -2 | M8: 0 | N8: 7 | O8: 8 | P8: 13 | Q8: 14 | R8: 1 | S8: 10
A9: 44044 | B9: 2 | C9: -3 | D9: 13 | E9: 6 | F9: 3 | G9: 4 | H9: 9 | I9: -2 | J9: 11 | K9: -1 | L9: 0 | M9: 0 | N9: 7 | O9: 10 | P9: 1 | Q9: 5 | R9: 12 | S9: 8
A10: 44094 | B10: 13 | C10: -1 | D10: 16 | E10: 4 | F10: 8 | G10: 7 | H10: 9 | I10: 3 | J10: 12 | K10: 5 | L10: 2 | M10: 1 | N10: 6 | O10: 15 | P10: 0 | Q10: 11 | R10: 14 | S10: 10
A11: 44105 | B11: 15 | C11: 12 | D11: 0 | E11: 10 | F11: 7 | G11: 8 | H11: 11 | I11: 2 | J11: 9 | K11: 14 | L11: 5 | M11: 4 | N11: -1 | O11: 13 | P11: 1 | Q11: 16 | R11: 6 | S11: 3
A12: 44136 | B12: 10 | C12: -1 | D12: -4 | E12: 5 | F12: 1 | G12: 9 | H12: 12 | I12: 2 | J12: 13 | K12: 6 | L12: -2 | M12: 8 | N12: 3 | O12: -3 | P12: 7 | Q12: 14 | R12: 11 | S12: 4
A13: 44166 | B13: -4 | C13: 6 | D13: 0 | E13: -2 | F13: -1 | G13: 3 | H13: 10 | I13: 8 | J13: 11 | K13: 5 | L13: -5 | M13: 2 | N13: 0 | O13: -3 | P13: 7 | Q13: 9 | R13: 1 | S13: 4
A14: 44197 | B14: 6 | C14: 0 | D14: 0 | E14: 10 | F14: -1 | G14: 9 | H14: 5 | I14: 1 | J14: 0 | K14: 0 | L14: 0 | M14: 4 | N14: 3 | O14: 8 | P14: -2 | Q14: 0 | R14: 2 | S14: 7
A15: 44228 | B15: 14 | C15: -2 | D15: 13 | E15: 6 | F15: 8 | G15: 4 | H15: 3 | I15: 2 | J15: 7 | K15: 5 | L15: -1 | M15: 1 | N15: 10 | O15: -3 | P15: 0 | Q15: 11 | R15: 9 | S15: 12
A16: 44256 | B16: 14 | C16: 12 | D16: 17 | E16: 5 | F16: 2 | G16: 9 | H16: 6 | I16: 4 | J16: 15 | K16: 16 | L16: -1 | M16: 1 | N16: 8 | O16: 11 | P16: 3 | Q16: 7 | R16: 10 | S16: 13
A17: 44287 | B17: 10 | C17: -1 | D17: 17 | E17: 8 | F17: 9 | G17: 7 | H17: 6 | I17: 2 | J17: 15 | K17: 12 | L17: 3 | M17: 4 | N17: 14 | O17: 1 | P17: 11 | Q17: 5 | R17: 13 | S17: 16
... A60: 45597 | B60: 13 | C60: 7 | D60: 14 | E60: 0 | F60: 2 | G60: 12 | H60: 9 | I60: 11 | J60: 4 | K60: 0 | L60: -1 | M60: 3 | N60: 8 | O60: -2 | P60: 10 | Q60: 6 | R60: 1 | S60: 5
A61: 45627
A62: 45658
A63: 45689
